spi_final/Synthesize/FINAL_I/spi_mosi.v
`timescale 1 ns / 1 ps
module spi_mosi (control_clk,spi_mosi_out,spi_cs,spi_clk,n_reset,spi_mosi_in);

  parameter DSIZE = 8;


    output  spi_mosi_out,control_clk;
    input spi_cs;
    input n_reset;
    input  spi_clk;
	input [DSIZE-1:0] spi_mosi_in;
    reg control_clk;

	reg spi_mosi_out;
    
	reg[3:0] point_add;
      reg[7:0] data ,add_byte;
 
      reg [2:0] point,control ;	


     


// control clock : control smooth transiction of Data from asy_fifo_to spi_mosi
	

always@(posedge spi_clk or negedge n_reset)
if(!n_reset) begin
                control<=3'b010;
               control_clk<=0;
			 end
else  begin
                         if(control==3'd7) begin
   				                                 control_clk<=~control_clk;
   				                                 control<=0;
   
					                       end
			             else
				                   begin
					                    control<=control+1;
				                   end
                    end
// data from asy fifo come to spi_mosi with the control clock

always@(posedge control_clk or negedge n_reset)
if(!n_reset) begin
              data<=8'd0;
             end
else begin
                    if(spi_cs) begin
               
                                  data<=8'd0;  // address
                 
            
               
                    	        end

	                else 
         	            begin
 		                      data<=spi_mosi_in;
               
              			end  
		        end



// spi clk manage data to send slave bit by bit
// every data byte also send e address byte by spi_mosi
// 
	
always@(posedge spi_clk or negedge n_reset)
if(! n_reset) begin
                    spi_mosi_out<=0;
                    add_byte<=01000110;   // address byte        
                    point_add<=4'd5;
	           	    point<=3'd0;
				end
else  begin
    
 	               	if(spi_cs ) begin
        		                   spi_mosi_out<=0;
                                   
                                   point<=3'd0;
		                           point_add<=4'd0;
            
               
                                end

	                else if(!spi_cs) begin
	                                    if(point_add==4'd8) begin
         
                                                                 if(point==3'd7) begin
          
                                                                                      point_add<=4'd0;
                                                                                      point<=3'b000;
		                                                                         end
	 
                   
               
         
	                                                              else if (control_clk==1) begin
                                                                                              spi_mosi_out<=data[point];
                                                                                               point<= point+1;
                                          	
                                                                                         end
	                                                          end
          

	
                                        else if(control_clk==0)begin
	                                        
	                                                               spi_mosi_out<=add_byte[point_add];	  // assign address byte
		                                                            point_add<= point_add+1; 

 //$display ("at time %0d spi_mosi_out=%b  ", $time, spi_mosi_out);
 //$display ("at time %0d point_add=%d  ", $time, point_add);

                                                                
					                                              end
	 
                                    end

                 end
   


		endmodule

spi_final/Synthesize/FINAL_I/spi_mosi_test.v
`timescale 1 ns / 1 ps



module spi_mosi_test;
  
 
reg n_reset;
reg [7:0] spi_mosi_in;
 reg  spi_clk,spi_cs;
 wire  control_clk;
 wire spi_mosi_out;

//`define stim #10 wdata=8'd
event end_first_pass;

	spi_mosi A(control_clk,spi_mosi_out,spi_cs,spi_clk,n_reset,spi_mosi_in);

	

initial begin
  $shm_open("spi_mosi.shm");
  $shm_probe("AS");
end

/*
initial begin
$dumpfile("spi_mosi_waveform_result.vcd");
$dumpvars(0,spi_mosi_test);
end
*/
initial
begin
    n_reset=0;
	#50
	n_reset=1;
	#100
	n_reset=0;
	#50
	n_reset=1;
    
     spi_clk=0;
     spi_cs=1;


end



always  #50 spi_clk= ~spi_clk;
always
begin
#50 ;
$display ("at time %0d spi_clk = %b   spi_cs= %b  control_clk=%b n_reset=%b spi_mosi_in=%b spi_mosi_out=%b  ", $time,      
   spi_clk,spi_cs,control_clk,n_reset,spi_mosi_in,spi_mosi_out);

end
initial
begin
#150 n_reset=0;

#150 n_reset=1;
 spi_mosi_in=8'd0;
 #250  
spi_cs=0;    
      spi_mosi_in=8'd1;
 
    #1500 spi_mosi_in =8'd2;
   
    #1500 spi_mosi_in =8'd3;
    #1500  spi_mosi_in =8'd4;
    #1500 spi_mosi_in=8'd5;
 
    #1500 spi_mosi_in =8'd6;
   
    #1500 spi_mosi_in =8'd7;
    #1500  spi_mosi_in =8'd8;
    #1500 spi_mosi_in=8'd9;
 
   #1500 spi_mosi_in =8'd10;
   
    #1500 spi_mosi_in =8'b01000111;
   #1500 spi_mosi_in =8'b01100001;
#1500 spi_mosi_in=8'd1;
 
    #1500 spi_mosi_in =8'b00100011;
   
   
	//#1700 spi_mosi_in=8'b11001010;
	
	
	
	
	#100000->end_first_pass;
   $finish;
   end


endmodule

spi_final/Synthesize/FINAL_I/spi_mosi_waveform_result.vcd
$date
    Jul 18, 2016  16:29:27
$end
$version
    Tool:	VERILOG-XL	08.20.001-d
$end
$timescale
     1ps
$end

$scope module spi_mosi_test $end
$var reg       1 !    n_reset  $end
$var reg       8 "    spi_mosi_in [7:0] $end
$var reg       1 #    spi_clk  $end
$var reg       1 $    spi_cs  $end
$var wire      1 %    control_clk  $end
$var wire      1 &    spi_mosi_out  $end
$var event     1 '    end_first_pass  $end

$scope module A $end
$var parameter 32 (    DSIZE  $end
$var wire      1 )    spi_cs  $end
$var wire      1 *    n_reset  $end
$var wire      1 +    spi_clk  $end
$var wire      8 ,    spi_mosi_in [7:0] $end
$var reg       1 -    control_clk  $end
$var reg       1 .    spi_mosi_out  $end
$var reg       4 /    point_add [3:0] $end
$var reg       8 0    data [7:0] $end
$var reg       8 1    add_byte [7:0] $end
$var reg       3 2    point [2:0] $end
$var reg       3 3    control [2:0] $end
$upscope $end

$upscope $end

$enddefinitions $end
$dumpvars
0!
bxxxxxxxx "
x#
x$
0%
0&
x'
b00000000000000000000000000001000 (
x)
0*
x+
bxxxxxxxx ,
0-
0.
b0101 /
b00000000 0
b10101110 1
b000 2
b010 3
$end
#50000
1!
1*
#150000
0!
0*
#200000
1!
0#
1$
1#
1*
1+
1)
b0000 /
b011 3
#250000
0#
0+
#300000
b00000000 "
1#
b00000000 ,
1+
b100 3
#350000
0#
0+
#400000
1#
1+
b101 3
#450000
0#
0+
#500000
1#
1+
b110 3
#550000
0$
b00000001 "
0#
0)
b00000001 ,
0+
#600000
1#
1+
b0001 /
b00000001 0
b111 3
#650000
0#
0+
#700000
1#
1+
1-
b000 3
1.
b0010 /
1%
1&
#750000
0#
0+
#800000
1#
1+
b001 3
#850000
0#
0+
#900000
1#
1+
b010 3
#950000
0#
0+
#1000000
1#
1+
b011 3
#1050000
0#
0+
#1100000
1#
1+
b100 3
#1150000
0#
0+
#1200000
1#
1+
b101 3
#1250000
0#
0+
#1300000
1#
1+
b110 3
#1350000
0#
0+
#1400000
1#
1+
b111 3
#1450000
0#
0+
#1500000
1#
1+
0-
b000 3
0%
#1550000
0#
0+
#1600000
1#
1+
b0011 /
b001 3
#1650000
0#
0+
#1700000
1#
1+
b010 3
b0100 /
#1750000
0#
0+
#1800000
1#
1+
0.
b0101 /
b011 3
0&
#1850000
0#
0+
#1900000
1#
1+
b100 3
1.
b0110 /
1&
#1950000
0#
0+
#2000000
1#
1+
0.
b0111 /
b101 3
0&
#2050000
b00000010 "
0#
b00000010 ,
0+
#2100000
1#
1+
b110 3
b00000010 0
1.
b1000 /
1&
#2150000
0#
0+
#2200000
1#
1+
b111 3
#2250000
0#
0+
#2300000
1#
1+
1-
b000 3
1%
#2350000
0#
0+
#2400000
1#
1+
0.
b001 2
b001 3
0&
#2450000
0#
0+
#2500000
1#
1+
b010 3
1.
b010 2
1&
#2550000
0#
0+
#2600000
1#
1+
0.
b011 2
b011 3
0&
#2650000
0#
0+
#2700000
1#
1+
b100 3
b100 2
#2750000
0#
0+
#2800000
1#
1+
b101 2
b101 3
#2850000
0#
0+
#2900000
1#
1+
b110 3
b110 2
#2950000
0#
0+
#3000000
1#
1+
b111 2
b111 3
#3050000
0#
0+
#3100000
1#
1+
0-
b000 3
b0000 /
b000 2
0%
#3150000
0#
0+
#3200000
1#
1+
b0001 /
b001 3
#3250000
0#
0+
#3300000
1#
1+
b010 3
1.
b0010 /
1&
#3350000
0#
0+
#3400000
1#
1+
b0011 /
b011 3
#3450000
0#
0+
#3500000
1#
1+
b100 3
b0100 /
#3550000
b00000011 "
0#
b00000011 ,
0+
#3600000
1#
1+
0.
b0101 /
b00000011 0
b101 3
0&
#3650000
0#
0+
#3700000
1#
1+
b110 3
1.
b0110 /
1&
#3750000
0#
0+
#3800000
1#
1+
0.
b0111 /
b111 3
0&
#3850000
0#
0+
#3900000
1#
1+
1-
b000 3
1.
b1000 /
1%
1&
#3950000
0#
0+
#4000000
1#
1+
b001 2
b001 3
#4050000
0#
0+
#4100000
1#
1+
b010 3
b010 2
#4150000
0#
0+
#4200000
1#
1+
0.
b011 2
b011 3
0&
#4250000
0#
0+
#4300000
1#
1+
b100 3
b100 2
#4350000
0#
0+
#4400000
1#
1+
b101 2
b101 3
#4450000
0#
0+
#4500000
1#
1+
b110 3
b110 2
#4550000
0#
0+
#4600000
1#
1+
b111 2
b111 3
#4650000
0#
0+
#4700000
1#
1+
0-
b000 3
b0000 /
b000 2
0%
#4750000
0#
0+
#4800000
1#
1+
b0001 /
b001 3
#4850000
0#
0+
#4900000
1#
1+
b010 3
1.
b0010 /
1&
#4950000
0#
0+
#5000000
1#
1+
b0011 /
b011 3
#5050000
b00000100 "
0#
b00000100 ,
0+
#5100000
1#
1+
b100 3
b00000100 0
b0100 /
#5150000
0#
0+
#5200000
1#
1+
0.
b0101 /
b101 3
0&
#5250000
0#
0+
#5300000
1#
1+
b110 3
1.
b0110 /
1&
#5350000
0#
0+
#5400000
1#
1+
0.
b0111 /
b111 3
0&
#5450000
0#
0+
#5500000
1#
1+
1-
b000 3
1.
b1000 /
1%
1&
#5550000
0#
0+
#5600000
1#
1+
0.
b001 2
b001 3
0&
#5650000
0#
0+
#5700000
1#
1+
b010 3
b010 2
#5750000
0#
0+
#5800000
1#
1+
1.
b011 2
b011 3
1&
#5850000
0#
0+
#5900000
1#
1+
b100 3
0.
b100 2
0&
#5950000
0#
0+
#6000000
1#
1+
b101 2
b101 3
#6050000
0#
0+
#6100000
1#
1+
b110 3
b110 2
#6150000
0#
0+
#6200000
1#
1+
b111 2
b111 3
#6250000
0#
0+
#6300000
1#
1+
0-
b000 3
b0000 /
b000 2
0%
#6350000
0#
0+
#6400000
1#
1+
b0001 /
b001 3
#6450000
0#
0+
#6500000
1#
1+
b010 3
1.
b0010 /
1&
#6550000
b00000101 "
0#
b00000101 ,
0+
#6600000
1#
1+
b0011 /
b00000101 0
b011 3
#6650000
0#
0+
#6700000
1#
1+
b100 3
b0100 /
#6750000
0#
0+
#6800000
1#
1+
0.
b0101 /
b101 3
0&
#6850000
0#
0+
#6900000
1#
1+
b110 3
1.
b0110 /
1&
#6950000
0#
0+
#7000000
1#
1+
0.
b0111 /
b111 3
0&
#7050000
0#
0+
#7100000
1#
1+
1-
b000 3
1.
b1000 /
1%
1&
#7150000
0#
0+
#7200000
1#
1+
b001 2
b001 3
#7250000
0#
0+
#7300000
1#
1+
b010 3
0.
b010 2
0&
#7350000
0#
0+
#7400000
1#
1+
1.
b011 2
b011 3
1&
#7450000
0#
0+
#7500000
1#
1+
b100 3
0.
b100 2
0&
#7550000
0#
0+
#7600000
1#
1+
b101 2
b101 3
#7650000
0#
0+
#7700000
1#
1+
b110 3
b110 2
#7750000
0#
0+
#7800000
1#
1+
b111 2
b111 3
#7850000
0#
0+
#7900000
1#
1+
0-
b000 3
b0000 /
b000 2
0%
#7950000
0#
0+
#8000000
1#
1+
b0001 /
b001 3
#8050000
b00000110 "
0#
b00000110 ,
0+
#8100000
1#
1+
b010 3
b00000110 0
1.
b0010 /
1&
#8150000
0#
0+
#8200000
1#
1+
b0011 /
b011 3
#8250000
0#
0+
#8300000
1#
1+
b100 3
b0100 /
#8350000
0#
0+
#8400000
1#
1+
0.
b0101 /
b101 3
0&
#8450000
0#
0+
#8500000
1#
1+
b110 3
1.
b0110 /
1&
#8550000
0#
0+
#8600000
1#
1+
0.
b0111 /
b111 3
0&
#8650000
0#
0+
#8700000
1#
1+
1-
b000 3
1.
b1000 /
1%
1&
#8750000
0#
0+
#8800000
1#
1+
0.
b001 2
b001 3
0&
#8850000
0#
0+
#8900000
1#
1+
b010 3
1.
b010 2
1&
#8950000
0#
0+
#9000000
1#
1+
b011 2
b011 3
#9050000
0#
0+
#9100000
1#
1+
b100 3
0.
b100 2
0&
#9150000
0#
0+
#9200000
1#
1+
b101 2
b101 3
#9250000
0#
0+
#9300000
1#
1+
b110 3
b110 2
#9350000
0#
0+
#9400000
1#
1+
b111 2
b111 3
#9450000
0#
0+
#9500000
1#
1+
0-
b000 3
b0000 /
b000 2
0%
#9550000
b00000111 "
0#
b00000111 ,
0+
#9600000
1#
1+
b0001 /
b00000111 0
b001 3
#9650000
0#
0+
#9700000
1#
1+
b010 3
1.
b0010 /
1&
#9750000
0#
0+
#9800000
1#
1+
b0011 /
b011 3
#9850000
0#
0+
#9900000
1#
1+
b100 3
b0100 /
#9950000
0#
0+
#10000000
1#
1+
0.
b0101 /
b101 3
0&
#10050000
0#
0+
#10100000
1#
1+
b110 3
1.
b0110 /
1&
#10150000
0#
0+
#10200000
1#
1+
0.
b0111 /
b111 3
0&
#10250000
0#
0+
#10300000
1#
1+
1-
b000 3
1.
b1000 /
1%
1&
#10350000
0#
0+
#10400000
1#
1+
b001 2
b001 3
#10450000
0#
0+
#10500000
1#
1+
b010 3
b010 2
#10550000
0#
0+
#10600000
1#
1+
b011 2
b011 3
#10650000
0#
0+
#10700000
1#
1+
b100 3
0.
b100 2
0&
#10750000
0#
0+
#10800000
1#
1+
b101 2
b101 3
#10850000
0#
0+
#10900000
1#
1+
b110 3
b110 2
#10950000
0#
0+
#11000000
1#
1+
b111 2
b111 3
#11050000
b00001000 "
0#
b00001000 ,
0+
#11100000
1#
1+
0-
b000 3
b00001000 0
b0000 /
b000 2
0%
#11150000
0#
0+
#11200000
1#
1+
b0001 /
b001 3
#11250000
0#
0+
#11300000
1#
1+
b010 3
1.
b0010 /
1&
#11350000
0#
0+
#11400000
1#
1+
b0011 /
b011 3
#11450000
0#
0+
#11500000
1#
1+
b100 3
b0100 /
#11550000
0#
0+
#11600000
1#
1+
0.
b0101 /
b101 3
0&
#11650000
0#
0+
#11700000
1#
1+
b110 3
1.
b0110 /
1&
#11750000
0#
0+
#11800000
1#
1+
0.
b0111 /
b111 3
0&
#11850000
0#
0+
#11900000
1#
1+
1-
b000 3
1.
b1000 /
1%
1&
#11950000
0#
0+
#12000000
1#
1+
0.
b001 2
b001 3
0&
#12050000
0#
0+
#12100000
1#
1+
b010 3
b010 2
#12150000
0#
0+
#12200000
1#
1+
b011 2
b011 3
#12250000
0#
0+
#12300000
1#
1+
b100 3
1.
b100 2
1&
#12350000
0#
0+
#12400000
1#
1+
0.
b101 2
b101 3
0&
#12450000
0#
0+
#12500000
1#
1+
b110 3
b110 2
#12550000
b00001001 "
0#
b00001001 ,
0+
#12600000
1#
1+
b111 2
b00001001 0
b111 3
#12650000
0#
0+
#12700000
1#
1+
0-
b000 3
b0000 /
b000 2
0%
#12750000
0#
0+
#12800000
1#
1+
b0001 /
b001 3
#12850000
0#
0+
#12900000
1#
1+
b010 3
1.
b0010 /
1&
#12950000
0#
0+
#13000000
1#
1+
b0011 /
b011 3
#13050000
0#
0+
#13100000
1#
1+
b100 3
b0100 /
#13150000
0#
0+
#13200000
1#
1+
0.
b0101 /
b101 3
0&
#13250000
0#
0+
#13300000
1#
1+
b110 3
1.
b0110 /
1&
#13350000
0#
0+
#13400000
1#
1+
0.
b0111 /
b111 3
0&
#13450000
0#
0+
#13500000
1#
1+
1-
b000 3
1.
b1000 /
1%
1&
#13550000
0#
0+
#13600000
1#
1+
b001 2
b001 3
#13650000
0#
0+
#13700000
1#
1+
b010 3
0.
b010 2
0&
#13750000
0#
0+
#13800000
1#
1+
b011 2
b011 3
#13850000
0#
0+
#13900000
1#
1+
b100 3
1.
b100 2
1&
#13950000
0#
0+
#14000000
1#
1+
0.
b101 2
b101 3
0&
#14050000
b00001010 "
0#
b00001010 ,
0+
#14100000
1#
1+
b110 3
b00001010 0
b110 2
#14150000
0#
0+
#14200000
1#
1+
b111 2
b111 3
#14250000
0#
0+
#14300000
1#
1+
0-
b000 3
b0000 /
b000 2
0%
#14350000
0#
0+
#14400000
1#
1+
b0001 /
b001 3
#14450000
0#
0+
#14500000
1#
1+
b010 3
1.
b0010 /
1&
#14550000
0#
0+
#14600000
1#
1+
b0011 /
b011 3
#14650000
0#
0+
#14700000
1#
1+
b100 3
b0100 /
#14750000
0#
0+
#14800000
1#
1+
0.
b0101 /
b101 3
0&
#14850000
0#
0+
#14900000
1#
1+
b110 3
1.
b0110 /
1&
#14950000
0#
0+
#15000000
1#
1+
0.
b0111 /
b111 3
0&
#15050000
0#
0+
#15100000
1#
1+
1-
b000 3
1.
b1000 /
1%
1&
#15150000
0#
0+
#15200000
1#
1+
0.
b001 2
b001 3
0&
#15250000
0#
0+
#15300000
1#
1+
b010 3
1.
b010 2
1&
#15350000
0#
0+
#15400000
1#
1+
0.
b011 2
b011 3
0&
#15450000
0#
0+
#15500000
1#
1+
b100 3
1.
b100 2
1&
#15550000
b01000111 "
0#
b01000111 ,
0+
#15600000
1#
1+
0.
b101 2
b01000111 0
b101 3
0&
#15650000
0#
0+
#15700000
1#
1+
b110 3
b110 2
#15750000
0#
0+
#15800000
1#
1+
1.
b111 2
b111 3
1&
#15850000
0#
0+
#15900000
1#
1+
0-
b000 3
b0000 /
b000 2
0%
#15950000
0#
0+
#16000000
1#
1+
0.
b0001 /
b001 3
0&
#16050000
0#
0+
#16100000
1#
1+
b010 3
1.
b0010 /
1&
#16150000
0#
0+
#16200000
1#
1+
b0011 /
b011 3
#16250000
0#
0+
#16300000
1#
1+
b100 3
b0100 /
#16350000
0#
0+
#16400000
1#
1+
0.
b0101 /
b101 3
0&
#16450000
0#
0+
#16500000
1#
1+
b110 3
1.
b0110 /
1&
#16550000
0#
0+
#16600000
1#
1+
0.
b0111 /
b111 3
0&
#16650000
0#
0+
#16700000
1#
1+
1-
b000 3
1.
b1000 /
1%
1&
#16750000
0#
0+
#16800000
1#
1+
b001 2
b001 3
#16850000
0#
0+
#16900000
1#
1+
b010 3
b010 2
#16950000
0#
0+
#17000000
1#
1+
b011 2
b011 3
#17050000
b01100001 "
0#
b01100001 ,
0+
#17100000
1#
1+
b100 3
b01100001 0
0.
b100 2
0&
#17150000
0#
0+
#17200000
1#
1+
b101 2
b101 3
#17250000
0#
0+
#17300000
1#
1+
b110 3
1.
b110 2
1&
#17350000
0#
0+
#17400000
1#
1+
b111 2
b111 3
#17450000
0#
0+
#17500000
1#
1+
0-
b000 3
b0000 /
b000 2
0%
#17550000
0#
0+
#17600000
1#
1+
0.
b0001 /
b001 3
0&
#17650000
0#
0+
#17700000
1#
1+
b010 3
1.
b0010 /
1&
#17750000
0#
0+
#17800000
1#
1+
b0011 /
b011 3
#17850000
0#
0+
#17900000
1#
1+
b100 3
b0100 /
#17950000
0#
0+
#18000000
1#
1+
0.
b0101 /
b101 3
0&
#18050000
0#
0+
#18100000
1#
1+
b110 3
1.
b0110 /
1&
#18150000
0#
0+
#18200000
1#
1+
0.
b0111 /
b111 3
0&
#18250000
0#
0+
#18300000
1#
1+
1-
b000 3
1.
b1000 /
1%
1&
#18350000
0#
0+
#18400000
1#
1+
b001 2
b001 3
#18450000
0#
0+
#18500000
1#
1+
b010 3
0.
b010 2
0&
#18550000
b00000001 "
0#
b00000001 ,
0+
#18600000
1#
1+
b011 2
b00000001 0
b011 3
#18650000
0#
0+
#18700000
1#
1+
b100 3
b100 2
#18750000
0#
0+
#18800000
1#
1+
b101 2
b101 3
#18850000
0#
0+
#18900000
1#
1+
b110 3
b110 2
#18950000
0#
0+
#19000000
1#
1+
b111 2
b111 3
#19050000
0#
0+
#19100000
1#
1+
0-
b000 3
b0000 /
b000 2
0%
#19150000
0#
0+
#19200000
1#
1+
b0001 /
b001 3
#19250000
0#
0+
#19300000
1#
1+
b010 3
1.
b0010 /
1&
#19350000
0#
0+
#19400000
1#
1+
b0011 /
b011 3
#19450000
0#
0+
#19500000
1#
1+
b100 3
b0100 /
#19550000
0#
0+
#19600000
1#
1+
0.
b0101 /
b101 3
0&
#19650000
0#
0+
#19700000
1#
1+
b110 3
1.
b0110 /
1&
#19750000
0#
0+
#19800000
1#
1+
0.
b0111 /
b111 3
0&
#19850000
0#
0+
#19900000
1#
1+
1-
b000 3
1.
b1000 /
1%
1&
#19950000
0#
0+
#20000000
1#
1+
b001 2
b001 3
#20050000
b00100011 "
0#
b00100011 ,
0+
#20100000
1#
1+
b010 3
b00100011 0
0.
b010 2
0&
#20150000
0#
0+
#20200000
1#
1+
b011 2
b011 3
#20250000
0#
0+
#20300000
1#
1+
b100 3
b100 2
#20350000
0#
0+
#20400000
1#
1+
b101 2
b101 3
#20450000
0#
0+
#20500000
1#
1+
b110 3
1.
b110 2
1&
#20550000
0#
0+
#20600000
1#
1+
0.
b111 2
b111 3
0&
#20650000
0#
0+
#20700000
1#
1+
0-
b000 3
b0000 /
b000 2
0%
#20750000
0#
0+
#20800000
1#
1+
b0001 /
b001 3
#20850000
0#
0+
#20900000
1#
1+
b010 3
1.
b0010 /
1&
#20950000
0#
0+
#21000000
1#
1+
b0011 /
b011 3
#21050000
0#
0+
#21100000
1#
1+
b100 3
b0100 /
#21150000
0#
0+
#21200000
1#
1+
0.
b0101 /
b101 3
0&
#21250000
0#
0+
#21300000
1#
1+
b110 3
1.
b0110 /
1&
#21350000
0#
0+
#21400000
1#
1+
0.
b0111 /
b111 3
0&
#21450000
0#
0+
#21500000
1#
1+
1-
b000 3
1.
b1000 /
1%
1&
#21550000
0#
0+
#21600000
1#
1+
b001 2
b001 3
#21650000
0#
0+
#21700000
1#
1+
b010 3
b010 2
#21750000
0#
0+
#21800000
1#
1+
0.
b011 2
b011 3
0&
#21850000
0#
0+
#21900000
1#
1+
b100 3
b100 2
#21950000
0#
0+
#22000000
1#
1+
b101 2
b101 3
#22050000
0#
0+
#22100000
1#
1+
b110 3
1.
b110 2
1&
#22150000
0#
0+
#22200000
1#
1+
0.
b111 2
b111 3
0&
#22250000
0#
0+
#22300000
1#
1+
0-
b000 3
b0000 /
b000 2
0%
#22350000
0#
0+
#22400000
1#
1+
b0001 /
b001 3
#22450000
0#
0+
#22500000
1#
1+
b010 3
1.
b0010 /
1&
#22550000
0#
0+
#22600000
1#
1+
b0011 /
b011 3
#22650000
0#
0+
#22700000
1#
1+
b100 3
b0100 /
#22750000
0#
0+
#22800000
1#
1+
0.
b0101 /
b101 3
0&
#22850000
0#
0+
#22900000
1#
1+
b110 3
1.
b0110 /
1&
#22950000
0#
0+
#23000000
1#
1+
0.
b0111 /
b111 3
0&
#23050000
0#
0+
#23100000
1#
1+
1-
b000 3
1.
b1000 /
1%
1&
#23150000
0#
0+
#23200000
1#
1+
b001 2
b001 3
#23250000
0#
0+
#23300000
1#
1+
b010 3
b010 2
#23350000
0#
0+
#23400000
1#
1+
0.
b011 2
b011 3
0&
#23450000
0#
0+
#23500000
1#
1+
b100 3
b100 2
#23550000
0#
0+
#23600000
1#
1+
b101 2
b101 3
#23650000
0#
0+
#23700000
1#
1+
b110 3
1.
b110 2
1&
#23750000
0#
0+
#23800000
1#
1+
0.
b111 2
b111 3
0&
#23850000
0#
0+
#23900000
1#
1+
0-
b000 3
b0000 /
b000 2
0%
#23950000
0#
0+
#24000000
1#
1+
b0001 /
b001 3
#24050000
0#
0+
#24100000
1#
1+
b010 3
1.
b0010 /
1&
#24150000
0#
0+
#24200000
1#
1+
b0011 /
b011 3
#24250000
0#
0+
#24300000
1#
1+
b100 3
b0100 /
#24350000
0#
0+
#24400000
1#
1+
0.
b0101 /
b101 3
0&
#24450000
0#
0+
#24500000
1#
1+
b110 3
1.
b0110 /
1&
#24550000
0#
0+
#24600000
1#
1+
0.
b0111 /
b111 3
0&
#24650000
0#
0+
#24700000
1#
1+
1-
b000 3
1.
b1000 /
1%
1&
#24750000
0#
0+
#24800000
1#
1+
b001 2
b001 3
#24850000
0#
0+
#24900000
1#
1+
b010 3
b010 2
#24950000
0#
0+
#25000000
1#
1+
0.
b011 2
b011 3
0&
#25050000
0#
0+
#25100000
1#
1+
b100 3
b100 2
#25150000
0#
0+
#25200000
1#
1+
b101 2
b101 3
#25250000
0#
0+
#25300000
1#
1+
b110 3
1.
b110 2
1&
#25350000
0#
0+
#25400000
1#
1+
0.
b111 2
b111 3
0&
#25450000
0#
0+
#25500000
1#
1+
0-
b000 3
b0000 /
b000 2
0%
#25550000
0#
0+
#25600000
1#
1+
b0001 /
b001 3
#25650000
0#
0+
#25700000
1#
1+
b010 3
1.
b0010 /
1&
#25750000
0#
0+
#25800000
1#
1+
b0011 /
b011 3
#25850000
0#
0+
#25900000
1#
1+
b100 3
b0100 /
#25950000
0#
0+
#26000000
1#
1+
0.
b0101 /
b101 3
0&
#26050000
0#
0+
#26100000
1#
1+
b110 3
1.
b0110 /
1&
#26150000
0#
0+
#26200000
1#
1+
0.
b0111 /
b111 3
0&
#26250000
0#
0+
#26300000
1#
1+
1-
b000 3
1.
b1000 /
1%
1&
#26350000
0#
0+
#26400000
1#
1+
b001 2
b001 3
#26450000
0#
0+
#26500000
1#
1+
b010 3
b010 2
#26550000
0#
0+
#26600000
1#
1+
0.
b011 2
b011 3
0&
#26650000
0#
0+
#26700000
1#
1+
b100 3
b100 2
#26750000
0#
0+
#26800000
1#
1+
b101 2
b101 3
#26850000
0#
0+
#26900000
1#
1+
b110 3
1.
b110 2
1&
#26950000
0#
0+
#27000000
1#
1+
0.
b111 2
b111 3
0&
#27050000
0#
0+
#27100000
1#
1+
0-
b000 3
b0000 /
b000 2
0%
#27150000
0#
0+
#27200000
1#
1+
b0001 /
b001 3
#27250000
0#
0+
#27300000
1#
1+
b010 3
1.
b0010 /
1&
#27350000
0#
0+
#27400000
1#
1+
b0011 /
b011 3
#27450000
0#
0+
#27500000
1#
1+
b100 3
b0100 /
#27550000
0#
0+
#27600000
1#
1+
0.
b0101 /
b101 3
0&
#27650000
0#
0+
#27700000
1#
1+
b110 3
1.
b0110 /
1&
#27750000
0#
0+
#27800000
1#
1+
0.
b0111 /
b111 3
0&
#27850000
0#
0+
#27900000
1#
1+
1-
b000 3
1.
b1000 /
1%
1&
#27950000
0#
0+
#28000000
1#
1+
b001 2
b001 3
#28050000
0#
0+
#28100000
1#
1+
b010 3
b010 2
#28150000
0#
0+
#28200000
1#
1+
0.
b011 2
b011 3
0&
#28250000
0#
0+
#28300000
1#
1+
b100 3
b100 2
#28350000
0#
0+
#28400000
1#
1+
b101 2
b101 3
#28450000
0#
0+
#28500000
1#
1+
b110 3
1.
b110 2
1&
#28550000
0#
0+
#28600000
1#
1+
0.
b111 2
b111 3
0&
#28650000
0#
0+
#28700000
1#
1+
0-
b000 3
b0000 /
b000 2
0%
#28750000
0#
0+
#28800000
1#
1+
b0001 /
b001 3
#28850000
0#
0+
#28900000
1#
1+
b010 3
1.
b0010 /
1&
#28950000
0#
0+
#29000000
1#
1+
b0011 /
b011 3
#29050000
0#
0+
#29100000
1#
1+
b100 3
b0100 /
#29150000
0#
0+
#29200000
1#
1+
0.
b0101 /
b101 3
0&
#29250000
0#
0+
#29300000
1#
1+
b110 3
1.
b0110 /
1&
#29350000
0#
0+
#29400000
1#
1+
0.
b0111 /
b111 3
0&
#29450000
0#
0+
#29500000
1#
1+
1-
b000 3
1.
b1000 /
1%
1&
#29550000
0#
0+
#29600000
1#
1+
b001 2
b001 3
#29650000
0#
0+
#29700000
1#
1+
b010 3
b010 2
#29750000
0#
0+
#29800000
1#
1+
0.
b011 2
b011 3
0&
#29850000
0#
0+
#29900000
1#
1+
b100 3
b100 2
#29950000
0#
0+
#30000000
1#
1+
b101 2
b101 3
#30050000
0#
0+
#30100000
1#
1+
b110 3
1.
b110 2
1&
#30150000
0#
0+
#30200000
1#
1+
0.
b111 2
b111 3
0&
#30250000
0#
0+
#30300000
1#
1+
0-
b000 3
b0000 /
b000 2
0%
#30350000
0#
0+
#30400000
1#
1+
b0001 /
b001 3
#30450000
0#
0+
#30500000
1#
1+
b010 3
1.
b0010 /
1&
#30550000
0#
0+
#30600000
1#
1+
b0011 /
b011 3
#30650000
0#
0+
#30700000
1#
1+
b100 3
b0100 /
#30750000
0#
0+
#30800000
1#
1+
0.
b0101 /
b101 3
0&
#30850000
0#
0+
#30900000
1#
1+
b110 3
1.
b0110 /
1&
#30950000
0#
0+
#31000000
1#
1+
0.
b0111 /
b111 3
0&
#31050000
0#
0+
#31100000
1#
1+
1-
b000 3
1.
b1000 /
1%
1&
#31150000
0#
0+
#31200000
1#
1+
b001 2
b001 3
#31250000
0#
0+
#31300000
1#
1+
b010 3
b010 2
#31350000
0#
0+
#31400000
1#
1+
0.
b011 2
b011 3
0&
#31450000
0#
0+
#31500000
1#
1+
b100 3
b100 2
#31550000
0#
0+
#31600000
1#
1+
b101 2
b101 3
#31650000
0#
0+
#31700000
1#
1+
b110 3
1.
b110 2
1&
#31750000
0#
0+
#31800000
1#
1+
0.
b111 2
b111 3
0&
#31850000
0#
0+
#31900000
1#
1+
0-
b000 3
b0000 /
b000 2
0%
#31950000
0#
0+
#32000000
1#
1+
b0001 /
b001 3
#32050000
0#
0+
#32100000
1#
1+
b010 3
1.
b0010 /
1&
#32150000
0#
0+
#32200000
1#
1+
b0011 /
b011 3
#32250000
0#
0+
#32300000
1#
1+
b100 3
b0100 /
#32350000
0#
0+
#32400000
1#
1+
0.
b0101 /
b101 3
0&
#32450000
0#
0+
#32500000
1#
1+
b110 3
1.
b0110 /
1&
#32550000
0#
0+
#32600000
1#
1+
0.
b0111 /
b111 3
0&
#32650000
0#
0+
#32700000
1#
1+
1-
b000 3
1.
b1000 /
1%
1&
#32750000
0#
0+
#32800000
1#
1+
b001 2
b001 3
#32850000
0#
0+
#32900000
1#
1+
b010 3
b010 2
#32950000
0#
0+
#33000000
1#
1+
0.
b011 2
b011 3
0&
#33050000
0#
0+
#33100000
1#
1+
b100 3
b100 2
#33150000
0#
0+
