spi_final/Synthesize/FINAL/clk_div.v
`timescale 1 ns / 1 ps
module clk_div (spi_clk, m_clk, spi_cs, nrst);
	input nrst, spi_cs, m_clk;
	output spi_clk;

	//wire nrst, spi_clk_en, m_clk;
	reg spi_clk;
	reg [0:3] counter;


	always @(posedge m_clk or negedge nrst)begin
		if (!nrst) begin 
			spi_clk <= 1'b0; 
			counter <= 4'b0000;
		end
		else begin
			if(!spi_cs) begin 
				if (counter == 4'b1001)
				   begin
					spi_clk <= !spi_clk;
					counter <= 4'b0000;
				   end // End of counter if
				else
					counter <= counter + 4'b0001;
			end // End of spi_clk_en if
		end // End of else
	end // End of always block

	
endmodule

spi_final/Synthesize/FINAL/clk_div_test.v
`timescale 1 ns / 1 ps
module clk_div_test();
	reg nrst, spi_cs, m_clk;
	wire spi_clk;
event end_first_pass;
	clk_div c0(spi_clk, m_clk, spi_cs, nrst);
	
	

	// Setting the initial input values
	initial
	begin
		nrst = 0;
		m_clk = 1;
	    spi_cs<=1;
	end
always #50 m_clk = ~m_clk;
	// Displaying signals as graphical waveforms //
	/*initial begin
		$shm_open("clk_div.shm");
		$shm_probe("AS"); // AS = all signals
	end
*/
initial 
	begin
      $dumpfile("clk_div_waveform_result.vcd");
     $dumpvars(0,clk_div_test);
      end    

	initial begin
		$display ("time m_clk, spi_cs, nrst, spi_clk");
		$monitor ("at time %0d nrst = %b spi_cs = %b m_clk = %b spi_clk=%d", $time, nrst, spi_cs, m_clk, spi_clk);
	end

	initial
	begin
	begin
	#100
	spi_cs<=0;
	nrst <= 1;
	#100
	nrst <=0;
	#200
    nrst<=1;
		
#5000 ->end_first_pass;
   end
   $finish;
		
	end
endmodule

spi_final/Synthesize/FINAL/clk_div_waveform_result.vcd
$date
    Jul 18, 2016  13:04:26
$end
$version
    Tool:	VERILOG-XL	08.20.001-d
$end
$timescale
     1ps
$end

$scope module clk_div_test $end
$var reg       1 !    nrst  $end
$var reg       1 "    spi_cs  $end
$var reg       1 #    m_clk  $end
$var wire      1 $    spi_clk  $end
$var event     1 %    end_first_pass  $end

$scope module c0 $end
$var wire      1 &    nrst  $end
$var wire      1 '    spi_cs  $end
$var wire      1 (    m_clk  $end
$var reg       1 )    spi_clk  $end
$var reg       4 *    counter [0:3] $end
$upscope $end

$upscope $end

$enddefinitions $end
$dumpvars
0!
1"
1#
0$
x%
0&
1'
1(
0)
b0000 *
$end
#50000
0#
0(
#100000
1#
1(
0"
1!
0'
1&
#150000
0#
0(
#200000
1#
1(
0!
b0001 *
0&
b0000 *
#250000
0#
0(
#300000
1#
1(
#350000
0#
0(
#400000
1#
1(
1!
1&
#450000
0#
0(
#500000
1#
1(
b0001 *
#550000
0#
0(
#600000
1#
1(
b0010 *
#650000
0#
0(
#700000
1#
1(
b0011 *
#750000
0#
0(
#800000
1#
1(
b0100 *
#850000
0#
0(
#900000
1#
1(
b0101 *
#950000
0#
0(
#1000000
1#
1(
b0110 *
#1050000
0#
0(
#1100000
1#
1(
b0111 *
#1150000
0#
0(
#1200000
1#
1(
b1000 *
#1250000
0#
0(
#1300000
1#
1(
b1001 *
#1350000
0#
0(
#1400000
1#
1(
1)
b0000 *
1$
#1450000
0#
0(
#1500000
1#
1(
b0001 *
#1550000
0#
0(
#1600000
1#
1(
b0010 *
#1650000
0#
0(
#1700000
1#
1(
b0011 *
#1750000
0#
0(
#1800000
1#
1(
b0100 *
#1850000
0#
0(
#1900000
1#
1(
b0101 *
#1950000
0#
0(
#2000000
1#
1(
b0110 *
#2050000
0#
0(
#2100000
1#
1(
b0111 *
#2150000
0#
0(
#2200000
1#
1(
b1000 *
#2250000
0#
0(
#2300000
1#
1(
b1001 *
#2350000
0#
0(
#2400000
1#
1(
0)
b0000 *
0$
#2450000
0#
0(
#2500000
1#
1(
b0001 *
#2550000
0#
0(
#2600000
1#
1(
b0010 *
#2650000
0#
0(
#2700000
1#
1(
b0011 *
#2750000
0#
0(
#2800000
1#
1(
b0100 *
#2850000
0#
0(
#2900000
1#
1(
b0101 *
#2950000
0#
0(
#3000000
1#
1(
b0110 *
#3050000
0#
0(
#3100000
1#
1(
b0111 *
#3150000
0#
0(
#3200000
1#
1(
b1000 *
#3250000
0#
0(
#3300000
1#
1(
b1001 *
#3350000
0#
0(
#3400000
1#
1(
1)
b0000 *
1$
#3450000
0#
0(
#3500000
1#
1(
b0001 *
#3550000
0#
0(
#3600000
1#
1(
b0010 *
#3650000
0#
0(
#3700000
1#
1(
b0011 *
#3750000
0#
0(
#3800000
1#
1(
b0100 *
#3850000
0#
0(
#3900000
1#
1(
b0101 *
#3950000
0#
0(
#4000000
1#
1(
b0110 *
#4050000
0#
0(
#4100000
1#
1(
b0111 *
#4150000
0#
0(
#4200000
1#
1(
b1000 *
#4250000
0#
0(
#4300000
1#
1(
b1001 *
#4350000
0#
0(
#4400000
1#
1(
0)
b0000 *
0$
#4450000
0#
0(
#4500000
1#
1(
b0001 *
#4550000
0#
0(
#4600000
1#
1(
b0010 *
#4650000
0#
0(
#4700000
1#
1(
b0011 *
#4750000
0#
0(
#4800000
1#
1(
b0100 *
#4850000
0#
0(
#4900000
1#
1(
b0101 *
#4950000
0#
0(
#5000000
1#
1(
b0110 *
#5050000
0#
0(
#5100000
1#
1(
b0111 *
#5150000
0#
0(
#5200000
1#
1(
b1000 *
#5250000
0#
0(
#5300000
1#
1(
b1001 *
#5350000
0#
0(
#5400000
x%
