Data_out/clk_div.v
`timescale 1 ns / 1 ps
module clk_div (spi_clk, m_clk, spi_clk_en, nrst);
	input nrst, spi_clk_en, m_clk;
	output spi_clk;

	wire nrst, spi_clk_en, m_clk;
	reg spi_clk;
	reg [0:3] counter;
	initial begin 
		counter <= 4'b0000;
		spi_clk <= 1'b0;
	end
	always @(posedge m_clk or negedge nrst)begin
		if (!nrst) begin 
			spi_clk <= 1'b0; 
			counter <= 4'b0000;
		end
		else begin
			if(spi_clk_en) begin 
				if (counter == 4'b1001)begin
					spi_clk <= !spi_clk;
					counter <= 4'b0000;
				end // End of counter if
				else
					counter <= counter + 4'b0001;
			end // End of spi_clk_en if
		end // End of else
	end // End of always block

	
endmodule

clock_div/clk_div_test.v
`timescale 1 ns / 1 ps
module clk_div_test();
	reg nrst, spi_clk_en, m_clk;
	wire spi_clk;

	clk_div c0(spi_clk, m_clk, spi_clk_en, nrst);
	
	always #50 m_clk = ~m_clk;

	// Setting the initial input values
	initial
	begin
		nrst = 1;
		m_clk = 1;
		spi_clk_en = 1;
	end

	// Displaying signals as graphical waveforms //
	/*initial begin
		$shm_open("clk_div.shm");
		$shm_probe("AS"); // AS = all signals
	end*/
initial 
	begin
      $dumpfile("clk_div_waveform_result.vcd");
     $dumpvars(0,clk_div_test);
      end    

	initial begin
		$display ("time m_clk, spi_clk_en, nrst, spi_clk");
		$monitor ("at time %0d nrst = %b spi_clk_en = %b m_clk = %b spi_clk=%d", $time, nrst, spi_clk_en, m_clk, spi_clk);
	end

	initial
	begin
		//We used initial value in the verilog code but the netlist does not get this value. So it is better to use an initial reset to set everything in motion
		//Initial reset
		#10
			nrst = 1'b0;
		// Turn off the reset
		#10
			nrst = 1'b1;
		// Turn on the reset again to see it's effect
		#10000
			nrst = 1'b0;
		// Turn off the reset
		#2000
			nrst = 1'b1;
		// Turn off the enable
		#2000
			spi_clk_en = 1'b0;
		// Turn on the enable again
		#2000
			spi_clk_en = 1'b1;
		// Wait for a while to see it's effect and then finish
		#2000
			$finish;
	end
endmodule

clock_div/clk_div_waveform_result.vcd
$date
	Sun Jun 26 15:01:42 2016
$end
$version
	Icarus Verilog
$end
$timescale
	1ps
$end
$scope module clk_div_test $end
$var wire 1 ! spi_clk $end
$var reg 1 " m_clk $end
$var reg 1 # nrst $end
$var reg 1 $ spi_clk_en $end
$scope module c0 $end
$var wire 1 " m_clk $end
$var wire 1 # nrst $end
$var wire 1 $ spi_clk_en $end
$var reg 4 % counter [0:3] $end
$var reg 1 ! spi_clk $end
$upscope $end
$upscope $end
$enddefinitions $end
#0
$dumpvars
bx %
1$
1#
1"
0!
$end
#10000
b0 %
0#
#20000
1#
#50000
0"
#100000
b1 %
1"
#150000
0"
#200000
b10 %
1"
#250000
0"
#300000
b11 %
1"
#350000
0"
#400000
b100 %
1"
#450000
0"
#500000
b101 %
1"
#550000
0"
#600000
b110 %
1"
#650000
0"
#700000
b111 %
1"
#750000
0"
#800000
b1000 %
1"
#850000
0"
#900000
b1001 %
1"
#950000
0"
#1000000
b0 %
1!
1"
#1050000
0"
#1100000
b1 %
1"
#1150000
0"
#1200000
b10 %
1"
#1250000
0"
#1300000
b11 %
1"
#1350000
0"
#1400000
b100 %
1"
#1450000
0"
#1500000
b101 %
1"
#1550000
0"
#1600000
b110 %
1"
#1650000
0"
#1700000
b111 %
1"
#1750000
0"
#1800000
b1000 %
1"
#1850000
0"
#1900000
b1001 %
1"
#1950000
0"
#2000000
b0 %
0!
1"
#2050000
0"
#2100000
b1 %
1"
#2150000
0"
#2200000
b10 %
1"
#2250000
0"
#2300000
b11 %
1"
#2350000
0"
#2400000
b100 %
1"
#2450000
0"
#2500000
b101 %
1"
#2550000
0"
#2600000
b110 %
1"
#2650000
0"
#2700000
b111 %
1"
#2750000
0"
#2800000
b1000 %
1"
#2850000
0"
#2900000
b1001 %
1"
#2950000
0"
#3000000
b0 %
1!
1"
#3050000
0"
#3100000
b1 %
1"
#3150000
0"
#3200000
b10 %
1"
#3250000
0"
#3300000
b11 %
1"
#3350000
0"
#3400000
b100 %
1"
#3450000
0"
#3500000
b101 %
1"
#3550000
0"
#3600000
b110 %
1"
#3650000
0"
#3700000
b111 %
1"
#3750000
0"
#3800000
b1000 %
1"
#3850000
0"
#3900000
b1001 %
1"
#3950000
0"
#4000000
b0 %
0!
1"
#4050000
0"
#4100000
b1 %
1"
#4150000
0"
#4200000
b10 %
1"
#4250000
0"
#4300000
b11 %
1"
#4350000
0"
#4400000
b100 %
1"
#4450000
0"
#4500000
b101 %
1"
#4550000
0"
#4600000
b110 %
1"
#4650000
0"
#4700000
b111 %
1"
#4750000
0"
#4800000
b1000 %
1"
#4850000
0"
#4900000
b1001 %
1"
#4950000
0"
#5000000
b0 %
1!
1"
#5050000
0"
#5100000
b1 %
1"
#5150000
0"
#5200000
b10 %
1"
#5250000
0"
#5300000
b11 %
1"
#5350000
0"
#5400000
b100 %
1"
#5450000
0"
#5500000
b101 %
1"
#5550000
0"
#5600000
b110 %
1"
#5650000
0"
#5700000
b111 %
1"
#5750000
0"
#5800000
b1000 %
1"
#5850000
0"
#5900000
b1001 %
1"
#5950000
0"
#6000000
b0 %
0!
1"
#6050000
0"
#6100000
b1 %
1"
#6150000
0"
#6200000
b10 %
1"
#6250000
0"
#6300000
b11 %
1"
#6350000
0"
#6400000
b100 %
1"
#6450000
0"
#6500000
b101 %
1"
#6550000
0"
#6600000
b110 %
1"
#6650000
0"
#6700000
b111 %
1"
#6750000
0"
#6800000
b1000 %
1"
#6850000
0"
#6900000
b1001 %
1"
#6950000
0"
#7000000
b0 %
1!
1"
#7050000
0"
#7100000
b1 %
1"
#7150000
0"
#7200000
b10 %
1"
#7250000
0"
#7300000
b11 %
1"
#7350000
0"
#7400000
b100 %
1"
#7450000
0"
#7500000
b101 %
1"
#7550000
0"
#7600000
b110 %
1"
#7650000
0"
#7700000
b111 %
1"
#7750000
0"
#7800000
b1000 %
1"
#7850000
0"
#7900000
b1001 %
1"
#7950000
0"
#8000000
b0 %
0!
1"
#8050000
0"
#8100000
b1 %
1"
#8150000
0"
#8200000
b10 %
1"
#8250000
0"
#8300000
b11 %
1"
#8350000
0"
#8400000
b100 %
1"
#8450000
0"
#8500000
b101 %
1"
#8550000
0"
#8600000
b110 %
1"
#8650000
0"
#8700000
b111 %
1"
#8750000
0"
#8800000
b1000 %
1"
#8850000
0"
#8900000
b1001 %
1"
#8950000
0"
#9000000
b0 %
1!
1"
#9050000
0"
#9100000
b1 %
1"
#9150000
0"
#9200000
b10 %
1"
#9250000
0"
#9300000
b11 %
1"
#9350000
0"
#9400000
b100 %
1"
#9450000
0"
#9500000
b101 %
1"
#9550000
0"
#9600000
b110 %
1"
#9650000
0"
#9700000
b111 %
1"
#9750000
0"
#9800000
b1000 %
1"
#9850000
0"
#9900000
b1001 %
1"
#9950000
0"
#10000000
b0 %
0!
1"
#10020000
0#
#10050000
0"
#10100000
1"
#10150000
0"
#10200000
1"
#10250000
0"
#10300000
1"
#10350000
0"
#10400000
1"
#10450000
0"
#10500000
1"
#10550000
0"
#10600000
1"
#10650000
0"
#10700000
1"
#10750000
0"
#10800000
1"
#10850000
0"
#10900000
1"
#10950000
0"
#11000000
1"
#11050000
0"
#11100000
1"
#11150000
0"
#11200000
1"
#11250000
0"
#11300000
1"
#11350000
0"
#11400000
1"
#11450000
0"
#11500000
1"
#11550000
0"
#11600000
1"
#11650000
0"
#11700000
1"
#11750000
0"
#11800000
1"
#11850000
0"
#11900000
1"
#11950000
0"
#12000000
1"
#12020000
1#
#12050000
0"
#12100000
b1 %
1"
#12150000
0"
#12200000
b10 %
1"
#12250000
0"
#12300000
b11 %
1"
#12350000
0"
#12400000
b100 %
1"
#12450000
0"
#12500000
b101 %
1"
#12550000
0"
#12600000
b110 %
1"
#12650000
0"
#12700000
b111 %
1"
#12750000
0"
#12800000
b1000 %
1"
#12850000
0"
#12900000
b1001 %
1"
#12950000
0"
#13000000
b0 %
1!
1"
#13050000
0"
#13100000
b1 %
1"
#13150000
0"
#13200000
b10 %
1"
#13250000
0"
#13300000
b11 %
1"
#13350000
0"
#13400000
b100 %
1"
#13450000
0"
#13500000
b101 %
1"
#13550000
0"
#13600000
b110 %
1"
#13650000
0"
#13700000
b111 %
1"
#13750000
0"
#13800000
b1000 %
1"
#13850000
0"
#13900000
b1001 %
1"
#13950000
0"
#14000000
b0 %
0!
1"
