spi_final/Synthesize/FINAL/control_unit.v

`timescale 1 ns / 1 ps
module control_unit(spi_mosi,data_av,read_req,add_byte,read_request,data_available,m_clk,n_reset,spi_mosi_I,spi_mosi_O);
output spi_mosi;
output data_av;
output read_req;
output[0:7] add_byte;
input read_request,data_available,m_clk,n_reset ;
input spi_mosi_I,spi_mosi_O;

reg [0:7] add_byte;
reg data_av,read_req;
reg write_en,read_en;
reg spi_mosi;
always @(posedge m_clk or negedge n_reset )
		if (!n_reset ) begin
			data_av<=1;
			read_req<=0;
			
		end		   
		else begin
			 if (data_available  &&  !read_request  ||  !data_available && read_request ) begin
				data_av<=1;
				read_req<=0;
				
			end
			else if (!data_available && !read_request) begin
				data_av<=data_available;
				
				
			end
			else if (data_available && read_request) begin            
				read_req<=read_request;
				
				
			end
         	end

always @(negedge data_av or posedge read_req or negedge n_reset)

 if (!n_reset) begin
        write_en<=0;
		read_en<=0;
end


else if (!data_av) begin

                   write_en<=1;
				   read_en<=0;
				   end
				   
else if (read_req) begin
                      write_en<=0;
					  read_en<=1;
					  end
					  
					  
 always @(posedge m_clk or negedge n_reset )

if(!n_reset) begin
                     add_byte<=0;
                   spi_mosi<=0;
		           end
else if(write_en==1) begin
                           add_byte<=8'b10101101;
                          spi_mosi<=spi_mosi_I;
                        end    
else if (read_en==1)begin
                          spi_mosi<=spi_mosi_O ;
                           add_byte<=8'd45;
                        end  
						
				




endmodule

spi_final/Synthesize/FINAL/control_unit_test.v
 `timescale 1 ns / 1 ps
 module control_unit_test;
 reg spi_mosi_I,spi_mosi_O;
 reg data_available, read_request,m_clk,n_reset;
 wire data_av,read_req;
 wire [0:7] add_byte;
 wire spi_mosi;
 
 event end_first_pass;

 control_unit   C0(spi_mosi,data_av,read_req,add_byte,read_request,data_available,m_clk,n_reset,spi_mosi_I,spi_mosi_O);
 
 










initial begin
		$shm_open("control_unit_output.shm");
		$shm_probe("AS"); // AS = all signals
	end
/* 
 initial begin
$dumpfile("control_unit_waveform_result.vcd");
$dumpvars(0,control_unit_test);
end
 */
 initial
     begin
	     n_reset=0;
		 
		 #50
		 n_reset=1;
		 #100
		 n_reset=0;
		 #50
		 n_reset=1;
		 data_available=1;
		 read_request=0;
		 
		 m_clk=0;
		 spi_mosi_I=0;
		 spi_mosi_O=0;
	end
	
	
	always  #50 m_clk= ~m_clk;
	
initial
begin
#50 ;
$display ("at time %0d data_av = %b   read_req = %b add_byte= %b  read_request=%b data_available=%d  m_clk=%b n_reset=%b", $time,      
     data_av,read_req,add_byte,read_request,data_available,m_clk,n_reset);

end


	initial
	begin
	begin
	
#4025
read_request=~read_request;
#100
read_request=~read_request;

#1000
read_request=~read_request;
#100
read_request=~read_request;
#1000
read_request=~read_request;
#100
read_request=~read_request;
		

#525

spi_mosi_O=0;
#100
spi_mosi_O=1;
#100
spi_mosi_O=0;

#300
spi_mosi_O=1;
#100
spi_mosi_O=0;
#500

spi_mosi_I=1;
#100
spi_mosi_I=0;

#300
spi_mosi_O=1;
#100
spi_mosi_O=0;


#525		 

data_available=~data_available;
#100
data_available=~data_available;

#1000
data_available=~data_available;
#100
data_available=~data_available;

#1000
data_available=~data_available;
#100
data_available=~data_available;

#1000
data_available=~data_available;
#100
data_available=~data_available;

#1000
data_available=~data_available;
#100
data_available=~data_available;






#525		
 spi_mosi_I=0;
#100
spi_mosi_I=1;
#100
spi_mosi_I=0;
#300
spi_mosi_I=1;
#100
spi_mosi_I=0;
#300
spi_mosi_O=1;
#100
spi_mosi_O=0;

#500
spi_mosi_I=1;
#100
spi_mosi_I=0;


#4025
read_request=~read_request;
#100
read_request=~read_request;
		
#5000 ->end_first_pass;
   end
   $finish;
		
	end
endmodule

spi_final/Synthesize/CONTROL/control_unit_waveform_result.vcd
$date
	Wed Jul 20 11:20:30 2016
$end
$version
	Icarus Verilog
$end
$timescale
	1ps
$end
$scope module control_unit_test $end
$var event 1 ! end_first_pass $end
$var wire 1 " spi_mosi $end
$var wire 1 # read_req $end
$var wire 1 $ data_av $end
$var wire 8 % add_byte [0:7] $end
$var reg 1 & data_available $end
$var reg 1 ' m_clk $end
$var reg 1 ( n_reset $end
$var reg 1 ) read_request $end
$var reg 1 * spi_mosi_I $end
$var reg 1 + spi_mosi_O $end
$scope module C0 $end
$var wire 1 & data_available $end
$var wire 1 ' m_clk $end
$var wire 1 ( n_reset $end
$var wire 1 ) read_request $end
$var wire 1 * spi_mosi_I $end
$var wire 1 + spi_mosi_O $end
$var reg 8 , add_byte [0:7] $end
$var reg 1 $ data_av $end
$var reg 1 - read_en $end
$var reg 1 # read_req $end
$var reg 1 " spi_mosi $end
$var reg 1 . write_en $end
$upscope $end
$upscope $end
$enddefinitions $end
#0
$dumpvars
0.
0-
b0 ,
x+
x*
x)
0(
x'
x&
b0 %
1$
0#
0"
1!
$end
#50000
1(
#150000
0(
#200000
0+
0*
1'
0)
1&
1(
#250000
0'
#300000
1'
#350000
0'
#400000
1'
#450000
0'
#500000
1'
#550000
0'
#600000
1'
#650000
0'
#700000
1'
#750000
0'
#800000
1'
#850000
0'
#900000
1'
#950000
0'
#1000000
1'
#1050000
0'
#1100000
1'
#1150000
0'
#1200000
1'
#1250000
0'
#1300000
1'
#1350000
0'
#1400000
1'
#1450000
0'
#1500000
1'
#1550000
0'
#1600000
1'
#1650000
0'
#1700000
1'
#1750000
0'
#1800000
1'
#1850000
0'
#1900000
1'
#1950000
0'
#2000000
1'
#2050000
0'
#2100000
1'
#2150000
0'
#2200000
1'
#2250000
0'
#2300000
1'
#2350000
0'
#2400000
1'
#2450000
0'
#2500000
1'
#2550000
0'
#2600000
1'
#2650000
0'
#2700000
1'
#2750000
0'
#2800000
1'
#2850000
0'
#2900000
1'
#2950000
0'
#3000000
1'
#3050000
0'
#3100000
1'
#3150000
0'
#3200000
1'
#3250000
0'
#3300000
1'
#3350000
0'
#3400000
1'
#3450000
0'
#3500000
1'
#3550000
0'
#3600000
1'
#3650000
0'
#3700000
1'
#3750000
0'
#3800000
1'
#3850000
0'
#3900000
1'
#3950000
0'
#4000000
1'
#4025000
1)
#4050000
0'
#4100000
1-
b101101 %
b101101 ,
1#
1'
#4125000
0)
#4150000
0'
#4200000
b0 %
b0 ,
0#
1'
#4250000
0'
#4300000
1'
#4350000
0'
#4400000
1'
#4450000
0'
#4500000
1'
#4550000
0'
#4600000
1'
#4650000
0'
#4700000
1'
#4750000
0'
#4800000
1'
#4850000
0'
#4900000
1'
#4950000
0'
#5000000
1'
#5050000
0'
#5100000
1'
#5125000
1)
#5150000
0'
#5200000
b101101 %
b101101 ,
1#
1'
#5225000
0)
#5250000
0'
#5300000
b0 %
b0 ,
0#
1'
#5350000
0'
#5400000
1'
#5450000
0'
#5500000
1'
#5550000
0'
#5600000
1'
#5650000
0'
#5700000
1'
#5750000
0'
#5800000
1'
#5850000
0'
#5900000
1'
#5950000
0'
#6000000
1'
#6050000
0'
#6100000
1'
#6150000
0'
#6200000
1'
#6225000
1)
#6250000
0'
#6300000
b101101 %
b101101 ,
1#
1'
#6325000
0)
#6350000
0'
#6400000
b0 %
b0 ,
0#
1'
#6450000
0'
#6500000
1'
#6550000
0'
#6600000
1'
#6650000
0'
#6700000
1'
#6750000
0'
#6800000
1'
#6850000
0'
#6900000
1'
#6950000
0'
1+
#7000000
1"
1'
#7050000
0'
0+
#7100000
0"
1'
#7150000
0'
#7200000
1'
#7250000
0'
#7300000
1'
#7350000
0'
1+
#7400000
1"
1'
#7450000
0'
0+
#7500000
0"
1'
#7550000
0'
#7600000
1'
#7650000
0'
#7700000
1'
#7750000
0'
#7800000
1'
#7850000
0'
#7900000
1'
#7950000
0'
1*
#8000000
1'
#8050000
0'
0*
#8100000
1'
#8150000
0'
#8200000
1'
#8250000
0'
#8300000
1'
#8350000
0'
1+
#8400000
1"
1'
#8450000
0'
0+
#8500000
0"
1'
#8550000
0'
#8600000
1'
#8650000
0'
#8700000
1'
#8750000
0'
#8800000
1'
#8850000
0'
#8900000
1'
#8950000
0'
#8975000
0&
#9000000
0-
1.
b101101 %
b101101 ,
0$
1'
#9050000
0'
#9075000
1&
#9100000
b0 %
b0 ,
1$
1'
#9150000
0'
#9200000
1'
#9250000
0'
#9300000
1'
#9350000
0'
#9400000
1'
#9450000
0'
#9500000
1'
#9550000
0'
#9600000
1'
#9650000
0'
#9700000
1'
#9750000
0'
#9800000
1'
#9850000
0'
#9900000
1'
#9950000
0'
#10000000
1'
#10050000
0'
#10075000
0&
#10100000
b101101 %
b101101 ,
0$
1'
#10150000
0'
#10175000
1&
#10200000
b0 %
b0 ,
1$
1'
#10250000
0'
#10300000
1'
#10350000
0'
#10400000
1'
#10450000
0'
#10500000
1'
#10550000
0'
#10600000
1'
#10650000
0'
#10700000
1'
#10750000
0'
#10800000
1'
#10850000
0'
#10900000
1'
#10950000
0'
#11000000
1'
#11050000
0'
#11100000
1'
#11150000
0'
#11175000
0&
#11200000
b101101 %
b101101 ,
0$
1'
#11250000
0'
#11275000
1&
#11300000
b0 %
b0 ,
1$
1'
#11350000
0'
#11400000
1'
#11450000
0'
#11500000
1'
#11550000
0'
#11600000
1'
#11650000
0'
#11700000
1'
#11750000
0'
#11800000
1'
#11850000
0'
#11900000
1'
#11950000
0'
#12000000
1'
#12050000
0'
#12100000
1'
#12150000
0'
#12200000
1'
#12250000
0'
#12275000
0&
#12300000
b101101 %
b101101 ,
0$
1'
#12350000
0'
#12375000
1&
#12400000
b0 %
b0 ,
1$
1'
#12450000
0'
#12500000
1'
#12550000
0'
#12600000
1'
#12650000
0'
#12700000
1'
#12750000
0'
#12800000
1'
#12850000
0'
#12900000
1'
#12950000
0'
#13000000
1'
#13050000
0'
#13100000
1'
#13150000
0'
#13200000
1'
#13250000
0'
#13300000
1'
#13350000
0'
#13375000
0&
#13400000
b101101 %
b101101 ,
0$
1'
#13450000
0'
#13475000
1&
#13500000
b0 %
b0 ,
1$
1'
#13550000
0'
#13600000
1'
#13650000
0'
#13700000
1'
#13750000
0'
#13800000
1'
#13850000
0'
#13900000
1'
#13950000
0'
#14000000
1'
#14050000
0'
#14100000
1"
1'
1*
#14150000
0'
#14200000
0"
1'
0*
#14250000
0'
#14300000
1'
#14350000
0'
#14400000
1'
#14450000
0'
#14500000
1"
1'
1*
#14550000
0'
#14600000
0"
1'
0*
#14650000
0'
#14700000
1'
#14750000
0'
#14800000
1'
#14850000
0'
#14900000
1'
1+
#14950000
0'
#15000000
1'
0+
#15050000
0'
#15100000
1'
#15150000
0'
#15200000
1'
#15250000
0'
#15300000
1'
#15350000
0'
#15400000
1'
#15450000
0'
#15500000
1"
1'
1*
#15550000
0'
#15600000
0"
1'
0*
