spi_final/asy_fifo_output.v
`timescale 1 ns / 1 ps
module asy_fifo_output(data_out,spi_cs, wdata,clk,control_clk_miso,rst,read_req);
   parameter MEMDEPTH = 30;
  parameter DSIZE = 8;
  parameter ASIZE = 4;
  output [119:0] data_out;
  output spi_cs;
  input control_clk_miso;
  input  [DSIZE-1:0] wdata;
  input               clk,read_req;
  input              rst;
  reg    [ASIZE-1:0]   w_pointer;
  reg    [ASIZE-1:0]   r_pointer;
  reg [DSIZE-1:0] rdata;
  reg winc,rinc;
 reg spi_cs;
  reg w_full,r_empty;
  reg read_en;
 
  reg [DSIZE-1:0] ex_mem[MEMDEPTH-1:0];
 reg [119:0] data_out;

  initial
      begin
       rdata<=8'd0;
       read_en<=0;
       w_pointer <= 5'b0000;
       r_pointer <= 5'b0000;
       w_full <=0;
       r_empty<=1;
       spi_cs<=0;
       data_out<=120'd0;
      end

 always @(posedge read_req)
      if(w_full==1)
        begin
           read_en<=1;
        end
      else
         begin
           read_en<=0;
         end
 
 
always @(posedge clk)

     if (w_full==0)
	 begin
	  spi_cs<=0;
	  r_empty<=0;
	  end
	  else if (r_empty==1)
	  begin
	  spi_cs<=0;
	  end
    else
	 begin
	  spi_cs<=1;
	 
	 end
	  

// control read and write operation
always @(posedge clk)
     if(read_en==1 && w_full==1)
         begin	
           winc<=0;
           rinc<=1;
	                                                                //$display ("at time %0d winc=%b rinc=%b", $time, winc,rinc);
        end
     else if (w_full==0) 
        begin
           winc<=1;
           rinc<=0;
                                                             //$display ("at time %0d winc=%b rinc=%b", $time, winc,rinc);
        end
     else
        begin
          winc<=0;
          rinc<=0;
        end

// control_clk_miso use for writing in Fifo

 always @(posedge control_clk_miso )

  
      if (!rst) 
         begin
           w_pointer <= 4'b0000;
        
	end

     else if(winc==1 && w_pointer==4'b1111)
       begin
	   w_full=1;		 
           w_pointer <= 4'b0000;
	  
        end

     else if (winc==1 && !w_full)
   
           begin
   
            w_pointer= w_pointer+1;

            ex_mem[w_pointer]<=  wdata;
 

//$display ("at time %0d w_pointer=%b", $time, w_pointer);
//$display ("at time %0d  ex_mem[w_pointer]=%d", $time,  ex_mem[w_pointer]);
  
           end
    else if (r_empty==1)
           begin
	     w_full<=0;
	   end

// clk use for reading from fifo

always @(posedge clk)

 if(rinc==1 && r_pointer==4'b1111)
         begin
		 r_empty=1;
		 r_pointer <= 4'b0000;
		 $display ("at time %0d rempty=%b", $time, r_empty);
		// w_full=0;
		    end

 else if(rinc==1 && !r_empty)
    begin

      r_pointer= r_pointer+1;

   rdata=ex_mem[r_pointer];
   
$display ("at time %0d rdata=%b", $time, rdata);
end

// making a 120 bit buffer output and output data deliver without delay---

always @(posedge clk)

 if(r_pointer==15)
begin

data_out[7:0]=ex_mem[1];
data_out[15:8]=ex_mem[2];
data_out[23:16]=ex_mem[3];
data_out[31:24]=ex_mem[4];
data_out[39:32]=ex_mem[5];
data_out[47:40]=ex_mem[6];
data_out[55:48]=ex_mem[7];
data_out[63:56]=ex_mem[8];
data_out[71:64]=ex_mem[9];
data_out[79:72]=ex_mem[10];
data_out[87:80]=ex_mem[11];
data_out[95:88]=ex_mem[12];
data_out[103:96]=ex_mem[13];
data_out[111:104]=ex_mem[14];
data_out[119:112]=ex_mem[15];


$display ("at time %0d data_out=%b", $time, data_out);
end



 //  data_out=rdata;
//data_out=data_out<<8;
	
  endmodule

spi_final/asy_fifo_output_test.v
  `timescale 1 ns / 1 ps
module asy_fifo_output_test;
  
  parameter MEMDEPTH = 30;

reg [7:0] wdata;
 reg  clk, rst,read_req,spi_clk,control_clk_miso;
 wire [119:0] data_out;
 wire spi_cs;

//`define stim #10 wdata=8'd
event end_first_pass;


    asy_fifo_output A1(data_out,spi_cs, wdata,clk,control_clk_miso ,rst,read_req);




initial begin
$dumpfile("asy_fifo_output_waveform_result.vcd");
$dumpvars(0,asy_fifo_output_test);
end

/*initial begin
		$shm_open("asy_fifo_output.shm");
		$shm_probe("AS"); // AS = all signals
	end

*/
initial
begin
    
    rst=0;
      control_clk_miso=0; 
  
    clk=0;
 read_req=0;
#400
read_req=~read_req;
#50
read_req=~read_req;

#1000
read_req=~read_req;
#50
read_req=~read_req;
#1000
read_req=~read_req;
#50
read_req=~read_req;

    
end


always  #50 control_clk_miso=~control_clk_miso;
always  #10 clk= ~clk;



always
begin
#50 ;
$display ("at time %0d clk = %b   control_clk_miso = %b rst= %b  read_req=%b wdata=%d  datat_out=%b ", $time,      
     clk,control_clk_miso,rst,read_req,wdata,data_out);

end

initial
begin
begin

#50
rst=1;
        
        wdata=8'd1;    

    #100 wdata=8'd2;
    #100 wdata=8'd20;
    #100 wdata=8'd30;
    #100 wdata=8'd40;
 
 
 #100 wdata=8'd50;
 #100 wdata=8'd60;
 #100 wdata=8'd70;
 
    

 #100 wdata=8'd100;
    #100 wdata=8'd120;
 #100 wdata=8'd130;
 #100 wdata=8'd140;
 #100 wdata=8'd150;


#4000 read_req=1;
 #100 wdata=8'd55;
 #100 wdata=8'd200;
 #100 wdata=8'd15;

 #100 wdata=8'd16;
    #100 wdata=8'd17;
 #100 wdata=8'd18;
 #100 wdata=8'd19;
 #100 wdata=8'd20;

#5000 ->end_first_pass;
   end
   $finish;
end
endmodule

spi_final/asy_fifo_output_waveform_result.vcd
$date
    Jul 19, 2016  14:59:44
$end
$version
    Tool:	VERILOG-XL	08.20.001-d
$end
$timescale
     1ps
$end

$scope module asy_fifo_output_test $end
$var parameter 32 !    MEMDEPTH  $end
$var reg       8 "    wdata [7:0] $end
$var reg       1 #    clk  $end
$var reg       1 $    rst  $end
$var reg       1 %    read_req  $end
$var reg       1 &    spi_clk  $end
$var reg       1 '    control_clk_miso  $end
$var wire     120 (    data_out [119:0] $end
$var wire      1 )    spi_cs  $end
$var event     1 *    end_first_pass  $end

$scope module A1 $end
$var parameter 32 +    MEMDEPTH  $end
$var parameter 32 ,    DSIZE  $end
$var parameter 32 -    ASIZE  $end
$var wire      1 .    control_clk_miso  $end
$var wire      8 /    wdata [7:0] $end
$var wire      1 0    clk  $end
$var wire      1 1    read_req  $end
$var wire      1 2    rst  $end
$var reg       4 3    w_pointer [3:0] $end
$var reg       4 4    r_pointer [3:0] $end
$var reg       8 5    rdata [7:0] $end
$var reg       1 6    winc  $end
$var reg       1 7    rinc  $end
$var reg       1 8    spi_cs  $end
$var reg       1 9    w_full  $end
$var reg       1 :    r_empty  $end
$var reg       1 ;    read_en  $end
$var reg      120 <    data_out [119:0] $end
$upscope $end

$upscope $end

$enddefinitions $end
$dumpvars
b00000000000000000000000000011110 !
bxxxxxxxx "
0#
0$
0%
x&
0'
b000000000000000000000000000000000000000000000000000000000000000000000000000000000000000000000000000000000000000000000000 (
0)
x*
b00000000000000000000000000011110 +
b00000000000000000000000000001000 ,
b00000000000000000000000000000100 -
0.
bxxxxxxxx /
00
01
02
b0000 3
b0000 4
b00000000 5
x6
x7
08
09
1:
0;
b000000000000000000000000000000000000000000000000000000000000000000000000000000000000000000000000000000000000000000000000 <
$end
#10000
1#
10
16
07
0:
#20000
0#
00
#30000
1#
10
#40000
0#
00
#50000
1'
1$
b00000001 "
1#
1.
12
b00000001 /
10
b0001 3
#60000
0#
00
#70000
1#
10
#80000
0#
00
#90000
1#
10
#100000
0'
0#
0.
00
#110000
1#
10
#120000
0#
00
#130000
1#
10
#140000
0#
00
#150000
b00000010 "
1'
1#
b00000010 /
1.
10
b0010 3
#160000
0#
00
#170000
1#
10
#180000
0#
00
#190000
1#
10
#200000
0'
0#
0.
00
#210000
1#
10
#220000
0#
00
#230000
1#
10
#240000
0#
00
#250000
b00010100 "
1'
1#
b00010100 /
1.
10
b0011 3
#260000
0#
00
#270000
1#
10
#280000
0#
00
#290000
1#
10
#300000
0'
0#
0.
00
#310000
1#
10
#320000
0#
00
#330000
1#
10
#340000
0#
00
#350000
b00011110 "
1'
1#
b00011110 /
1.
10
b0100 3
#360000
0#
00
#370000
1#
10
#380000
0#
00
#390000
1#
10
#400000
1%
0'
0#
11
0.
00
#410000
1#
10
#420000
0#
00
#430000
1#
10
#440000
0#
00
#450000
b00101000 "
0%
1'
1#
b00101000 /
01
1.
10
b0101 3
#460000
0#
00
#470000
1#
10
#480000
0#
00
#490000
1#
10
#500000
0'
0#
0.
00
#510000
1#
10
#520000
0#
00
#530000
1#
10
#540000
0#
00
#550000
b00110010 "
1'
1#
b00110010 /
1.
10
b0110 3
#560000
0#
00
#570000
1#
10
#580000
0#
00
#590000
1#
10
#600000
0'
0#
0.
00
#610000
1#
10
#620000
0#
00
#630000
1#
10
#640000
0#
00
#650000
b00111100 "
1'
1#
b00111100 /
1.
10
b0111 3
#660000
0#
00
#670000
1#
10
#680000
0#
00
#690000
1#
10
#700000
0'
0#
0.
00
#710000
1#
10
#720000
0#
00
#730000
1#
10
#740000
0#
00
#750000
b01000110 "
1'
1#
b01000110 /
1.
10
b1000 3
#760000
0#
00
#770000
1#
10
#780000
0#
00
#790000
1#
10
#800000
0'
0#
0.
00
#810000
1#
10
#820000
0#
00
#830000
1#
10
#840000
0#
00
#850000
b01100100 "
1'
1#
b01100100 /
1.
10
b1001 3
#860000
0#
00
#870000
1#
10
#880000
0#
00
#890000
1#
10
#900000
0'
0#
0.
00
#910000
1#
10
#920000
0#
00
#930000
1#
10
#940000
0#
00
#950000
b01111000 "
1'
1#
b01111000 /
1.
10
b1010 3
#960000
0#
00
#970000
1#
10
#980000
0#
00
#990000
1#
10
#1000000
0'
0#
0.
00
#1010000
1#
10
#1020000
0#
00
#1030000
1#
10
#1040000
0#
00
#1050000
b10000010 "
1'
1#
b10000010 /
1.
10
b1011 3
#1060000
0#
00
#1070000
1#
10
#1080000
0#
00
#1090000
1#
10
#1100000
0'
0#
0.
00
#1110000
1#
10
#1120000
0#
00
#1130000
1#
10
#1140000
0#
00
#1150000
b10001100 "
1'
1#
b10001100 /
1.
10
b1100 3
#1160000
0#
00
#1170000
1#
10
#1180000
0#
00
#1190000
1#
10
#1200000
0'
0#
0.
00
#1210000
1#
10
#1220000
0#
00
#1230000
1#
10
#1240000
0#
00
#1250000
b10010110 "
1'
1#
b10010110 /
1.
10
b1101 3
#1260000
0#
00
#1270000
1#
10
#1280000
0#
00
#1290000
1#
10
#1300000
0'
0#
0.
00
#1310000
1#
10
#1320000
0#
00
#1330000
1#
10
#1340000
0#
00
#1350000
1'
1#
1.
10
b1110 3
#1360000
0#
00
#1370000
1#
10
#1380000
0#
00
#1390000
1#
10
#1400000
0'
0#
0.
00
#1410000
1#
10
#1420000
0#
00
#1430000
1#
10
#1440000
0#
00
#1450000
1%
1'
1#
11
1.
10
b1111 3
#1460000
0#
00
#1470000
1#
10
#1480000
0#
00
#1490000
1#
10
#1500000
0%
0'
0#
01
0.
00
#1510000
1#
10
#1520000
0#
00
#1530000
1#
10
#1540000
0#
00
#1550000
1'
1#
1.
10
19
b0000 3
18
06
1)
