spi_final/clk_div.v
`timescale 1 ns / 1 ps
module clk_div (spi_clk, m_clk, spi_cs, nrst);
	input nrst, spi_cs, m_clk;
	output spi_clk;

	//wire nrst, spi_clk_en, m_clk;
	reg spi_clk;
	reg [0:3] counter;

	initial
	begin 
		counter <= 4'b1000;
		spi_clk<=0;
		
	end
	always @(posedge m_clk )begin
		if (!nrst) begin 
			spi_clk <= 1'b0; 
			counter <= 4'b0000;
		end
		else begin
			if(!spi_cs) begin 
				if (counter == 4'b1001)
				   begin
					spi_clk <= !spi_clk;
					counter <= 4'b0000;
				   end // End of counter if
				else
					counter <= counter + 4'b0001;
			end // End of spi_clk_en if
		end // End of else
	end // End of always block

	
endmodule

spi_final/clk_div_test.v
`timescale 1 ns / 1 ps
module clk_div_test();
	reg nrst, spi_cs, m_clk;
	wire spi_clk;
event end_first_pass;
	clk_div c0(spi_clk, m_clk, spi_cs, nrst);
	
	

	// Setting the initial input values
	initial
	begin
		nrst = 0;
		m_clk = 1;
	    spi_cs<=1;
	end
always #50 m_clk = ~m_clk;
	// Displaying signals as graphical waveforms //
	/*initial begin
		$shm_open("clk_div.shm");
		$shm_probe("AS"); // AS = all signals
	end
*/
initial 
	begin
      $dumpfile("clk_div_waveform_result.vcd");
     $dumpvars(0,clk_div_test);
      end    

	initial begin
		$display ("time m_clk, spi_cs, nrst, spi_clk");
		$monitor ("at time %0d nrst = %b spi_cs = %b m_clk = %b spi_clk=%d", $time, nrst, spi_cs, m_clk, spi_clk);
	end

	initial
	begin
	begin
	#100
	spi_cs<=0;
	nrst <= 1;
	#1000
    nrst<=1;
		
#5000 ->end_first_pass;
   end
   $finish;
		
	end
endmodule

spi_final/clk_div_waveform_result.vcd
$date
	Wed Jul 13 22:43:13 2016
$end
$version
	Icarus Verilog
$end
$timescale
	1ps
$end
$scope module clk_div_test $end
$var event 1 ! end_first_pass $end
$var wire 1 " spi_clk $end
$var reg 1 # m_clk $end
$var reg 1 $ nrst $end
$var reg 1 % spi_cs $end
$scope module c0 $end
$var wire 1 # m_clk $end
$var wire 1 $ nrst $end
$var wire 1 % spi_cs $end
$var reg 4 & counter [0:3] $end
$var reg 1 " spi_clk $end
$upscope $end
$upscope $end
$enddefinitions $end
#0
$dumpvars
b0 &
1%
0$
1#
0"
1!
$end
#50000
0#
#100000
1$
0%
1#
#150000
0#
#200000
b1 &
1#
#250000
0#
#300000
b10 &
1#
#350000
0#
#400000
b11 &
1#
#450000
0#
#500000
b100 &
1#
#550000
0#
#600000
b101 &
1#
#650000
0#
#700000
b110 &
1#
#750000
0#
#800000
b111 &
1#
#850000
0#
#900000
b1000 &
1#
#950000
0#
#1000000
b1001 &
1#
#1050000
0#
#1100000
b0 &
1"
1#
#1150000
0#
#1200000
b1 &
1#
#1250000
0#
#1300000
b10 &
1#
#1350000
0#
#1400000
b11 &
1#
#1450000
0#
#1500000
b100 &
1#
#1550000
0#
#1600000
b101 &
1#
#1650000
0#
#1700000
b110 &
1#
#1750000
0#
#1800000
b111 &
1#
#1850000
0#
#1900000
b1000 &
1#
#1950000
0#
#2000000
b1001 &
1#
#2050000
0#
#2100000
b0 &
0"
1#
#2150000
0#
#2200000
b1 &
1#
#2250000
0#
#2300000
b10 &
1#
#2350000
0#
#2400000
b11 &
1#
#2450000
0#
#2500000
b100 &
1#
#2550000
0#
#2600000
b101 &
1#
#2650000
0#
#2700000
b110 &
1#
#2750000
0#
#2800000
b111 &
1#
#2850000
0#
#2900000
b1000 &
1#
#2950000
0#
#3000000
b1001 &
1#
#3050000
0#
#3100000
b0 &
1"
1#
#3150000
0#
#3200000
b1 &
1#
#3250000
0#
#3300000
b10 &
1#
#3350000
0#
#3400000
b11 &
1#
#3450000
0#
#3500000
b100 &
1#
#3550000
0#
#3600000
b101 &
1#
#3650000
0#
#3700000
b110 &
1#
#3750000
0#
#3800000
b111 &
1#
#3850000
0#
#3900000
b1000 &
1#
#3950000
0#
#4000000
b1001 &
1#
#4050000
0#
#4100000
b0 &
0"
1#
#4150000
0#
#4200000
b1 &
1#
#4250000
0#
#4300000
b10 &
1#
#4350000
0#
#4400000
b11 &
1#
#4450000
0#
#4500000
b100 &
1#
#4550000
0#
#4600000
b101 &
1#
#4650000
0#
#4700000
b110 &
1#
#4750000
0#
#4800000
b111 &
1#
#4850000
0#
#4900000
b1000 &
1#
#4950000
0#
#5000000
b1001 &
1#
#5050000
0#
#5100000
b0 &
1"
1#
#5150000
0#
#5200000
b1 &
1#
#5250000
0#
#5300000
b10 &
1#
#5350000
0#
#5400000
b11 &
1#
#5450000
0#
#5500000
b100 &
1#
#5550000
0#
#5600000
b101 &
1#
#5650000
0#
#5700000
b110 &
1#
#5750000
0#
#5800000
b111 &
1#
#5850000
0#
#5900000
b1000 &
1#
#5950000
0#
#6000000
b1001 &
1#
#6050000
0#
#6100000
b0 &
0"
1#
1!
