spi_final/asy_fifo_output.v
`timescale 1 ns / 1 ps
module asy_fifo_output(data_out,spi_cs, wdata,clk,control_clk_miso,rst,read_req);
   parameter MEMDEPTH = 30;
  parameter DSIZE = 8;
  parameter ASIZE = 4;
  output [119:0] data_out;
  output spi_cs;
  input control_clk_miso;
  input  [DSIZE-1:0] wdata;
  input               clk,read_req;
  input              rst;
  reg    [ASIZE-1:0]   w_pointer;
  reg    [ASIZE-1:0]   r_pointer;
  reg [DSIZE-1:0] rdata;
  reg winc,rinc;
 reg spi_cs;
  reg w_full,r_empty;
  reg read_en;
 
  reg [DSIZE-1:0] ex_mem[MEMDEPTH-1:0];
 reg [119:0] data_out;

  initial
      begin
       rdata<=8'd0;
       read_en<=0;
       w_pointer <= 5'b0000;
       r_pointer <= 5'b0000;
       w_full <=0;
       r_empty<=1;
       spi_cs<=0;
       data_out<=120'd0;
      end

 always @(posedge read_req)
      if(w_full==1)
        begin
           read_en<=1;
        end
      else
         begin
           read_en<=0;
         end
 
 
always @(posedge clk)

     if (w_full==0)
	 begin
	  spi_cs<=0;
	  r_empty<=0;
	  end
	  else if (r_empty==1)
	  begin
	  spi_cs<=0;
	  end
    else
	 begin
	  spi_cs<=1;
	 
	 end
	  

// control read and write operation
always @(posedge clk)
     if(read_en==1 && w_full==1)
         begin	
           winc<=0;
           rinc<=1;
	                                                                //$display ("at time %0d winc=%b rinc=%b", $time, winc,rinc);
        end
     else if (w_full==0) 
        begin
           winc<=1;
           rinc<=0;
                                                             //$display ("at time %0d winc=%b rinc=%b", $time, winc,rinc);
        end
     else
        begin
          winc<=0;
          rinc<=0;
        end

// control_clk_miso use for writing in Fifo

 always @(posedge control_clk_miso )

  
      if (!rst) 
         begin
           w_pointer <= 4'b0000;
        
	end

     else if(winc==1 && w_pointer==4'b1111)
       begin
	   w_full=1;		 
           w_pointer <= 4'b0000;
	  
        end

     else if (winc==1 && !w_full)
   
           begin
   
            w_pointer= w_pointer+1;

            ex_mem[w_pointer]<=  wdata;
 

//$display ("at time %0d w_pointer=%b", $time, w_pointer);
//$display ("at time %0d  ex_mem[w_pointer]=%d", $time,  ex_mem[w_pointer]);
  
           end
    else if (r_empty==1)
           begin
	     w_full<=0;
	   end

// clk use for reading from fifo

always @(posedge clk)

 if(rinc==1 && r_pointer==4'b1111)
         begin
		 r_empty=1;
		 r_pointer <= 4'b0000;
		 $display ("at time %0d rempty=%b", $time, r_empty);
		// w_full=0;
		    end

 else if(rinc==1 && !r_empty)
    begin

      r_pointer= r_pointer+1;

   rdata=ex_mem[r_pointer];
   
$display ("at time %0d rdata=%b", $time, rdata);
end

// making a 120 bit buffer output and output data deliver without delay---

always @(posedge clk)

 if(r_pointer==15)
begin

data_out[7:0]=ex_mem[1];
data_out[15:8]=ex_mem[2];
data_out[23:16]=ex_mem[3];
data_out[31:24]=ex_mem[4];
data_out[39:32]=ex_mem[5];
data_out[47:40]=ex_mem[6];
data_out[55:48]=ex_mem[7];
data_out[63:56]=ex_mem[8];
data_out[71:64]=ex_mem[9];
data_out[79:72]=ex_mem[10];
data_out[87:80]=ex_mem[11];
data_out[95:88]=ex_mem[12];
data_out[103:96]=ex_mem[13];
data_out[111:104]=ex_mem[14];
data_out[119:112]=ex_mem[15];


$display ("at time %0d data_out=%b", $time, data_out);
end



 //  data_out=rdata;
//data_out=data_out<<8;
	
  endmodule

spi_final/spi_miso.v
`timescale 1 ns / 1 ps
module spi_miso (control_clk_miso,spi_mosi_out,spi_miso_out,spi_cs,spi_clk,spi_miso_in);

 parameter DSIZE = 8;
output control_clk_miso;
output spi_mosi_out;
 output  [DSIZE-1:0] spi_miso_out;
 input spi_cs;
 input  spi_clk;
input spi_miso_in;

	
reg control_clk_miso;
reg [DSIZE-1:0] spi_miso_out;
reg spi_mosi_out;
reg [DSIZE-1:0] data,final_data,add_byte;
reg[2:0] point,point_add;
      
reg [2:0] control;

	



initial
            begin
              spi_miso_out<=0;
	           point<=3'b000;
		       point_add<=3'b000;
               data<=8'd0;
			   final_data<=8'd0;
               control<=3'b010;
               control_clk_miso<=1'b0;
             
			   add_byte<=10000101; // address byte
 
		                end
	


// create control clock for sending data to asy_fifo_output


always@(posedge spi_clk)


        begin
           if(control==3'd7)
               begin
   		
                        control_clk_miso<=~control_clk_miso;
   		       control<=0;
   
			end
		else
				
                       begin
			control=control+1;
		            end
        end
	


// spi_clk read data bit by bit from slave and keep it in final data

always @(posedge spi_clk)

	 if(spi_cs) 
             begin
           spi_mosi_out<=0;
            point<=0;
           data<= 8'd0;
               
               end

	  else if (!spi_cs )
	   begin
	   if(point_add==3'b111)
	       begin
	          if (point==3'b111)
                   begin      
                    final_data<=data;
                         point<=0;
                     	point_add<=0;
					 
                    end
               else
                   begin
		    data[point]<=spi_miso_in;	
		
             spi_mosi_out<=0;
 $display ("at time %0d data=%b  ", $time, data);
 $display ("at time %0d point=%d  ", $time, point);

                     point<= point+1;

		    end
		
			end
	 else
	 begin
	  spi_mosi_out<=add_byte[point_add];	  /// assign address byte.... adress byte send through mosi
		data<=8'd0;

 $display ("at time %0d spi_mosi_out=%b  ", $time, spi_mosi_out);
 $display ("at time %0d point_add=%d  ", $time, point_add);

                     point_add<= point_add+1;
					 end
	 
		   end 
 // control clock control final data and push it to spi_miso_out

always @(posedge control_clk_miso)


if(spi_cs)
spi_miso_out<=0;
else                
   begin

               
                spi_miso_out<=final_data;
                 
            
          		end	

		

		endmodule

spi_final/clk_div.v
`timescale 1 ns / 1 ps
module clk_div (spi_clk, m_clk, spi_cs, nrst);
	input nrst, spi_cs, m_clk;
	output spi_clk;

	//wire nrst, spi_clk_en, m_clk;
	reg spi_clk;
	reg [0:3] counter;

	initial
	begin 
		counter <= 4'b1000;
		spi_clk<=0;
		
	end
	always @(posedge m_clk )begin
		if (!nrst) begin 
			spi_clk <= 1'b0; 
			counter <= 4'b0000;
		end
		else begin
			if(!spi_cs) begin 
				if (counter == 4'b1001)
				   begin
					spi_clk <= !spi_clk;
					counter <= 4'b0000;
				   end // End of counter if
				else
					counter <= counter + 4'b0001;
			end // End of spi_clk_en if
		end // End of else
	end // End of always block

	
endmodule

spi_final/final_O.v
`timescale 1 ns / 1 ps

`include "asy_fifo_output.v"
`include "spi_miso.v"
`include "clk_div.v"
module  spi_final_O (data_out,spi_mosi_out,spi_miso_in,read_req,m_clk,n_reset);



output [119:0] data_out;
output spi_mosi_out;
input m_clk,read_req;
input n_reset;

input spi_miso_in;

wire[119:0] data_out;


wire [7:0] spi_miso_out;

    wire control_clk_miso,spi_clk,spi_cs;




clk_div A(.spi_clk(spi_clk),.m_clk(m_clk),.spi_cs(spi_cs),.nrst(n_reset)); // spi_cs control spi_clk by spi_clk enable

// input (spi_mosi_out,m_clk,n_reset,spi_cs,data_in,data_av);

//spi_mosi I2(.control_clk(control_clk),.spi_mosi_out(spi_mosi_out),.spi_cs(spi_cs),.spi_clk(spi_clk),.n_reset(n_reset),.spi_mosi_in(spi_mosi_in));

//asy_fifo_input I1(.data_to_mosi(spi_mosi_in), .wdata(data_in),.clk(m_clk),.rst(n_reset),.data_av(data_av),.control_clk(control_clk));



//output


spi_miso O2(.control_clk_miso(control_clk_miso),.spi_mosi_out(spi_mosi_out),.spi_miso_out(spi_miso_out),.spi_cs(spi_cs),.spi_clk(spi_clk),.spi_miso_in(spi_miso_in));

asy_fifo_output O1(.data_out(data_out),.spi_cs(spi_cs) ,.wdata(spi_miso_out),.clk(m_clk),.control_clk_miso(control_clk_miso),.rst(n_reset),.read_req(read_req));






initial
begin


end
endmodule

spi_final/Synthesize/FINAL_O/final_test_O.v
`timescale 1 ns / 1 ps
module final_test_O;


reg m_clk;
reg n_reset;
reg  spi_miso_in;
wire[119:0] data_out;
wire spi_mosi_out;
reg read_req;

event end_first_pass;
     spi_final_O T(data_out,spi_mosi_out,spi_miso_in,read_req,m_clk,n_reset);

always #50 m_clk = ~m_clk;

	// Setting the initial input values
	initial
	begin
	m_clk=0;
       
n_reset=0;

read_req<=0; 
   
	

	end
	
	/*initial 
	begin
      $dumpfile("final_O_waveform_result.vcd");
     $dumpvars(0,final_test_O);
      end */   
initial begin
		$shm_open("final_O.shm");
		$shm_probe("AS"); // AS = all signals
	end
	initial begin
		$display ("time spi_miso_in, n_reset,m_clk,read_req,data_out");
		$monitor ("at time %0d spi_mosi_out=%b spi_miso_in =%b n_reset = %b  m_clk = %b  read_req =%b data_out=%b", $time, spi_mosi_out,spi_miso_in,n_reset,m_clk, read_req,data_out);
	end





initial
begin

begin
 #2500
n_reset=1;


spi_miso_in =1'b1;
#2000 spi_miso_in =1'b0;
#2000 spi_miso_in =1'b0;
#2000 spi_miso_in =1'b0;
#2000 spi_miso_in =1'b0;
#2000 spi_miso_in =1'b0;
#2000 spi_miso_in =1'b0;
#2000 spi_miso_in =1'b0;


#2000

 spi_miso_in =1'b0;
#2000 spi_miso_in =1'b1;
#2000 spi_miso_in =1'b0;
#2000 spi_miso_in =1'b0;
#2000 spi_miso_in =1'b0;
#2000 spi_miso_in =1'b0;
#2000 spi_miso_in =1'b0;
#2000 spi_miso_in =1'b0;

#2000




 spi_miso_in =1'b1;
#2000 spi_miso_in =1'b1;
#2000 spi_miso_in =1'b0;
#2000 spi_miso_in =1'b0;
#2000 spi_miso_in =1'b0;
#2000 spi_miso_in =1'b0;
#2000 spi_miso_in =1'b0;
#2000 spi_miso_in =1'b1;

#2000




 spi_miso_in =1'b0;
#2000 spi_miso_in =1'b0;
#2000 spi_miso_in =1'b1;
#2000 spi_miso_in =1'b0;
#2000 spi_miso_in =1'b0;
#2000 spi_miso_in =1'b0;
#2000 spi_miso_in =1'b0;
#2000 spi_miso_in =1'b1;

#2000




 spi_miso_in =1'b1;
#2000 spi_miso_in =1'b0;
#2000 spi_miso_in =1'b1;
#2000 spi_miso_in =1'b0;
#2000 spi_miso_in =1'b0;
#2000 spi_miso_in =1'b0;
#2000 spi_miso_in =1'b0;
#2000 spi_miso_in =1'b1;

#2000




 spi_miso_in =1'b1;
#2000 spi_miso_in =1'b1;
#2000 spi_miso_in =1'b1;
#2000 spi_miso_in =1'b0;
#2000 spi_miso_in =1'b0;
#2000 spi_miso_in =1'b0;
#2000 spi_miso_in =1'b0;
#2000 spi_miso_in =1'b1;

#2000




 spi_miso_in =1'b0;
#2000 spi_miso_in =1'b0;
#2000 spi_miso_in =1'b0;
#2000 spi_miso_in =1'b1;
#2000 spi_miso_in =1'b0;
#2000 spi_miso_in =1'b0;
#2000 spi_miso_in =1'b0;
#2000 spi_miso_in =1'b1;

#2000




 spi_miso_in =1'b1;
#2000 spi_miso_in =1'b0;
#2000 spi_miso_in =1'b0;
#2000 spi_miso_in =1'b1;
#2000 spi_miso_in =1'b0;
#2000 spi_miso_in =1'b0;
#2000 spi_miso_in =1'b0;
#2000 spi_miso_in =1'b1;

#2000




 spi_miso_in =1'b0;
#2000 spi_miso_in =1'b1;
#2000 spi_miso_in =1'b0;
#2000 spi_miso_in =1'b1;
#2000 spi_miso_in =1'b0;
#2000 spi_miso_in =1'b0;
#2000 spi_miso_in =1'b0;
#2000 spi_miso_in =1'b1;

#2000




 spi_miso_in =1'b1;
#2000 spi_miso_in =1'b1;
#2000 spi_miso_in =1'b0;
#2000 spi_miso_in =1'b1;
#2000 spi_miso_in =1'b0;
#2000 spi_miso_in =1'b0;
#2000 spi_miso_in =1'b0;
#2000 spi_miso_in =1'b1;

#2000




 spi_miso_in =1'b0;
#2000 spi_miso_in =1'b0;
#2000 spi_miso_in =1'b1;
#2000 spi_miso_in =1'b1;
#2000 spi_miso_in =1'b0;
#2000 spi_miso_in =1'b0;
#2000 spi_miso_in =1'b0;
#2000 spi_miso_in =1'b1;

#2000




 spi_miso_in =1'b1;
#2000 spi_miso_in =1'b0;
#2000 spi_miso_in =1'b1;
#2000 spi_miso_in =1'b1;
#2000 spi_miso_in =1'b0;
#2000 spi_miso_in =1'b0;
#2000 spi_miso_in =1'b0;
#2000 spi_miso_in =1'b1;

#2000




 spi_miso_in =1'b0;
#2000 spi_miso_in =1'b1;
#2000 spi_miso_in =1'b1;
#2000 spi_miso_in =1'b1;
#2000 spi_miso_in =1'b0;
#2000 spi_miso_in =1'b0;
#2000 spi_miso_in =1'b0;
#2000 spi_miso_in =1'b1;

#2000




 spi_miso_in =1'b1;
#2000 spi_miso_in =1'b1;
#2000 spi_miso_in =1'b1;
#2000 spi_miso_in =1'b1;
#2000 spi_miso_in =1'b0;
#2000 spi_miso_in =1'b0;
#2000 spi_miso_in =1'b0;
#2000 spi_miso_in =1'b1;

#2000




 spi_miso_in =1'b0;
#2000 spi_miso_in =1'b0;
#2000 spi_miso_in =1'b0;
#2000 spi_miso_in =1'b0;
#2000 spi_miso_in =1'b1;
#2000 spi_miso_in =1'b0;
#2000 spi_miso_in =1'b0;
#2000 spi_miso_in =1'b1;

#2000




 spi_miso_in =1'b1;
#2000 spi_miso_in =1'b0;
#2000 spi_miso_in =1'b0;
#2000 spi_miso_in =1'b0;
#2000 spi_miso_in =1'b1;
#2000 spi_miso_in =1'b0;
#2000 spi_miso_in =1'b0;
#2000 spi_miso_in =1'b1;

#2000




 spi_miso_in =1'b1;
#2000 spi_miso_in =1'b1;
#2000 spi_miso_in =1'b0;
#2000 spi_miso_in =1'b0;
#2000 spi_miso_in =1'b0;
#2000 spi_miso_in =1'b0;
#2000 spi_miso_in =1'b0;
#2000 spi_miso_in =1'b1;

#2000




 spi_miso_in =1'b1;
#2000 spi_miso_in =1'b1;
#2000 spi_miso_in =1'b0;
#2000 spi_miso_in =1'b0;
#2000 spi_miso_in =1'b0;
#2000 spi_miso_in =1'b0;
#2000 spi_miso_in =1'b0;
#2000 spi_miso_in =1'b1;

#2000




 spi_miso_in =1'b1;
#2000 spi_miso_in =1'b1;
#2000 spi_miso_in =1'b0;
#2000 spi_miso_in =1'b0;
#2000 spi_miso_in =1'b0;
#2000 spi_miso_in =1'b0;
#2000 spi_miso_in =1'b0;
#2000 spi_miso_in =1'b1;

#2000




 spi_miso_in =1'b1;
#2000 spi_miso_in =1'b1;
#2000 spi_miso_in =1'b0;
#2000 spi_miso_in =1'b0;
#2000 spi_miso_in =1'b0;
#2000 spi_miso_in =1'b0;
#2000 spi_miso_in =1'b0;
#2000 spi_miso_in =1'b1;
#2000



 spi_miso_in =1'b1;
#2000 spi_miso_in =1'b0;
#2000 spi_miso_in =1'b0;
#2000 spi_miso_in =1'b1;
#2000 spi_miso_in =1'b0;
#2000 spi_miso_in =1'b0;
#2000 spi_miso_in =1'b0;
#2000 spi_miso_in =1'b1;

#2000




 spi_miso_in =1'b0;
#2000 spi_miso_in =1'b1;
#2000 spi_miso_in =1'b0;
#2000 spi_miso_in =1'b1;
#2000 spi_miso_in =1'b0;
#2000 spi_miso_in =1'b0;
#2000 spi_miso_in =1'b0;
#2000 spi_miso_in =1'b1;

#2000




 spi_miso_in =1'b1;
#2000 spi_miso_in =1'b1;
#2000 spi_miso_in =1'b0;
#2000 spi_miso_in =1'b1;
#2000 spi_miso_in =1'b0;
#2000 spi_miso_in =1'b0;
#2000 spi_miso_in =1'b0;
#2000 spi_miso_in =1'b1;

#2000




 spi_miso_in =1'b0;
#2000 spi_miso_in =1'b0;
#2000 spi_miso_in =1'b1;
#2000 spi_miso_in =1'b1;
#2000 spi_miso_in =1'b0;
#2000 spi_miso_in =1'b0;
#2000 spi_miso_in =1'b0;
#2000 spi_miso_in =1'b1;

#2000




 spi_miso_in =1'b1;
#2000 spi_miso_in =1'b0;
#2000 spi_miso_in =1'b1;
#2000 spi_miso_in =1'b1;
#2000 spi_miso_in =1'b0;
#2000 spi_miso_in =1'b0;
#2000 spi_miso_in =1'b0;
#2000 spi_miso_in =1'b1;

#2000




 spi_miso_in =1'b0;
#2000 spi_miso_in =1'b1;
#2000 spi_miso_in =1'b1;
#2000 spi_miso_in =1'b1;
#2000 spi_miso_in =1'b0;
#2000 spi_miso_in =1'b0;
#2000 spi_miso_in =1'b0;
#2000 spi_miso_in =1'b1;

#2000




 spi_miso_in =1'b1;
#2000 spi_miso_in =1'b1;
#2000 spi_miso_in =1'b1;
#2000 spi_miso_in =1'b1;
#2000 spi_miso_in =1'b0;
#2000 spi_miso_in =1'b0;
#2000 spi_miso_in =1'b0;
#2000 spi_miso_in =1'b1;

#2000




 spi_miso_in =1'b0;
#2000 spi_miso_in =1'b0;
#2000 spi_miso_in =1'b0;
#2000 spi_miso_in =1'b0;
#2000 spi_miso_in =1'b1;
#2000 spi_miso_in =1'b0;
#2000 spi_miso_in =1'b0;
#2000 spi_miso_in =1'b1;

#2000




 spi_miso_in =1'b1;
#2000 spi_miso_in =1'b0;
#2000 spi_miso_in =1'b0;
#2000 spi_miso_in =1'b0;
#2000 spi_miso_in =1'b1;
#2000 spi_miso_in =1'b0;
#2000 spi_miso_in =1'b0;
#2000 spi_miso_in =1'b1;

#2000




 spi_miso_in =1'b1;
#2000 spi_miso_in =1'b1;
#2000 spi_miso_in =1'b0;
#2000 spi_miso_in =1'b0;
#2000 spi_miso_in =1'b0;
#2000 spi_miso_in =1'b0;
#2000 spi_miso_in =1'b0;
#2000 spi_miso_in =1'b1;

#2000




 spi_miso_in =1'b1;
#2000 spi_miso_in =1'b1;
#2000 spi_miso_in =1'b0;
#2000 spi_miso_in =1'b0;
#2000 spi_miso_in =1'b0;
#2000 spi_miso_in =1'b0;
#2000 spi_miso_in =1'b0;
#2000 spi_miso_in =1'b1;

#2000




 spi_miso_in =1'b1;
#2000 spi_miso_in =1'b1;
#2000 spi_miso_in =1'b0;
#2000 spi_miso_in =1'b0;
#2000 spi_miso_in =1'b0;
#2000 spi_miso_in =1'b0;
#2000 spi_miso_in =1'b0;
#2000 spi_miso_in =1'b1;

#2000




 spi_miso_in =1'b1;
#2000 spi_miso_in =1'b1;
#2000 spi_miso_in =1'b0;
#2000 spi_miso_in =1'b0;
#2000 spi_miso_in =1'b0;
#2000 spi_miso_in =1'b0;
#2000 spi_miso_in =1'b0;
#2000 spi_miso_in =1'b1;


read_req=0;
#400
read_req=~read_req;
#50
read_req=~read_req;

#10000
read_req=~read_req;
#50
read_req=~read_req;
#6000
read_req=~read_req;
#50
read_req=~read_req;
#10000
read_req=~read_req;
#50
read_req=~read_req;
#20000
read_req=~read_req;
#50
read_req=~read_req;


#100000 ->end_first_pass;
   end
   $finish;
end
endmodule

spi_final/final_O_waveform_result.vcd
$date
	Thu Jul 14 00:05:15 2016
$end
$version
	Icarus Verilog
$end
$timescale
	1ps
$end
$scope module final_test_O $end
$var event 1 ! end_first_pass $end
$var wire 1 " spi_mosi_out $end
$var wire 120 # data_out [119:0] $end
$var reg 1 $ m_clk $end
$var reg 1 % n_reset $end
$var reg 1 & read_req $end
$var reg 1 ' spi_miso_in $end
$scope module T $end
$var wire 1 $ m_clk $end
$var wire 1 % n_reset $end
$var wire 1 & read_req $end
$var wire 1 ' spi_miso_in $end
$var wire 1 " spi_mosi_out $end
$var wire 8 ( spi_miso_out [7:0] $end
$var wire 1 ) spi_cs $end
$var wire 1 * spi_clk $end
$var wire 120 + data_out [119:0] $end
$var wire 1 , control_clk_miso $end
$scope module A $end
$var wire 1 $ m_clk $end
$var wire 1 % nrst $end
$var wire 1 ) spi_cs $end
$var reg 4 - counter [0:3] $end
$var reg 1 * spi_clk $end
$upscope $end
$scope module O1 $end
$var wire 1 $ clk $end
$var wire 1 & read_req $end
$var wire 1 % rst $end
$var wire 8 . wdata [7:0] $end
$var wire 1 , control_clk_miso $end
$var reg 120 / data_out [119:0] $end
$var reg 1 0 r_empty $end
$var reg 4 1 r_pointer [3:0] $end
$var reg 8 2 rdata [7:0] $end
$var reg 1 3 read_en $end
$var reg 1 4 rinc $end
$var reg 1 ) spi_cs $end
$var reg 1 5 w_full $end
$var reg 4 6 w_pointer [3:0] $end
$var reg 1 7 winc $end
$upscope $end
$scope module O2 $end
$var wire 1 * spi_clk $end
$var wire 1 ) spi_cs $end
$var wire 1 ' spi_miso_in $end
$var reg 8 8 add_byte [7:0] $end
$var reg 3 9 control [2:0] $end
$var reg 1 , control_clk_miso $end
$var reg 8 : data [7:0] $end
$var reg 8 ; final_data [7:0] $end
$var reg 3 < point [2:0] $end
$var reg 3 = point_add [2:0] $end
$var reg 8 > spi_miso_out [7:0] $end
$var reg 1 " spi_mosi_out $end
$upscope $end
$upscope $end
$upscope $end
$enddefinitions $end
#0
$dumpvars
b0 >
b0 =
b0 <
b0 ;
b0 :
b10 9
b11100101 8
x7
b0 6
05
x4
03
b0 2
b0 1
10
b0 /
b0 .
b1000 -
0,
b0 +
0*
0)
b0 (
x'
0&
0%
0$
b0 #
x"
1!
$end
#50000
b0 -
00
04
17
1$
#100000
0$
#150000
1$
#200000
0$
#250000
1$
#300000
0$
#350000
1$
#400000
0$
#450000
1$
#500000
0$
#550000
1$
#600000
0$
#650000
1$
#700000
0$
#750000
1$
#800000
0$
#850000
1$
#900000
0$
#950000
1$
#1000000
0$
#1050000
1$
#1100000
0$
#1150000
1$
#1200000
0$
#1250000
1$
#1300000
0$
#1350000
1$
#1400000
0$
#1450000
1$
#1500000
0$
#1550000
1$
#1600000
0$
#1650000
1$
#1700000
0$
#1750000
1$
#1800000
0$
#1850000
1$
#1900000
0$
#1950000
1$
#2000000
0$
#2050000
1$
#2100000
0$
#2150000
1$
#2200000
0$
#2250000
1$
#2300000
0$
#2350000
1$
#2400000
0$
#2450000
1$
#2500000
0$
1'
1%
#2550000
b1 -
1$
#2600000
0$
#2650000
b10 -
1$
#2700000
0$
#2750000
b11 -
1$
#2800000
0$
#2850000
b100 -
1$
#2900000
0$
#2950000
b101 -
1$
#3000000
0$
#3050000
b110 -
1$
#3100000
0$
#3150000
b111 -
1$
#3200000
0$
#3250000
b1000 -
1$
#3300000
0$
#3350000
b1001 -
1$
#3400000
0$
#3450000
b1 =
1"
b11 9
b0 -
1*
1$
#3500000
0$
#3550000
b1 -
1$
#3600000
0$
#3650000
b10 -
1$
#3700000
0$
#3750000
b11 -
1$
#3800000
0$
#3850000
b100 -
1$
#3900000
0$
#3950000
b101 -
1$
#4000000
0$
#4050000
b110 -
1$
#4100000
0$
#4150000
b111 -
1$
#4200000
0$
#4250000
b1000 -
1$
#4300000
0$
#4350000
b1001 -
1$
#4400000
0$
#4450000
b0 -
0*
1$
#4500000
0$
0'
#4550000
b1 -
1$
#4600000
0$
#4650000
b10 -
1$
#4700000
0$
#4750000
b11 -
1$
#4800000
0$
#4850000
b100 -
1$
#4900000
0$
#4950000
b101 -
1$
#5000000
0$
#5050000
b110 -
1$
#5100000
0$
#5150000
b111 -
1$
#5200000
0$
#5250000
b1000 -
1$
#5300000
0$
#5350000
b1001 -
1$
#5400000
0$
#5450000
b10 =
0"
b100 9
b0 -
1*
1$
#5500000
0$
#5550000
b1 -
1$
#5600000
0$
#5650000
b10 -
1$
#5700000
0$
#5750000
b11 -
1$
#5800000
0$
#5850000
b100 -
1$
#5900000
0$
#5950000
b101 -
1$
#6000000
0$
#6050000
b110 -
1$
#6100000
0$
#6150000
b111 -
1$
#6200000
0$
#6250000
b1000 -
1$
#6300000
0$
#6350000
b1001 -
1$
#6400000
0$
#6450000
b0 -
0*
1$
#6500000
0$
#6550000
b1 -
1$
#6600000
0$
#6650000
b10 -
1$
#6700000
0$
#6750000
b11 -
1$
#6800000
0$
#6850000
b100 -
1$
#6900000
0$
#6950000
b101 -
1$
#7000000
0$
#7050000
b110 -
1$
#7100000
0$
#7150000
b111 -
1$
#7200000
0$
#7250000
b1000 -
1$
#7300000
0$
#7350000
b1001 -
1$
#7400000
0$
#7450000
b11 =
1"
b101 9
b0 -
1*
1$
#7500000
0$
#7550000
b1 -
1$
#7600000
0$
#7650000
b10 -
1$
#7700000
0$
#7750000
b11 -
1$
#7800000
0$
#7850000
b100 -
1$
#7900000
0$
#7950000
b101 -
1$
#8000000
0$
#8050000
b110 -
1$
#8100000
0$
#8150000
b111 -
1$
#8200000
0$
#8250000
b1000 -
1$
#8300000
0$
#8350000
b1001 -
1$
#8400000
0$
#8450000
b0 -
0*
1$
#8500000
0$
#8550000
b1 -
1$
#8600000
0$
#8650000
b10 -
1$
#8700000
0$
#8750000
b11 -
1$
#8800000
0$
#8850000
b100 -
1$
#8900000
0$
#8950000
b101 -
1$
#9000000
0$
#9050000
b110 -
1$
#9100000
0$
#9150000
b111 -
1$
#9200000
0$
#9250000
b1000 -
1$
#9300000
0$
#9350000
b1001 -
1$
#9400000
0$
#9450000
b100 =
0"
b110 9
b0 -
1*
1$
#9500000
0$
#9550000
b1 -
1$
#9600000
0$
#9650000
b10 -
1$
#9700000
0$
#9750000
b11 -
1$
#9800000
0$
#9850000
b100 -
1$
#9900000
0$
#9950000
b101 -
1$
#10000000
0$
#10050000
b110 -
1$
#10100000
0$
#10150000
b111 -
1$
#10200000
0$
#10250000
b1000 -
1$
#10300000
0$
#10350000
b1001 -
1$
#10400000
0$
#10450000
b0 -
0*
1$
#10500000
0$
#10550000
b1 -
1$
#10600000
0$
#10650000
b10 -
1$
#10700000
0$
#10750000
b11 -
1$
#10800000
0$
#10850000
b100 -
1$
#10900000
0$
#10950000
b101 -
1$
#11000000
0$
#11050000
b110 -
1$
#11100000
0$
#11150000
b111 -
1$
#11200000
0$
#11250000
b1000 -
1$
#11300000
0$
#11350000
b1001 -
1$
#11400000
0$
#11450000
b101 =
b111 9
b0 -
1*
1$
#11500000
0$
#11550000
b1 -
1$
#11600000
0$
#11650000
b10 -
1$
#11700000
0$
#11750000
b11 -
1$
#11800000
0$
#11850000
b100 -
1$
#11900000
0$
#11950000
b101 -
1$
#12000000
0$
#12050000
b110 -
1$
#12100000
0$
#12150000
b111 -
1$
#12200000
0$
#12250000
b1000 -
1$
#12300000
0$
#12350000
b1001 -
1$
#12400000
0$
#12450000
b0 -
0*
1$
#12500000
0$
#12550000
b1 -
1$
#12600000
0$
#12650000
b10 -
1$
#12700000
0$
#12750000
b11 -
1$
#12800000
0$
#12850000
b100 -
1$
#12900000
0$
#12950000
b101 -
1$
#13000000
0$
#13050000
b110 -
1$
#13100000
0$
#13150000
b111 -
1$
#13200000
0$
#13250000
b1000 -
1$
#13300000
0$
#13350000
b1001 -
1$
#13400000
0$
#13450000
b1 6
b110 =
1"
b0 9
1,
b0 -
1*
1$
#13500000
0$
#13550000
b1 -
1$
#13600000
0$
#13650000
b10 -
1$
#13700000
0$
#13750000
b11 -
1$
#13800000
0$
#13850000
b100 -
1$
#13900000
0$
#13950000
b101 -
1$
#14000000
0$
#14050000
b110 -
1$
#14100000
0$
#14150000
b111 -
1$
#14200000
0$
#14250000
b1000 -
1$
#14300000
0$
#14350000
b1001 -
1$
#14400000
0$
#14450000
b0 -
0*
1$
#14500000
0$
#14550000
b1 -
1$
#14600000
0$
#14650000
b10 -
1$
#14700000
0$
#14750000
b11 -
1$
#14800000
0$
#14850000
b100 -
1$
#14900000
0$
#14950000
b101 -
1$
#15000000
0$
#15050000
b110 -
1$
#15100000
0$
#15150000
b111 -
1$
#15200000
0$
#15250000
b1000 -
1$
#15300000
0$
#15350000
b1001 -
1$
#15400000
0$
#15450000
b111 =
b1 9
b0 -
1*
1$
#15500000
0$
#15550000
b1 -
1$
#15600000
0$
#15650000
b10 -
1$
#15700000
0$
#15750000
b11 -
1$
#15800000
0$
#15850000
b100 -
1$
#15900000
0$
#15950000
b101 -
1$
#16000000
0$
#16050000
b110 -
1$
#16100000
0$
#16150000
b111 -
1$
#16200000
0$
#16250000
b1000 -
1$
#16300000
0$
#16350000
b1001 -
1$
#16400000
0$
#16450000
b0 -
0*
1$
#16500000
0$
#16550000
b1 -
1$
#16600000
0$
#16650000
b10 -
1$
#16700000
0$
#16750000
b11 -
1$
#16800000
0$
#16850000
b100 -
1$
#16900000
0$
#16950000
b101 -
1$
#17000000
0$
#17050000
b110 -
1$
#17100000
0$
#17150000
b111 -
1$
#17200000
0$
#17250000
b1000 -
1$
#17300000
0$
#17350000
b1001 -
1$
#17400000
0$
#17450000
b1 <
0"
b10 9
b0 -
1*
1$
#17500000
0$
#17550000
b1 -
1$
#17600000
0$
#17650000
b10 -
1$
#17700000
0$
#17750000
b11 -
1$
#17800000
0$
#17850000
b100 -
1$
#17900000
0$
#17950000
b101 -
1$
#18000000
0$
#18050000
b110 -
1$
#18100000
0$
#18150000
b111 -
1$
#18200000
0$
#18250000
b1000 -
1$
#18300000
0$
#18350000
b1001 -
1$
#18400000
0$
#18450000
b0 -
0*
1$
#18500000
0$
#18550000
b1 -
1$
#18600000
0$
#18650000
b10 -
1$
#18700000
0$
#18750000
b11 -
1$
#18800000
0$
#18850000
b100 -
1$
#18900000
0$
#18950000
b101 -
1$
#19000000
0$
#19050000
b110 -
1$
#19100000
0$
#19150000
b111 -
1$
#19200000
0$
#19250000
b1000 -
1$
#19300000
0$
#19350000
b1001 -
1$
#19400000
0$
#19450000
b10 <
b11 9
b0 -
1*
1$
#19500000
0$
#19550000
b1 -
1$
#19600000
0$
#19650000
b10 -
1$
#19700000
0$
#19750000
b11 -
1$
#19800000
0$
#19850000
b100 -
1$
#19900000
0$
#19950000
b101 -
1$
#20000000
0$
#20050000
b110 -
1$
#20100000
0$
#20150000
b111 -
1$
#20200000
0$
#20250000
b1000 -
1$
#20300000
0$
#20350000
b1001 -
1$
#20400000
0$
#20450000
b0 -
0*
1$
#20500000
0$
1'
#20550000
b1 -
1$
#20600000
0$
#20650000
b10 -
1$
#20700000
0$
#20750000
b11 -
1$
#20800000
0$
#20850000
b100 -
1$
#20900000
0$
#20950000
b101 -
1$
#21000000
0$
#21050000
b110 -
1$
#21100000
0$
#21150000
b111 -
1$
#21200000
0$
#21250000
b1000 -
1$
#21300000
0$
#21350000
b1001 -
1$
