spi_final/spi_mosi.v
`timescale 1 ns / 1 ps
module spi_mosi (control_clk,spi_mosi_out,spi_cs,spi_clk,,n_reset,spi_mosi_in);

  parameter DSIZE = 8;


    output  spi_mosi_out,control_clk;
    input spi_cs;
    input n_reset;
    input  spi_clk;
	input [DSIZE-1:0] spi_mosi_in;
    reg control_clk;

	reg spi_mosi_out;
    
	reg[3:0] point_add;
      reg[7:0] data ,add_byte;
 
      reg [2:0] point,control ;	


     
initial
     
            begin
              
              
                control<=3'b010;
               control_clk<=0;
               spi_mosi_out<=0;
                 add_byte<=01000110;   // address byte        
               data<=8'd0;
               point_add<=4'd5;
	       point<=3'd0;
			   
		end


// control clock : control smooth transiction of Data from asy_fifo_to spi_mosi
	

always@(posedge spi_clk)


        begin
           if(control==3'd7)
               begin
   				control_clk<=~control_clk;
   				control<=0;
   
					end
			else
				begin
					control=control+1;
				end
        end
// data from asy fifo come to spi_mosi with the control clock

always@(posedge spi_clk)
       begin
           if(spi_cs) 
               begin
               
                 data<=8'd0;  // address
                 
            
               
                    	end

	  else 
         	begin
 		data<=spi_mosi_in;
               
              			end  
		end



// spi clk manage data to send slave bit by bit
// every data byte also send e address byte by spi_mosi
// 
	
always@(posedge spi_clk)
    begin
 		if(spi_cs ) 
             begin
        		   spi_mosi_out<=0;
                             
                              data<=8'd0;
                              point<=3'd0;
		              point_add<=4'd0;
            
               
             end

	  else if(!spi_cs)
begin
	   if(point_add==4'd8)
	begin
         
          if(point==3'd7)	
                begin
          
                    point_add<=4'd0;
                   point<=3'b000;
		             end
	 
                   
               
         
	         else
                     begin
                      spi_mosi_out<=data[point];
                     point<= point+1;
                     	
                    end
	end
          

	
else
	     begin
	  spi_mosi_out<=add_byte[point_add];	  // assign address byte
		

 $display ("at time %0d spi_mosi_out=%b  ", $time, spi_mosi_out);
 $display ("at time %0d point_add=%d  ", $time, point_add);

                     point_add<= point_add+1;
					 end
	 
end

end
   


		endmodule

spi_final/asy_fifo_input.v
`timescale 1 ns / 1 ps
module asy_fifo_input (data_to_mosi, spi_cs,wdata,clk,rst,data_av,control_clk);
   parameter MEMDEPTH = 30;
  parameter DSIZE = 8;
  parameter ASIZE = 4;
  output [7:0] data_to_mosi;
  output spi_cs;
  input  [DSIZE-1:0] wdata;
  input               clk,data_av,control_clk;
  input              rst;
  reg    [ASIZE-1:0]   w_pointer;
  reg    [ASIZE-1:0]   r_pointer;
  reg [DSIZE-1:0] rdata;
  reg winc,rinc;
  reg spi_cs;
  reg w_full,r_empty;
  reg data_en;
 
  reg [DSIZE-1:0] ex_mem[MEMDEPTH-1:0];
 reg [7:0] data_to_mosi;



always @(posedge data_av or negedge rst)
if(!rst) begin
            data_en<=0;
         end
else if (rst) begin

                 if(w_full==0 ||r_empty==1)
                           begin
                               data_en<=1;
                           end
                 else
                           begin
                              data_en<=0;
                           end
 
             end
  
always @(posedge clk or negedge rst)
if(!rst) begin
           spi_cs<=0;
         end
else if (rst ) begin

                   if (w_full==1 || r_empty==1) begin
	  					    spi_cs<=0;
	  					end
     	  
    		   else
	 		begin
	  			spi_cs<=1;
	 		end
	       end

// for control increment for write and read
always @(posedge clk or negedge rst )

if (!rst) begin
             winc<=0;
             rinc<=0;
	end
else if (rst) begin
               
                  if(data_en==1 && w_full==0)                          // input data depend on data_av because winc and rinc depend on data_av
                                            begin	
                                              winc<=1;
                                              rinc<=0;
	                                                    // $display ("at time %0d winc=%b rinc=%b", $time, winc,rinc);
                                            end
                  else if(w_full==1)
                                           begin
                                              winc<=0;
                                              rinc<=1;
                                           end
                  else
                            begin
                               winc<=0;
                               rinc<=0;
                                                         //$display ("at time %0d winc=%b rinc=%b", $time, winc,rinc);
                            end

               end


  
//*****writing Data in FIFO


 always @(posedge clk or negedge rst)

  
       if (!rst) 
                 begin
                    w_pointer <= 4'b0000;
                    w_full<=0;
         
	             end

     else if (rst) begin
                     if (r_empty==1 && data_en==0) begin
                                                       w_full<=0;
                                                   end
	            else   if(winc==1 && w_pointer==4'b1111 ) begin
		    						   w_full<=1;		 
        	    						   w_pointer <= 4'b0000;
	   
	 	 						end

	            else if (winc==1 && !w_full ) begin
   
		    					w_pointer= w_pointer+1;

		    					ex_mem[w_pointer]<=  wdata;
 

                                                                  //$display ("at time %0d w_pointer=%b", $time, w_pointer);
                                                                    //$display ("at time %0d  ex_mem[w_pointer]=%d", $time,  ex_mem[w_pointer]);
                				      end

		    end

//****** Reading Data from FIFO

always @(posedge control_clk or negedge rst)


if (!rst) begin
               r_pointer <= 4'b0000;
               r_empty<=1;
               rdata<=0;
               data_to_mosi<=0;
            end
else if (rst) begin
  
             
              
		  if(rinc==1 && r_pointer==4'b1111)
				
                   			      begin
						r_empty=1;
						r_pointer <= 4'b0000;
						                       //$display ("at time %0d rempty=%b", $time, r_empty);
				
                   				   end
              
		else if(rinc==1 && !r_empty)
						begin
                                                        
							r_pointer= r_pointer+1;

							rdata=ex_mem[r_pointer];
							data_to_mosi=rdata;
                                             					
                                                    end           	//$display ("at time %0d rdata=%b", $time, rdata);
		 else if(w_full==1 && rinc==1 && winc==0)begin
                                                    r_empty<=0;
                                                end				
				
			
              end

  endmodule

spi_final/clk_div.v
`timescale 1 ns / 1 ps
module clk_div (spi_clk, m_clk, spi_cs, nrst);
	input nrst, spi_cs, m_clk;
	output spi_clk;

	//wire nrst, spi_clk_en, m_clk;
	reg spi_clk;
	reg [0:3] counter;

	initial
	begin 
		counter <= 4'b1000;
		spi_clk<=0;
		
	end
	always @(posedge m_clk )begin
		if (!nrst) begin 
			spi_clk <= 1'b0; 
			counter <= 4'b0000;
		end
		else begin
			if(!spi_cs) begin 
				if (counter == 4'b1001)
				   begin
					spi_clk <= !spi_clk;
					counter <= 4'b0000;
				   end // End of counter if
				else
					counter <= counter + 4'b0001;
			end // End of spi_clk_en if
		end // End of else
	end // End of always block

	
endmodule

spi_final/Synthesize/FINAL_I/final_I.v
`timescale 1 ns / 1 ps

`include "asy_fifo_input.v"
`include "spi_mosi.v"
`include "clk_div.v"

module  spi_final (spi_mosi_out,m_clk,n_reset,data_in,data_av);



output spi_mosi_out;
input m_clk,data_av;
input n_reset;

input[7:0] data_in;
wire spi_mosi_out;




 wire[7:0] spi_mosi_in;
 wire control_clk,spi_cs;




clk_div A(.spi_clk(spi_clk),.m_clk(m_clk),.spi_cs(spi_cs),.nrst(n_reset)); // spi_cs control spi_clk by spi_clk enable

// input (data_to_mosi, wdata,clk,rst,data_av,control_clk);
asy_fifo_input I1(.data_to_mosi(spi_mosi_in),.spi_cs(spi_cs),.wdata(data_in),.clk(m_clk),.rst(n_reset),.data_av(data_av),.control_clk(control_clk));

spi_mosi I2(.control_clk(control_clk),.spi_mosi_out(spi_mosi_out),.spi_cs(spi_cs),.spi_clk(spi_clk),.n_reset(n_reset),.spi_mosi_in(spi_mosi_in));





//output




endmodule

spi_final/final_test_I.v
`timescale 1 ns / 1 ps
module final_test_I;


reg m_clk;
reg n_reset;
reg [7:0] data_in;
wire  spi_mosi_out;
reg data_av;

event end_first_pass;
     spi_final O(spi_mosi_out,m_clk,n_reset,data_in,data_av);

always #50 m_clk = ~m_clk;
always 
begin
#50 data_av=~data_av;
#1500
data_av=~data_av;
end
	// Setting the initial input values
	initial
	begin
	m_clk=0;
        
        n_reset=1;

        data_av=0;

   
	

	end
/*
	initial 
	begin
      $dumpfile("final_I_waveform_result.vcd");
     $dumpvars(0,final_test_I);
      end  
*/  
initial begin
		$shm_open("final_I.shm");
		$shm_probe("AS"); // AS = all signals
	end
	initial begin
		$display ("time m_clk, data_in,n_reset,data_av,spi_mosi_out");
		$monitor ("at time %0d n_reset = %b  m_clk = %b  data_av =%b spi_mosi_out=%b", $time, n_reset,  m_clk, data_av,spi_mosi_out);
	end





initial
begin

begin
     




    


    #100 data_in=8'd2;
    #100 data_in=8'd3;
    #100 data_in=8'd4;
    #100 data_in=8'd5;
 
 
 #100 data_in=8'd6;
 #100 data_in=8'd7;
 #100 data_in=8'd8;
 
    

 #100 data_in=8'd9;
    #100 data_in=8'd10;
 #100 data_in=8'd11;
 #100 data_in=8'd12;
 #100 data_in=8'd13;


 #100 data_in=8'd14;
 #100 data_in=8'd15;


 #100 data_in=8'd16;
 #100 data_in=8'd17;
    #100 data_in=8'd18;

 #100 data_in=8'd18;
 #100 data_in=8'd19;

 #100 data_in=8'd20;






#1000000

#100000 ->end_first_pass;
   end
   $finish;
end
endmodule

spi_final/final_I_waveform_result.vcd
$date
	Thu Jul 14 03:33:20 2016
$end
$version
	Icarus Verilog
$end
$timescale
	1ps
$end
$scope module final_test_I $end
$var event 1 ! end_first_pass $end
$var wire 1 " spi_mosi_out $end
$var reg 1 # data_av $end
$var reg 8 $ data_in [7:0] $end
$var reg 1 % m_clk $end
$var reg 1 & n_reset $end
$scope module O $end
$var wire 1 # data_av $end
$var wire 8 ' data_in [7:0] $end
$var wire 1 % m_clk $end
$var wire 1 & n_reset $end
$var wire 1 " spi_mosi_out $end
$var wire 8 ( spi_mosi_in [7:0] $end
$var wire 1 ) spi_cs $end
$var wire 1 * spi_clk $end
$var wire 1 + control_clk $end
$scope module A $end
$var wire 1 % m_clk $end
$var wire 1 & nrst $end
$var wire 1 ) spi_cs $end
$var reg 4 , counter [0:3] $end
$var reg 1 * spi_clk $end
$upscope $end
$scope module I1 $end
$var wire 1 % clk $end
$var wire 1 # data_av $end
$var wire 1 & rst $end
$var wire 8 - wdata [7:0] $end
$var wire 1 + control_clk $end
$var reg 1 . data_en $end
$var reg 8 / data_to_mosi [7:0] $end
$var reg 1 0 r_empty $end
$var reg 4 1 r_pointer [3:0] $end
$var reg 8 2 rdata [7:0] $end
$var reg 1 3 rinc $end
$var reg 1 ) spi_cs $end
$var reg 1 4 w_full $end
$var reg 4 5 w_pointer [3:0] $end
$var reg 1 6 winc $end
$upscope $end
$scope module I2 $end
$var wire 1 & n_reset $end
$var wire 1 * spi_clk $end
$var wire 1 ) spi_cs $end
$var wire 8 7 spi_mosi_in [7:0] $end
$var reg 8 8 add_byte [7:0] $end
$var reg 3 9 control [2:0] $end
$var reg 1 + control_clk $end
$var reg 8 : data [7:0] $end
$var reg 3 ; point [2:0] $end
$var reg 4 < point_add [3:0] $end
$var reg 1 " spi_mosi_out $end
$upscope $end
$upscope $end
$upscope $end
$enddefinitions $end
#0
$dumpvars
b101 <
b0 ;
b0 :
b10 9
b10101110 8
b0 7
x6
b0 5
04
x3
b0 2
b0 1
00
b0 /
0.
bx -
b1000 ,
0+
0*
1)
b0 (
bx '
1&
0%
bx $
1#
0"
1!
$end
#50000
03
06
0#
1%
#100000
0%
#150000
1%
#200000
0%
#250000
1%
#300000
0%
#350000
1%
#400000
0%
#450000
1%
#500000
0%
#550000
1%
#600000
0%
#650000
1%
#700000
0%
#750000
1%
#800000
0%
#850000
1%
#900000
0%
#950000
1%
#1000000
0%
#1050000
1.
1%
1#
#1100000
0%
#1150000
16
1%
b10 $
b10 '
b10 -
#1200000
0%
#1250000
b1 5
1%
b11 $
b11 '
b11 -
#1300000
0%
#1350000
b10 5
1%
b100 $
b100 '
b100 -
#1400000
0%
#1450000
b11 5
1%
b101 $
b101 '
b101 -
#1500000
0%
#1550000
b100 5
1%
b110 $
b110 '
b110 -
#1600000
0%
#1650000
b101 5
1%
b111 $
b111 '
b111 -
#1700000
0%
#1750000
b110 5
1%
b1000 $
b1000 '
b1000 -
#1800000
0%
#1850000
b111 5
1%
b1001 $
b1001 '
b1001 -
#1900000
0%
#1950000
b1000 5
1%
b1010 $
b1010 '
b1010 -
#2000000
0%
#2050000
b1001 5
1%
b1011 $
b1011 '
b1011 -
#2100000
0%
#2150000
b1010 5
1%
b1100 $
b1100 '
b1100 -
#2200000
0%
#2250000
b1011 5
1%
b1101 $
b1101 '
b1101 -
#2300000
0%
#2350000
b1100 5
1%
b1110 $
b1110 '
b1110 -
#2400000
0%
#2450000
b1101 5
1%
b1111 $
b1111 '
b1111 -
#2500000
0%
#2550000
b1110 5
1%
b10000 $
b10000 '
b10000 -
#2600000
0%
#2650000
b1111 5
1%
b10001 $
b10001 '
b10001 -
#2700000
0%
#2750000
b0 5
14
1%
b10010 $
b10010 '
b10010 -
#2800000
0%
#2850000
0)
13
06
1%
#2900000
0%
#2950000
1)
b1001 ,
1%
b10011 $
b10011 '
b10011 -
#3000000
0%
#3050000
0)
1%
b10100 $
b10100 '
b10100 -
#3100000
0%
#3150000
b0 <
b11 9
1)
b0 ,
1*
1%
#3200000
0%
#3250000
0)
1%
#3300000
0%
#3350000
1)
b1 ,
1%
#3400000
0%
#3450000
0)
1%
#3500000
0%
#3550000
1)
b10 ,
1%
#3600000
0%
#3650000
0)
1%
#3700000
0%
#3750000
1)
b11 ,
1%
#3800000
0%
#3850000
0)
1%
#3900000
0%
#3950000
1)
b100 ,
1%
#4000000
0%
#4050000
0)
1%
#4100000
0%
#4150000
1)
b101 ,
1%
#4200000
0%
#4250000
0)
1%
#4300000
0%
#4350000
1)
b110 ,
1%
#4400000
0%
#4450000
0)
1%
#4500000
0%
#4550000
1)
b111 ,
1%
#4600000
0%
#4650000
0)
1%
#4700000
0%
#4750000
1)
b1000 ,
1%
#4800000
0%
#4850000
0)
1%
#4900000
0%
#4950000
1)
b1001 ,
1%
#5000000
0%
#5050000
0)
1%
#5100000
0%
#5150000
1)
b0 ,
0*
1%
#5200000
0%
#5250000
0)
1%
#5300000
0%
#5350000
1)
b1 ,
1%
#5400000
0%
#5450000
0)
1%
#5500000
0%
#5550000
1)
b10 ,
1%
#5600000
0%
#5650000
0)
1%
#5700000
0%
#5750000
1)
b11 ,
1%
#5800000
0%
#5850000
0)
1%
#5900000
0%
#5950000
1)
b100 ,
1%
#6000000
0%
#6050000
0)
1%
#6100000
0%
#6150000
1)
b101 ,
1%
#6200000
0%
#6250000
0)
1%
#6300000
0%
#6350000
1)
b110 ,
1%
#6400000
0%
#6450000
0)
1%
#6500000
0%
#6550000
1)
b111 ,
1%
#6600000
0%
#6650000
0)
1%
#6700000
0%
#6750000
1)
b1000 ,
1%
#6800000
0%
#6850000
0)
1%
#6900000
0%
#6950000
1)
b1001 ,
1%
#7000000
0%
#7050000
0)
1%
#7100000
0%
#7150000
b100 9
1)
b0 ,
1*
1%
#7200000
0%
#7250000
0)
1%
#7300000
0%
#7350000
1)
b1 ,
1%
#7400000
0%
#7450000
0)
1%
#7500000
0%
#7550000
1)
b10 ,
1%
#7600000
0%
#7650000
0)
1%
#7700000
0%
#7750000
1)
b11 ,
1%
#7800000
0%
#7850000
0)
1%
#7900000
0%
#7950000
1)
b100 ,
1%
#8000000
0%
#8050000
0)
1%
#8100000
0%
#8150000
1)
b101 ,
1%
#8200000
0%
#8250000
0)
1%
#8300000
0%
#8350000
1)
b110 ,
1%
#8400000
0%
#8450000
0)
1%
#8500000
0%
#8550000
1)
b111 ,
1%
#8600000
0%
#8650000
0)
1%
#8700000
0%
#8750000
1)
b1000 ,
1%
#8800000
0%
#8850000
0)
1%
#8900000
0%
#8950000
1)
b1001 ,
1%
#9000000
0%
#9050000
0)
1%
#9100000
0%
#9150000
1)
b0 ,
0*
1%
#9200000
0%
#9250000
0)
1%
#9300000
0%
#9350000
1)
b1 ,
1%
#9400000
0%
#9450000
0)
1%
#9500000
0%
#9550000
1)
b10 ,
1%
#9600000
0%
#9650000
0)
1%
#9700000
0%
#9750000
1)
b11 ,
1%
#9800000
0%
#9850000
0)
1%
#9900000
0%
#9950000
1)
b100 ,
1%
#10000000
0%
#10050000
0)
1%
#10100000
0%
#10150000
1)
b101 ,
1%
#10200000
0%
#10250000
0)
1%
#10300000
0%
#10350000
1)
b110 ,
1%
#10400000
0%
#10450000
0)
1%
#10500000
0%
#10550000
1)
b111 ,
1%
#10600000
0%
#10650000
0)
1%
#10700000
0%
#10750000
1)
b1000 ,
1%
#10800000
0%
#10850000
0)
1%
#10900000
0%
#10950000
1)
b1001 ,
1%
#11000000
0%
#11050000
0)
1%
#11100000
0%
#11150000
b101 9
1)
b0 ,
1*
1%
#11200000
0%
#11250000
0)
1%
#11300000
0%
#11350000
1)
b1 ,
1%
#11400000
0%
#11450000
0)
1%
#11500000
0%
#11550000
1)
b10 ,
1%
#11600000
0%
#11650000
0)
1%
#11700000
0%
#11750000
1)
b11 ,
1%
#11800000
0%
#11850000
0)
1%
#11900000
0%
#11950000
1)
b100 ,
1%
#12000000
0%
#12050000
0)
1%
#12100000
0%
#12150000
1)
b101 ,
1%
#12200000
0%
#12250000
0)
1%
#12300000
0%
#12350000
1)
b110 ,
1%
#12400000
0%
#12450000
0)
1%
#12500000
0%
#12550000
1)
b111 ,
1%
#12600000
0%
#12650000
0)
1%
#12700000
0%
#12750000
1)
b1000 ,
1%
#12800000
0%
#12850000
0)
1%
#12900000
0%
#12950000
1)
b1001 ,
1%
#13000000
0%
#13050000
0)
1%
#13100000
0%
#13150000
1)
b0 ,
0*
1%
#13200000
0%
#13250000
0)
1%
#13300000
0%
#13350000
1)
b1 ,
1%
#13400000
0%
#13450000
0)
1%
#13500000
0%
#13550000
1)
b10 ,
1%
#13600000
0%
#13650000
0)
1%
#13700000
0%
#13750000
1)
b11 ,
1%
#13800000
0%
#13850000
0)
1%
#13900000
0%
#13950000
1)
b100 ,
1%
#14000000
0%
#14050000
0)
1%
#14100000
0%
#14150000
1)
b101 ,
1%
#14200000
0%
#14250000
0)
1%
#14300000
0%
#14350000
1)
b110 ,
1%
#14400000
0%
#14450000
0)
1%
#14500000
0%
#14550000
1)
b111 ,
1%
#14600000
0%
#14650000
0)
1%
#14700000
0%
#14750000
1)
b1000 ,
1%
#14800000
0%
#14850000
0)
1%
#14900000
0%
#14950000
1)
b1001 ,
1%
#15000000
0%
#15050000
0)
1%
#15100000
0%
#15150000
b110 9
1)
b0 ,
1*
1%
#15200000
0%
#15250000
0)
1%
#15300000
0%
#15350000
1)
b1 ,
1%
#15400000
0%
#15450000
0)
1%
#15500000
0%
#15550000
1)
b10 ,
1%
#15600000
0%
#15650000
0)
1%
#15700000
0%
#15750000
1)
b11 ,
1%
#15800000
0%
#15850000
0)
1%
#15900000
0%
#15950000
1)
b100 ,
1%
#16000000
0%
#16050000
0)
1%
#16100000
0%
#16150000
1)
b101 ,
1%
#16200000
0%
#16250000
0)
1%
#16300000
0%
#16350000
1)
b110 ,
1%
#16400000
0%
#16450000
0)
1%
#16500000
0%
#16550000
1)
b111 ,
1%
#16600000
0%
#16650000
0)
1%
#16700000
0%
#16750000
1)
b1000 ,
1%
#16800000
0%
#16850000
0)
1%
#16900000
0%
#16950000
1)
b1001 ,
1%
#17000000
0%
#17050000
0)
1%
#17100000
0%
#17150000
1)
b0 ,
0*
1%
#17200000
0%
#17250000
0)
1%
#17300000
0%
#17350000
1)
b1 ,
1%
#17400000
0%
#17450000
0)
1%
#17500000
0%
#17550000
1)
b10 ,
1%
#17600000
0%
#17650000
0)
1%
#17700000
0%
#17750000
1)
b11 ,
1%
#17800000
0%
#17850000
0)
1%
#17900000
0%
#17950000
1)
b100 ,
1%
#18000000
0%
#18050000
0)
1%
#18100000
0%
#18150000
1)
b101 ,
1%
#18200000
0%
#18250000
0)
1%
#18300000
0%
#18350000
1)
b110 ,
1%
#18400000
0%
#18450000
0)
1%
#18500000
0%
#18550000
1)
b111 ,
1%
#18600000
0%
#18650000
0)
1%
#18700000
0%
#18750000
1)
b1000 ,
1%
#18800000
0%
#18850000
0)
1%
#18900000
0%
#18950000
1)
b1001 ,
1%
#19000000
0%
#19050000
0)
1%
#19100000
0%
#19150000
b111 9
1)
b0 ,
1*
1%
#19200000
0%
#19250000
0)
1%
#19300000
0%
#19350000
1)
b1 ,
1%
#19400000
0%
#19450000
0)
1%
#19500000
0%
#19550000
1)
b10 ,
1%
#19600000
0%
#19650000
0)
1%
#19700000
0%
#19750000
1)
b11 ,
1%
#19800000
0%
#19850000
0)
1%
#19900000
0%
#19950000
1)
b100 ,
1%
#20000000
0%
#20050000
0)
1%
#20100000
0%
#20150000
1)
b101 ,
1%
#20200000
0%
#20250000
0)
1%
#20300000
0%
#20350000
1)
b110 ,
1%
#20400000
0%
#20450000
0)
1%
#20500000
0%
#20550000
1)
b111 ,
1%
#20600000
0%
#20650000
0)
1%
#20700000
0%
#20750000
1)
b1000 ,
1%
#20800000
0%
#20850000
0)
1%
#20900000
0%
#20950000
1)
b1001 ,
1%
#21000000
0%
#21050000
0)
1%
#21100000
0%
#21150000
1)
b0 ,
0*
1%
#21200000
0%
#21250000
0)
1%
#21300000
0%
#21350000
1)
b1 ,
1%
#21400000
0%
#21450000
0)
1%
#21500000
0%
#21550000
1)
b10 ,
1%
#21600000
0%
#21650000
0)
1%
#21700000
0%
#21750000
1)
b11 ,
1%
#21800000
0%
#21850000
0)
1%
#21900000
0%
#21950000
1)
b100 ,
1%
#22000000
0%
#22050000
0)
1%
#22100000
0%
#22150000
1)
b101 ,
1%
#22200000
0%
#22250000
0)
1%
#22300000
0%
#22350000
1)
b110 ,
1%
#22400000
0%
#22450000
0)
1%
#22500000
0%
#22550000
1)
b111 ,
1%
#22600000
0%
#22650000
0)
1%
#22700000
0%
#22750000
1)
b1000 ,
1%
#22800000
0%
#22850000
0)
1%
#22900000
0%
#22950000
1)
b1001 ,
1%
#23000000
0%
#23050000
0)
1%
#23100000
0%
#23150000
b11 (
b11 /
b11 7
b11 2
b1 1
b0 9
1+
1)
b0 ,
1*
1%
#23200000
0%
#23250000
0)
1%
#23300000
0%
#23350000
1)
b1 ,
1%
#23400000
0%
#23450000
0)
1%
#23500000
0%
#23550000
1)
b10 ,
1%
#23600000
0%
#23650000
0)
1%
#23700000
0%
#23750000
1)
b11 ,
1%
#23800000
0%
#23850000
0)
1%
#23900000
0%
#23950000
1)
b100 ,
1%
#24000000
0%
#24050000
0)
1%
#24100000
0%
#24150000
1)
b101 ,
1%
#24200000
0%
#24250000
0)
1%
#24300000
0%
#24350000
1)
b110 ,
1%
#24400000
0%
#24450000
0)
1%
#24500000
0%
#24550000
1)
b111 ,
1%
#24600000
0%
#24650000
0)
1%
#24700000
0%
#24750000
1)
b1000 ,
1%
#24800000
0%
#24850000
0)
1%
#24900000
0%
#24950000
1)
b1001 ,
1%
#25000000
0%
#25050000
0)
1%
#25100000
0%
#25150000
1)
b0 ,
0*
1%
#25200000
0%
#25250000
0)
1%
#25300000
0%
#25350000
1)
b1 ,
1%
#25400000
0%
#25450000
0)
1%
#25500000
0%
#25550000
1)
b10 ,
1%
#25600000
0%
#25650000
0)
1%
#25700000
0%
#25750000
1)
b11 ,
1%
#25800000
0%
#25850000
0)
1%
#25900000
0%
#25950000
1)
b100 ,
1%
#26000000
0%
#26050000
0)
1%
#26100000
0%
#26150000
1)
b101 ,
1%
#26200000
0%
#26250000
0)
1%
#26300000
0%
#26350000
1)
b110 ,
1%
#26400000
0%
#26450000
0)
1%
#26500000
0%
#26550000
1)
b111 ,
1%
#26600000
0%
#26650000
0)
1%
#26700000
0%
#26750000
1)
b1000 ,
1%
#26800000
0%
#26850000
0)
1%
#26900000
0%
#26950000
1)
b1001 ,
1%
#27000000
0%
#27050000
0)
1%
#27100000
0%
#27150000
b1 9
1)
b0 ,
1*
1%
#27200000
0%
#27250000
0)
1%
#27300000
0%
#27350000
1)
b1 ,
1%
#27400000
0%
#27450000
0)
1%
#27500000
0%
#27550000
1)
b10 ,
1%
#27600000
0%
#27650000
0)
1%
#27700000
0%
#27750000
1)
b11 ,
1%
#27800000
0%
#27850000
0)
1%
#27900000
0%
#27950000
1)
b100 ,
1%
#28000000
0%
#28050000
0)
1%
#28100000
0%
#28150000
1)
b101 ,
1%
#28200000
0%
#28250000
0)
1%
#28300000
0%
#28350000
1)
b110 ,
1%
#28400000
0%
#28450000
0)
1%
#28500000
0%
#28550000
1)
b111 ,
1%
#28600000
0%
#28650000
0)
1%
#28700000
0%
#28750000
1)
b1000 ,
1%
#28800000
0%
#28850000
0)
1%
#28900000
0%
#28950000
1)
b1001 ,
1%
#29000000
0%
#29050000
0)
1%
#29100000
0%
#29150000
1)
b0 ,
0*
1%
#29200000
0%
#29250000
0)
1%
#29300000
0%
#29350000
1)
b1 ,
1%
#29400000
0%
#29450000
0)
1%
#29500000
0%
#29550000
1)
b10 ,
1%
#29600000
0%
#29650000
0)
1%
#29700000
0%
#29750000
1)
b11 ,
1%
#29800000
0%
#29850000
0)
1%
#29900000
0%
#29950000
1)
b100 ,
1%
#30000000
0%
#30050000
0)
1%
#30100000
0%
#30150000
1)
b101 ,
1%
#30200000
0%
#30250000
0)
1%
#30300000
0%
#30350000
1)
b110 ,
1%
#30400000
0%
#30450000
0)
1%
#30500000
0%
#30550000
1)
b111 ,
1%
#30600000
0%
#30650000
0)
1%
#30700000
0%
#30750000
1)
b1000 ,
1%
#30800000
0%
#30850000
0)
1%
#30900000
0%
#30950000
1)
b1001 ,
1%
#31000000
0%
#31050000
0)
1%
#31100000
0%
#31150000
b10 9
1)
b0 ,
1*
1%
#31200000
0%
#31250000
0)
1%
#31300000
0%
#31350000
1)
b1 ,
1%
#31400000
0%
#31450000
0)
1%
#31500000
0%
#31550000
1)
b10 ,
1%
#31600000
0%
#31650000
0)
1%
#31700000
0%
#31750000
1)
b11 ,
1%
#31800000
0%
#31850000
0)
1%
#31900000
0%
#31950000
1)
b100 ,
1%
#32000000
0%
#32050000
0)
1%
#32100000
0%
#32150000
1)
b101 ,
1%
#32200000
0%
#32250000
0)
1%
#32300000
0%
#32350000
1)
b110 ,
1%
#32400000
0%
#32450000
0)
1%
#32500000
0%
#32550000
1)
b111 ,
1%
#32600000
0%
#32650000
0)
1%
#32700000
0%
#32750000
1)
b1000 ,
1%
#32800000
0%
#32850000
0)
1%
#32900000
0%
#32950000
1)
b1001 ,
1%
#33000000
0%
#33050000
0)
1%
#33100000
0%
#33150000
1)
b0 ,
0*
1%
#33200000
0%
#33250000
0)
1%
#33300000
0%
#33350000
1)
b1 ,
1%
#33400000
0%
#33450000
0)
1%
#33500000
0%
#33550000
1)
b10 ,
1%
#33600000
0%
#33650000
0)
1%
#33700000
0%
#33750000
1)
b11 ,
1%
#33800000
0%
#33850000
0)
1%
#33900000
0%
#33950000
1)
b100 ,
1%
#34000000
0%
#34050000
0)
1%
#34100000
0%
#34150000
1)
b101 ,
1%
#34200000
0%
#34250000
0)
1%
#34300000
0%
#34350000
1)
b110 ,
1%
#34400000
0%
#34450000
0)
1%
#34500000
0%
#34550000
1)
b111 ,
1%
#34600000
0%
#34650000
0)
1%
#34700000
0%
#34750000
1)
b1000 ,
1%
#34800000
0%
#34850000
0)
1%
#34900000
0%
#34950000
1)
b1001 ,
1%
#35000000
0%
#35050000
0)
1%
#35100000
0%
#35150000
b11 9
1)
b0 ,
1*
1%
#35200000
0%
#35250000
0)
1%
#35300000
0%
#35350000
1)
b1 ,
1%
#35400000
0%
#35450000
0)
1%
#35500000
0%
#35550000
1)
b10 ,
1%
#35600000
0%
#35650000
0)
1%
#35700000
0%
#35750000
1)
b11 ,
1%
#35800000
0%
#35850000
0)
1%
#35900000
0%
#35950000
1)
b100 ,
1%
#36000000
0%
#36050000
0)
1%
#36100000
0%
#36150000
1)
b101 ,
1%
#36200000
0%
#36250000
0)
1%
#36300000
0%
#36350000
1)
b110 ,
1%
#36400000
0%
#36450000
0)
1%
#36500000
0%
#36550000
1)
b111 ,
1%
#36600000
0%
#36650000
0)
1%
#36700000
0%
#36750000
1)
b1000 ,
1%
#36800000
0%
#36850000
0)
1%
#36900000
0%
#36950000
1)
b1001 ,
1%
#37000000
0%
#37050000
0)
1%
#37100000
0%
#37150000
1)
b0 ,
0*
1%
#37200000
0%
#37250000
0)
1%
#37300000
0%
#37350000
1)
b1 ,
1%
#37400000
0%
#37450000
0)
1%
#37500000
0%
#37550000
1)
b10 ,
1%
#37600000
0%
#37650000
0)
1%
#37700000
0%
#37750000
1)
b11 ,
1%
#37800000
0%
#37850000
0)
1%
#37900000
0%
#37950000
1)
b100 ,
1%
#38000000
0%
#38050000
0)
1%
#38100000
0%
#38150000
1)
b101 ,
1%
#38200000
0%
#38250000
0)
1%
#38300000
0%
#38350000
1)
b110 ,
1%
#38400000
0%
#38450000
0)
1%
#38500000
0%
#38550000
1)
b111 ,
1%
#38600000
0%
#38650000
0)
1%
#38700000
0%
#38750000
1)
b1000 ,
1%
#38800000
0%
#38850000
0)
1%
#38900000
0%
#38950000
1)
b1001 ,
1%
#39000000
0%
#39050000
0)
1%
#39100000
0%
#39150000
b100 9
1)
b0 ,
1*
1%
#39200000
0%
#39250000
0)
1%
#39300000
0%
#39350000
1)
b1 ,
1%
#39400000
0%
#39450000
0)
1%
#39500000
0%
#39550000
1)
b10 ,
1%
#39600000
0%
#39650000
0)
1%
#39700000
0%
#39750000
1)
b11 ,
1%
#39800000
0%
#39850000
0)
1%
#39900000
0%
#39950000
1)
b100 ,
1%
#40000000
0%
#40050000
0)
1%
#40100000
0%
#40150000
1)
b101 ,
1%
#40200000
0%
#40250000
0)
1%
#40300000
0%
#40350000
1)
b110 ,
1%
#40400000
0%
#40450000
0)
1%
#40500000
0%
#40550000
1)
b111 ,
1%
#40600000
0%
#40650000
0)
1%
#40700000
0%
#40750000
1)
b1000 ,
1%
#40800000
0%
#40850000
0)
1%
#40900000
0%
#40950000
1)
b1001 ,
1%
#41000000
0%
#41050000
0)
1%
#41100000
0%
#41150000
1)
b0 ,
0*
1%
#41200000
0%
#41250000
0)
1%
#41300000
0%
#41350000
1)
b1 ,
1%
#41400000
0%
#41450000
0)
1%
#41500000
0%
#41550000
1)
b10 ,
1%
#41600000
0%
#41650000
0)
1%
#41700000
0%
#41750000
1)
b11 ,
1%
#41800000
0%
#41850000
0)
1%
#41900000
0%
#41950000
1)
b100 ,
1%
