spi_final/spi_miso.v
`timescale 1 ns / 1 ps
module spi_miso (control_clk_miso,spi_mosi_out,spi_miso_out,spi_cs,spi_clk,spi_miso_in);

 parameter DSIZE = 8;
output control_clk_miso;
output spi_mosi_out;
 output  [DSIZE-1:0] spi_miso_out;
 input spi_cs;
 input  spi_clk;
input spi_miso_in;

	
reg control_clk_miso;
reg [DSIZE-1:0] spi_miso_out;
reg spi_mosi_out;
reg [DSIZE-1:0] data,final_data,add_byte;
reg[2:0] point,point_add;
      
reg [2:0] control;

	



initial
            begin
              spi_miso_out<=0;
	           point<=3'b000;
		       point_add<=3'b000;
               data<=8'd0;
			   final_data<=8'd0;
               control<=3'b010;
               control_clk_miso<=1'b0;
             
			   add_byte<=10000101; // address byte
 
		                end
	


// create control clock for sending data to asy_fifo_output


always@(posedge spi_clk)


        begin
           if(control==3'd7)
               begin
   		
                        control_clk_miso<=~control_clk_miso;
   		       control<=0;
   
			end
		else
				
                       begin
			control=control+1;
		            end
        end
	


// spi_clk read data bit by bit from slave and keep it in final data

always @(posedge spi_clk)

	 if(spi_cs) 
             begin
           spi_mosi_out<=0;
            point<=0;
           data<= 8'd0;
               
               end

	  else if (!spi_cs )
	   begin
	   if(point_add==3'b111)
	       begin
	          if (point==3'b111)
                   begin      
                    final_data<=data;
                         point<=0;
                     	point_add<=0;
					 
                    end
               else
                   begin
		    data[point]<=spi_miso_in;	
		
             spi_mosi_out<=0;
 $display ("at time %0d data=%b  ", $time, data);
 $display ("at time %0d point=%d  ", $time, point);

                     point<= point+1;

		    end
		
			end
	 else
	 begin
	  spi_mosi_out<=add_byte[point_add];	  /// assign address byte.... adress byte send through mosi
		data<=8'd0;

 $display ("at time %0d spi_mosi_out=%b  ", $time, spi_mosi_out);
 $display ("at time %0d point_add=%d  ", $time, point_add);

                     point_add<= point_add+1;
					 end
	 
		   end 
 // control clock control final data and push it to spi_miso_out

always @(posedge control_clk_miso)


if(spi_cs)
spi_miso_out<=0;
else                
   begin

               
                spi_miso_out<=final_data;
                 
            
          		end	

		

		endmodule

spi_final/spi_miso_test.v
`timescale 1 ns / 1 ps
module spi_miso_test;
  

reg  spi_miso_in;
 reg  spi_clk,spi_cs;
 wire [7:0] spi_miso_out;
wire spi_mosi_out;
wire control_clk_miso;

//`define stim #10 wdata=8'd
event end_first_pass;


    spi_miso A1(control_clk_miso,spi_mosi_out,spi_miso_out,spi_cs,spi_clk,spi_miso_in);
	

/*initial begin
  $shm_open("spi_miso.shm");
  $shm_probe("AS");
end
*/
initial begin
$dumpfile("spi_miso_waveform_result.vcd");
$dumpvars(0,spi_miso_test);
end
initial
begin
    
     spi_clk=0;
     spi_cs=1;


   
end



always  #50 spi_clk= ~spi_clk;
always
begin
#50 ;
$display ("at time %0d spi_clk = %b   control_clk_miso=%b spi_cs= %b  spi_miso_in=%b spi_miso_out=%d spi_mosi_out=%d ", $time,      
     control_clk_miso,spi_clk,spi_cs,spi_miso_in,spi_miso_out,spi_mosi_out);

end
initial
begin
begin


 spi_cs=0;
#2100
#100 spi_miso_in =1'b1;
#100 spi_miso_in =1'b0;
#100 spi_miso_in =1'b0;
#100 spi_miso_in =1'b0;
#100 spi_miso_in =1'b0;
#100 spi_miso_in =1'b0;
#100 spi_miso_in =1'b0;
#100 spi_miso_in =1'b0;


#800
 spi_miso_in =1'b0;
#100 spi_miso_in =1'b1;
#100 spi_miso_in =1'b0;
#100 spi_miso_in =1'b0;
#100 spi_miso_in =1'b0;
#100 spi_miso_in =1'b0;
#100 spi_miso_in =1'b0;
#100 spi_miso_in =1'b0;



#800

 spi_miso_in =1'b1;
#100 spi_miso_in =1'b1;
#100 spi_miso_in =1'b0;
#100 spi_miso_in =1'b0;
#100 spi_miso_in =1'b0;
#100 spi_miso_in =1'b0;
#100 spi_miso_in =1'b0;
#100 spi_miso_in =1'b0;


    
    
	//#1700 spi_mosi_in=8'b11001010;
	
	
	
	
	#3000->end_first_pass;
   end
   $finish;
end
endmodule

spi_final/spi_miso_waveform_result.vcd
$date
	Sun Jul 10 19:31:20 2016
$end
$version
	Icarus Verilog
$end
$timescale
	1ps
$end
$scope module spi_miso_test $end
$var event 1 ! end_first_pass $end
$var wire 1 " spi_mosi_out $end
$var wire 8 # spi_miso_out [7:0] $end
$var wire 1 $ control_clk_miso $end
$var reg 1 % spi_clk $end
$var reg 1 & spi_cs $end
$var reg 1 ' spi_miso_in $end
$scope module A1 $end
$var wire 1 % spi_clk $end
$var wire 1 & spi_cs $end
$var wire 1 ' spi_miso_in $end
$var reg 8 ( add_byte [7:0] $end
$var reg 3 ) control [2:0] $end
$var reg 1 $ control_clk_miso $end
$var reg 8 * data [7:0] $end
$var reg 8 + final_data [7:0] $end
$var reg 3 , point [2:0] $end
$var reg 3 - point_add [2:0] $end
$var reg 8 . spi_miso_out [7:0] $end
$var reg 1 " spi_mosi_out $end
$upscope $end
$upscope $end
$enddefinitions $end
#0
$dumpvars
b0 .
b0 -
b0 ,
bx +
bx *
b10 )
b11100101 (
x'
0&
0%
0$
b0 #
x"
1!
$end
#50000
b1 -
b0 *
1"
b11 )
1%
#100000
0%
#150000
b10 -
0"
b100 )
1%
#200000
0%
#250000
b11 -
1"
b101 )
1%
#300000
0%
#350000
b100 -
0"
b110 )
1%
#400000
0%
#450000
b101 -
b111 )
1%
#500000
0%
#550000
bx #
bx .
b110 -
1"
b0 )
1$
1%
#600000
0%
#650000
b111 -
b1 )
1%
#700000
0%
#750000
b1 ,
0"
b0x *
b10 )
1%
#800000
0%
#850000
b10 ,
b0xx *
b11 )
1%
#900000
0%
#950000
b11 ,
b0xxx *
b100 )
1%
#1000000
0%
#1050000
b100 ,
b0xxxx *
b101 )
1%
#1100000
0%
#1150000
b101 ,
b0xxxxx *
b110 )
1%
#1200000
0%
#1250000
b110 ,
b0xxxxxx *
b111 )
1%
#1300000
0%
#1350000
b111 ,
b0xxxxxxx *
b0 )
0$
1%
#1400000
0%
#1450000
b0 -
b0 ,
b0xxxxxxx +
b1 )
1%
#1500000
0%
#1550000
b1 -
b0 *
1"
b10 )
1%
#1600000
0%
#1650000
b10 -
0"
b11 )
1%
#1700000
0%
#1750000
b11 -
1"
b100 )
1%
#1800000
0%
#1850000
b100 -
0"
b101 )
1%
#1900000
0%
#1950000
b101 -
b110 )
1%
#2000000
0%
#2050000
b110 -
1"
b111 )
1%
#2100000
0%
#2150000
b0xxxxxxx #
b0xxxxxxx .
b111 -
b0 )
1$
1%
#2200000
0%
1'
#2250000
b1 ,
0"
b1 *
b1 )
1%
#2300000
0%
0'
#2350000
b10 ,
b10 )
1%
#2400000
0%
#2450000
b11 ,
b11 )
1%
#2500000
0%
#2550000
b100 ,
b100 )
1%
#2600000
0%
#2650000
b101 ,
b101 )
1%
#2700000
0%
#2750000
b110 ,
b110 )
1%
#2800000
0%
#2850000
b111 ,
b111 )
1%
#2900000
0%
#2950000
b0 -
b0 ,
b1 +
b0 )
0$
1%
#3000000
0%
#3050000
b1 -
b0 *
1"
b1 )
1%
#3100000
0%
#3150000
b10 -
0"
b10 )
1%
#3200000
0%
#3250000
b11 -
1"
b11 )
1%
#3300000
0%
#3350000
b100 -
0"
b100 )
1%
#3400000
0%
#3450000
b101 -
b101 )
1%
#3500000
0%
#3550000
b110 -
1"
b110 )
1%
#3600000
0%
#3650000
b111 -
b111 )
1%
#3700000
0%
#3750000
b1 #
b1 .
b1 ,
0"
b0 )
1$
1%
#3800000
0%
1'
#3850000
b10 ,
b10 *
b1 )
1%
#3900000
0%
0'
#3950000
b11 ,
b10 )
1%
#4000000
0%
#4050000
b100 ,
b11 )
1%
#4100000
0%
#4150000
b101 ,
b100 )
1%
#4200000
0%
#4250000
b110 ,
b101 )
1%
#4300000
0%
#4350000
b111 ,
b110 )
1%
#4400000
0%
#4450000
b0 -
b0 ,
b10 +
b111 )
1%
#4500000
0%
#4550000
b1 -
b0 *
1"
b0 )
0$
1%
#4600000
0%
#4650000
b10 -
0"
b1 )
1%
#4700000
0%
#4750000
b11 -
1"
b10 )
1%
#4800000
0%
#4850000
b100 -
0"
b11 )
1%
#4900000
0%
#4950000
b101 -
b100 )
1%
#5000000
0%
#5050000
b110 -
1"
b101 )
1%
#5100000
0%
#5150000
b111 -
b110 )
1%
#5200000
0%
1'
#5250000
b1 ,
0"
b1 *
b111 )
1%
#5300000
0%
#5350000
b10 #
b10 .
b10 ,
b11 *
b0 )
1$
1%
#5400000
0%
0'
#5450000
b11 ,
b1 )
1%
#5500000
0%
#5550000
b100 ,
b10 )
1%
#5600000
0%
#5650000
b101 ,
b11 )
1%
#5700000
0%
#5750000
b110 ,
b100 )
1%
#5800000
0%
#5850000
b111 ,
b101 )
1%
#5900000
0%
#5950000
b0 -
b0 ,
b11 +
b110 )
1%
#6000000
0%
#6050000
b1 -
b0 *
1"
b111 )
1%
#6100000
0%
#6150000
b10 -
0"
b0 )
0$
1%
#6200000
0%
#6250000
b11 -
1"
b1 )
1%
#6300000
0%
#6350000
b100 -
0"
b10 )
1%
#6400000
0%
#6450000
b101 -
b11 )
1%
#6500000
0%
#6550000
b110 -
1"
b100 )
1%
#6600000
0%
#6650000
b111 -
b101 )
1%
#6700000
0%
#6750000
b1 ,
0"
b110 )
1%
#6800000
0%
#6850000
b10 ,
b111 )
1%
#6900000
0%
#6950000
b11 #
b11 .
b11 ,
b0 )
1$
1%
#7000000
0%
#7050000
b100 ,
b1 )
1%
#7100000
0%
#7150000
b101 ,
b10 )
1%
#7200000
0%
#7250000
b110 ,
b11 )
1%
#7300000
0%
#7350000
b111 ,
b100 )
1%
#7400000
0%
#7450000
b0 -
b0 ,
b0 +
b101 )
1%
#7500000
0%
#7550000
b1 -
1"
b110 )
1%
#7600000
0%
#7650000
b10 -
0"
b111 )
1%
#7700000
0%
#7750000
b11 -
1"
b0 )
0$
1%
#7800000
0%
#7850000
b100 -
0"
b1 )
1%
#7900000
0%
#7950000
b101 -
b10 )
1%
#8000000
0%
#8050000
b110 -
1"
b11 )
1%
#8100000
0%
#8150000
b111 -
b100 )
1%
#8200000
0%
#8250000
b1 ,
0"
b101 )
1%
#8300000
0%
#8350000
b10 ,
b110 )
1%
#8400000
0%
#8450000
b11 ,
b111 )
1%
#8500000
0%
#8550000
b0 #
b0 .
b100 ,
b0 )
1$
1%
#8600000
0%
#8650000
b101 ,
b1 )
1%
#8700000
0%
#8750000
b110 ,
b10 )
1%
#8800000
0%
#8850000
b111 ,
b11 )
1%
#8900000
0%
1!
