asy_fifo/asy_fifo.v
`timescale 1 ns / 1 ps
module asy_fifo (rdata,  wdata,winc, clk, rst, rinc);

  parameter DSIZE = 8;
  parameter ASIZE = 4;
  output [DSIZE-1:0] rdata;
  
  input  [DSIZE-1:0] wdata;
  input              winc, clk;
  input              rinc,rst;
  reg    [ASIZE:0]   w_pointer;
  reg    [ASIZE:0]   r_pointer;
  reg [DSIZE-1:0] rdata;
  
  reg w_full,r_empty;
  parameter MEMDEPTH = 15;
 
  reg [DSIZE-1:0] ex_mem[MEMDEPTH-1:0];

  initial
begin
       
     
       w_pointer <= 5'b00000;
         r_pointer <= 5'b00000;
		 w_full =0;
		 r_empty=0;
end


always @(posedge clk )

  
      if (rst) 
         begin
         w_pointer <= 5'b00000;
         r_pointer <= 5'b00000;
	end
else if(rinc && r_pointer==5'b11111)
         begin
		 r_empty=1;
		 r_pointer <= 5'b00000;
		 $display ("at time %0d rempty=%b", $time, r_empty);
		    end
else if(winc && w_pointer==5'b11111)
       begin
	   w_full=1;		 
       w_pointer <= 5'b00000;
             end

else if (winc && !w_full)
   
  begin
   
 w_pointer= w_pointer+1;

 ex_mem[w_pointer]<=  wdata;
 

$display ("at time %0d w_pointer=%d", $time, w_pointer);
   end

else if(rinc && !r_empty)
    begin

      r_pointer= r_pointer+1;

    rdata<=ex_mem[r_pointer];
	

$display ("at time %0d r_pointer=%d", $time, r_pointer);
    end
  endmodule

asy_fifo/asy_fifo_test.v
  `timescale 1 ns / 1 ps
module asy_fifo_test;
  
 

reg [7:0] wdata;
 reg  winc, clk, rst ,rinc;
 wire [7:0] rdata;

//`define stim #10 wdata=8'd
event end_first_pass;


    asy_fifo A1(rdata, wdata,
                  winc, clk, rst, rinc);




initial begin
$dumpfile("asy_fifo_waveform_result.vcd");
$dumpvars(0,asy_fifo_test);
end
initial
begin
    
    rst=0;
    rst=1;
    rst=0;
    clk=0;
    winc=0;
    rinc=0;
    
end



always  #50 clk= ~clk;



always
begin
#50 ;
$display ("at time %0d clk = %b   rst= %b  winc=%b rinc=%b wdata=%d rdata=%d ", $time,      
     clk,rst,winc,rinc,wdata,rdata);

end

initial
begin
begin
        
        wdata=8'd1;    
 winc=1;
 rinc=0; 
    #50 wdata=8'd1;
    #100 wdata=8'd20;
    #150 wdata=8'd30;
    #160 wdata=8'd40;
 
 winc=0;
 rinc=1;
 #170 wdata=8'd50;
 #180 wdata=8'd60;
 #190 wdata=8'd70;
 
    
winc=1;
rinc=0;
 #300 wdata=8'd100;
    #310 wdata=8'd120;
 #320 wdata=8'd130;
 #330 wdata=8'd140;
 #340 wdata=8'd150;

 winc=0;
 rinc=1;
 #170 wdata=8'd55;
 #180 wdata=8'd200;
 #190 wdata=8'd300;
 winc=1;
rinc=0;
 #300 wdata=8'd1000;
    #310 wdata=8'd1020;
 #320 wdata=8'd1300;
 #330 wdata=8'd1040;
 #340 wdata=8'd1050;
winc=0;
rinc=1;
#500 ->end_first_pass;
   end
   $finish;
end
endmodule

asy_fifo/asy_fifo_waveform_result.vcd
$date
	Wed Jun 22 01:05:21 2016
$end
$version
	Icarus Verilog
$end
$timescale
	1ps
$end
$scope module asy_fifo_test $end
$var event 1 ! end_first_pass $end
$var wire 8 " rdata [7:0] $end
$var reg 1 # clk $end
$var reg 1 $ rinc $end
$var reg 1 % rst $end
$var reg 8 & wdata [7:0] $end
$var reg 1 ' winc $end
$scope module A1 $end
$var wire 1 # clk $end
$var wire 1 $ rinc $end
$var wire 1 % rst $end
$var wire 8 ( wdata [7:0] $end
$var wire 1 ' winc $end
$var reg 1 ) r_empty $end
$var reg 5 * r_pointer [4:0] $end
$var reg 8 + rdata [7:0] $end
$var reg 1 , w_full $end
$var reg 5 - w_pointer [4:0] $end
$upscope $end
$upscope $end
$enddefinitions $end
#0
$dumpvars
b0 -
0,
bx +
b0 *
0)
b1 (
1'
b1 &
0%
0$
0#
bx "
1!
$end
#50000
b1 -
1#
#100000
0#
#150000
b10 -
1#
b10100 &
b10100 (
#200000
0#
#250000
b11 -
1#
#300000
0#
b11110 &
b11110 (
#350000
b100 -
1#
#400000
0#
#450000
b101 -
1#
#460000
1$
0'
b101000 &
b101000 (
#500000
0#
#550000
b1 "
b1 +
b1 *
1#
#600000
0#
#630000
b110010 &
b110010 (
#650000
b10100 "
b10100 +
b10 *
1#
#700000
0#
#750000
b11 *
1#
#800000
0#
#810000
b111100 &
b111100 (
#850000
b11110 "
b11110 +
b100 *
1#
#900000
0#
#950000
b101 *
1#
#1000000
0#
0$
1'
b1000110 &
b1000110 (
#1050000
b110 -
1#
#1100000
0#
#1150000
b111 -
1#
#1200000
0#
#1250000
b1000 -
1#
#1300000
0#
b1100100 &
b1100100 (
#1350000
b1001 -
1#
#1400000
0#
#1450000
b1010 -
1#
#1500000
0#
#1550000
b1011 -
1#
#1600000
0#
#1610000
b1111000 &
b1111000 (
#1650000
b1100 -
1#
#1700000
0#
#1750000
b1101 -
1#
#1800000
0#
#1850000
b1110 -
1#
#1900000
0#
#1930000
b10000010 &
b10000010 (
#1950000
b1111 -
1#
#2000000
0#
#2050000
b10000 -
1#
#2100000
0#
#2150000
b10001 -
1#
#2200000
0#
#2250000
b10010 -
1#
#2260000
b10001100 &
b10001100 (
#2300000
0#
#2350000
b10011 -
1#
#2400000
0#
#2450000
b10100 -
1#
#2500000
0#
#2550000
b10101 -
1#
#2600000
0#
1$
0'
b10010110 &
b10010110 (
#2650000
b1000110 "
b1000110 +
b110 *
1#
#2700000
0#
#2750000
b111 *
1#
#2770000
b110111 &
b110111 (
#2800000
0#
#2850000
b1000 *
1#
#2900000
0#
#2950000
b1100100 "
b1100100 +
b1001 *
1#
b11001000 &
b11001000 (
#3000000
0#
#3050000
b1010 *
1#
#3100000
0#
#3140000
0$
1'
b101100 &
b101100 (
#3150000
b10110 -
1#
#3200000
0#
#3250000
b10111 -
1#
#3300000
0#
#3350000
b11000 -
1#
#3400000
0#
#3440000
b11101000 &
b11101000 (
#3450000
b11001 -
1#
#3500000
0#
#3550000
b11010 -
1#
#3600000
0#
#3650000
b11011 -
1#
#3700000
0#
#3750000
b11100 -
1#
b11111100 &
b11111100 (
#3800000
0#
#3850000
b11101 -
1#
#3900000
0#
#3950000
b11110 -
1#
#4000000
0#
#4050000
b11111 -
1#
#4070000
b10100 &
b10100 (
#4100000
0#
#4150000
b0 -
1,
1#
#4200000
0#
#4250000
1#
#4300000
0#
#4350000
1#
#4400000
0#
b10000 &
b10000 (
#4450000
1#
#4500000
0#
#4550000
1#
#4600000
0#
#4650000
1#
#4700000
0#
#4740000
1$
0'
b11010 &
b11010 (
#4750000
b1011 *
1#
#4800000
0#
#4850000
b1111000 "
b1111000 +
b1100 *
1#
#4900000
0#
#4950000
b1101 *
1#
#5000000
0#
#5050000
b1110 *
1#
#5100000
0#
#5150000
b10000010 "
b10000010 +
b1111 *
1#
#5200000
0#
#5240000
1!
