Data_out/asy_fifo.v
`timescale 1 ns / 1 ps
module asy_fifo (data_out,wdata,winc, clk, rst, rinc);

  parameter DSIZE = 8;
  parameter ASIZE = 4;
  output [119:0] data_out ;
  
  input  [DSIZE-1:0] wdata;
  input              winc, clk;
  input              rinc,rst;
  reg    [ASIZE:0]   w_pointer;
  reg    [ASIZE:0]   r_pointer;
  reg [DSIZE-1:0] rdata;
  reg  [119:0] data_out ;
 
  reg w_full,r_empty;
  integer i=0;
  parameter MEMDEPTH = 20;
 
  reg [DSIZE-1:0] ex_mem[MEMDEPTH-1:0];

  initial
begin
       
     
       w_pointer <= 5'b00000;
         r_pointer <= 5'b00000;
		 w_full =0;
		 r_empty=0;
	
		 
end


always @(posedge clk )

  
      if (rst) 
         begin
         w_pointer <= 5'b00000;
         r_pointer <= 5'b00000;
	end
else if(rinc && r_pointer==5'b11111)
         begin
		 r_empty=1;
		 r_pointer <= 5'b00000;
		 $display ("at time %0d rempty=%b", $time, r_empty);
		    end
else if(winc && w_pointer==5'b11111)
       begin
	   w_full=1;		 
       w_pointer <= 5'b00000;
             end

else if (winc && !w_full)
   
  begin
   
 w_pointer= w_pointer+1;

 ex_mem[w_pointer]<=  wdata;
 

$display ("at time %0d w_pointer=%d", $time, w_pointer);
   end

else if(rinc && !r_empty )
    begin

      r_pointer= r_pointer+1;

    rdata=ex_mem[r_pointer];
	$display ("at time %0d r_pointer=%d", $time, r_pointer);
	$display ("at time %0d rdata=%d", $time, rdata);
	  data_out=rdata;
	 data_out=data_out<<i;
	  i=i+8;
	  $display ("at time %0d data_out=%b", $time, data_out);
	 
	

    end
	
	
  endmodule

Data_out/asy_fifo_test.v
  `timescale 1 ns / 1 ps
module asy_fifo_test;
  
 

reg [7:0] wdata;
 reg  winc, clk, rst ,rinc;
 wire [119:0] data_out;

//`define stim #10 wdata=8'd
event end_first_pass;


    asy_fifo A1(data_out, wdata,
                  winc, clk, rst, rinc);




initial begin
$dumpfile("asy_fifo_waveform_result.vcd");
$dumpvars(0,asy_fifo_test);
end
initial
begin
    
    rst=0;
    rst=1;
    rst=0;
    clk=0;
    winc=0;
    rinc=0;
    
end



always  #50 clk= ~clk;



always
begin
#50 ;
$display ("at time %0d clk = %b   rst= %b  winc=%b rinc=%b wdata=%d data_out=%d ", $time,      
     clk,rst,winc,rinc,wdata,data_out);

end

initial
begin
begin
        
           
 winc=1;
 rinc=0; 
    #50 wdata=8'd01;
    #100 wdata=8'd02;
    #150 wdata=8'd03;
    #200 wdata=8'd04;
    #250 wdata=8'd05;
/*
 #170 wdata=8'd50;
 #180 wdata=8'd60;
 #190 wdata=8'd70;
 
    

 #300 wdata=8'd100;
    #310 wdata=8'd120;
 #320 wdata=8'd130;
 #330 wdata=8'd140;
 #340 wdata=8'd150;
*/

 
winc=0;
rinc=1;
#1000 ->end_first_pass;
   end
   $finish;
end
endmodule

Data_out/asy_fifo_waveform_result.vcd
$date
	Sun Jun 26 01:23:37 2016
$end
$version
	Icarus Verilog
$end
$timescale
	1ps
$end
$scope module asy_fifo_test $end
$var event 1 ! end_first_pass $end
$var wire 120 " data_out [119:0] $end
$var reg 1 # clk $end
$var reg 1 $ rinc $end
$var reg 1 % rst $end
$var reg 8 & wdata [7:0] $end
$var reg 1 ' winc $end
$scope module A1 $end
$var wire 1 # clk $end
$var wire 1 $ rinc $end
$var wire 1 % rst $end
$var wire 8 ( wdata [7:0] $end
$var wire 1 ' winc $end
$var reg 120 ) data_out [119:0] $end
$var reg 1 * r_empty $end
$var reg 5 + r_pointer [4:0] $end
$var reg 8 , rdata [7:0] $end
$var reg 1 - w_full $end
$var reg 5 . w_pointer [4:0] $end
$var integer 32 / i [31:0] $end
$upscope $end
$upscope $end
$enddefinitions $end
#0
$dumpvars
b0 /
b0 .
0-
bx ,
b0 +
0*
bx )
bx (
1'
bx &
0%
0$
0#
bx "
1!
$end
#50000
b1 .
b1 &
b1 (
1#
#100000
0#
#150000
b10 .
1#
b10 &
b10 (
#200000
0#
#250000
b11 .
1#
#300000
0#
b11 &
b11 (
#350000
b100 .
1#
#400000
0#
#450000
b101 .
1#
#500000
0#
b100 &
b100 (
#550000
b110 .
1#
#600000
0#
#650000
b111 .
1#
#700000
0#
#750000
b1000 /
b1 "
b1 )
b1 ,
b1 +
1#
1$
0'
b101 &
b101 (
#800000
0#
#850000
b10000 /
b1000000000 "
b1000000000 )
b10 ,
b10 +
1#
#900000
0#
#950000
b11000 /
b100000000000000000 "
b100000000000000000 )
b11 +
1#
#1000000
0#
#1050000
b100000 /
b11000000000000000000000000 "
b11000000000000000000000000 )
b11 ,
b100 +
1#
#1100000
0#
#1150000
b101000 /
b1100000000000000000000000000000000 "
b1100000000000000000000000000000000 )
b101 +
1#
#1200000
0#
#1250000
b110000 /
b1000000000000000000000000000000000000000000 "
b1000000000000000000000000000000000000000000 )
b100 ,
b110 +
1#
#1300000
0#
#1350000
b111000 /
b100000000000000000000000000000000000000000000000000 "
b100000000000000000000000000000000000000000000000000 )
b111 +
1#
#1400000
0#
#1450000
b1000000 /
b0xxxxxxxx00000000000000000000000000000000000000000000000000000000 "
b0xxxxxxxx00000000000000000000000000000000000000000000000000000000 )
bx ,
b1000 +
1#
#1500000
0#
#1550000
b1001000 /
b0xxxxxxxx0000000000000000000000000000000000000000000000000000000000000000 "
b0xxxxxxxx0000000000000000000000000000000000000000000000000000000000000000 )
b1001 +
1#
#1600000
0#
#1650000
b1010000 /
b0xxxxxxxx000000000000000000000000000000000000000000000000000000000000000000000000 "
b0xxxxxxxx000000000000000000000000000000000000000000000000000000000000000000000000 )
b1010 +
1#
#1700000
0#
#1750000
b1011 +
1#
1!
