spi_final/Synthesize/FINAL/asy_fifo_output.v
`timescale 1 ns / 1 ps
module asy_fifo_output(data_out,spi_cs, wdata,clk,control_clk_miso,rst,read_req);
   parameter MEMDEPTH = 30;
  parameter DSIZE = 8;
  parameter ASIZE = 4;
  output [119:0] data_out;
  output spi_cs;
  input control_clk_miso;
  input  [DSIZE-1:0] wdata;
  input               clk,read_req;
  input              rst;
  reg    [ASIZE-1:0]   w_pointer;
  reg    [ASIZE-1:0]   r_pointer;
  reg [DSIZE-1:0] rdata;
  reg winc,rinc;
 reg spi_cs;
  reg w_full,r_empty;
  reg read_en;
 
  reg [DSIZE-1:0] ex_mem[MEMDEPTH-1:0];
 reg [119:0] data_out;



always @(posedge read_req or negedge rst)
if(!rst) begin
               read_en<=0;
		 end
		 
else  begin
                 if(w_full==1) begin
                                   read_en<=1;
                                end
                 else
                       begin
                           read_en<=0;
                       end
                end
 
always @(posedge clk or negedge rst)
if (!rst)  begin
             spi_cs<=0;
			
			 
	      end
else  begin

              if (w_full==0) begin
	                              spi_cs<=0;
	                             
	                         end
	             else if (r_empty==1) begin
	                                     spi_cs<=0;
	                                  end
                        else  begin
	                              spi_cs<=1;
	 
	                           end
	  
             end
// control read and write operation

always @(posedge clk or negedge rst)
if(!rst) begin
           winc<=0;
		   rinc<=0;
		 end
else begin
 
            	if(read_en==1 && w_full==1) begin	
                                               winc<=0;
                                               rinc<=1;
	  $display ("at time %0d winc=%b rinc=%b", $time, winc,rinc);
                                             end
                else if (w_full==0) begin
                                         winc<=1;
                                         rinc<=0;
$display ("at time %0d winc=%b rinc=%b", $time, winc,rinc);
                                     end
                else begin
                         winc<=0;
                         rinc<=0;
                     end
             end
// control_clk_miso use for writing in Fifo

 always @(posedge control_clk_miso or negedge rst )

  
      if (!rst)  begin
                     w_pointer <= 4'b0000;
					 w_full<=0;
                     
	             end
	 else begin
	 

                 if(winc==1 && w_pointer==4'b1111) begin
	                                                     w_full<=1;		 
                                                         w_pointer <= 4'b0000;
	  
                                                   end

                 else if (winc==1 && !w_full)  begin
   
                                                    w_pointer<= w_pointer+1;

                                                     ex_mem[w_pointer]<=  wdata;
 

$display ("at time %0d w_pointer=%b", $time, w_pointer);
$display ("at time %0d  ex_mem[w_pointer]=%d", $time,  ex_mem[w_pointer]);
  
                                                 end
                 else if (r_empty==1) begin
	                                       w_full<=0;
	                                  end
               end
// clk use for reading from fifo

always @(posedge clk or negedge rst)

 if(!rst) begin
              r_pointer<=0;
		      r_empty<=0;
			  rdata<=0;
		  end
else begin
                   if(rinc==1 && r_pointer==4'b1111)  begin
		                                                   r_empty<=1;
		                                                   r_pointer <= 4'b0000;
		 $display ("at time %0d rempty=%b", $time, r_empty);
		
		                                              end

                   else if(rinc==1 && !r_empty) begin

                                                    r_pointer<= r_pointer+1;

                                                   rdata<=ex_mem[r_pointer];
   
$display ("at time %0d rdata=%b", $time, rdata);
                                                 end
                else if(read_en==0)
                               begin
                                     r_empty<=0;
                               end    
             

               end

			  
			  

// making a 120 bit buffer output and output data deliver without delay---



always @(posedge clk or negedge rst)

if(!rst) begin
            data_out<=8'd0;
		end
else begin         

                    if(r_pointer==15) begin

data_out[7:0]<=ex_mem[0];
data_out[15:8]<=ex_mem[1];
data_out[23:16]<=ex_mem[2];
data_out[31:24]<=ex_mem[3];
data_out[39:32]<=ex_mem[4];
data_out[47:40]<=ex_mem[5];
data_out[55:48]<=ex_mem[6];
data_out[63:56]<=ex_mem[7];
data_out[71:64]<=ex_mem[8];
data_out[79:72]<=ex_mem[9];
data_out[87:80]<=ex_mem[10];
data_out[95:88]<=ex_mem[11];
data_out[103:96]<=ex_mem[12];
data_out[111:104]<=ex_mem[13];
data_out[119:112]<=ex_mem[14];

                                       end
$display ("at time %0d data_out=%b", $time, data_out);
               end




	
  endmodule

spi_final/Synthesize/FINAL_O/spi_miso.v
`timescale 1 ns / 1 ps
module spi_miso (control_clk_miso,spi_mosi_out,spi_miso_out,spi_cs,spi_clk,spi_miso_in,n_reset);

 parameter DSIZE = 8;
output control_clk_miso;
output spi_mosi_out;
 output  [DSIZE-1:0] spi_miso_out;
 input spi_cs;
 input  spi_clk,n_reset;
input spi_miso_in;

	
reg control_clk_miso;
reg [DSIZE-1:0] spi_miso_out;
reg spi_mosi_out;
reg [DSIZE-1:0] data,final_data,add_byte;
reg[2:0] point,point_add;
      
reg [2:0] control;

	





// create control clock for sending data to asy_fifo_output


always@(posedge spi_clk or negedge n_reset)
if(! n_reset)begin
                 
                 control<=3'b010;
                 control_clk_miso<=1'b0;
			 end
else  begin
                      if(control==3'd7) begin
   		
                                             control_clk_miso<=~control_clk_miso;
   		                                     control<=0;
   
			                             end
		              else
				
                          begin
			                    control<=control+1;
		                  end
                   end
	


// spi_clk read data bit by bit from slave and keep it in final data

always @(posedge spi_clk or negedge n_reset)
if (!n_reset) begin
                       spi_mosi_out<=0;
	                point<=3'b000;
		            point_add<=3'b000;
					data<=8'd0;
				    final_data<=8'd0;
					add_byte<=10000101; // address byte
				end
else  begin

					 if(spi_cs) 
                               begin
                                    spi_mosi_out<=0;
                                    point<=0;
                                    data<= 8'd0;
               
                                end

	                 else if (!spi_cs )
	                              begin
	                                  if(point_add==3'b111)
	                                                       begin
	                                                           if (point==3'b111)
                                                                                begin      
                                                                                    final_data<=data;
                                                                                    point<=0;
										    point_add<=0;
										end
								else if (control_clk_miso==1)
										begin
										      data[point]<=spi_miso_in;	
		
										      spi_mosi_out<=0;
 //$display ("at time %0d data=%b  ", $time, data);
 //$display ("at time %0d point=%d  ", $time, point);

								           		point<= point+1;

										end
		
								end
					else if (control_clk_miso==0)
								begin
								  spi_mosi_out<=add_byte[point_add];	  /// assign address byte.... adress byte send through mosi
								   data<=8'd0;

 $display ("at time %0d spi_mosi_out=%b  ", $time, spi_mosi_out);
 $display ("at time %0d point_add=%d  ", $time, point_add);

								   point_add<= point_add+1;
								end
	 
					end 
		 end
 // control clock control final data and push it to spi_miso_out

always @(posedge control_clk_miso or negedge n_reset)


 if (!n_reset) begin
                  spi_miso_out<=0;
               end
else begin

                      if(spi_cs) begin
                                     spi_miso_out<=0;
								    end
									
                     else                
                          begin

               
                             spi_miso_out<=final_data;
                 
            
          		          end	

		            end

		endmodule

spi_final/Synthesize/FINAL/clk_div.v
`timescale 1 ns / 1 ps
module clk_div (spi_clk, m_clk, spi_cs, nrst);
	input nrst, spi_cs, m_clk;
	output spi_clk;

	//wire nrst, spi_clk_en, m_clk;
	reg spi_clk;
	reg [0:3] counter;


	always @(posedge m_clk or negedge nrst)begin
		if (!nrst) begin 
			spi_clk <= 1'b0; 
			counter <= 4'b0000;
		end
		else begin
			if(!spi_cs) begin 
				if (counter == 4'b1001)
				   begin
					spi_clk <= !spi_clk;
					counter <= 4'b0000;
				   end // End of counter if
				else
					counter <= counter + 4'b0001;
			end // End of spi_clk_en if
		end // End of else
	end // End of always block

	
endmodule

spi_final/Synthesize/FINAL_O/final_O.v
`timescale 1 ns / 1 ps

`include "asy_fifo_output.v"
`include "spi_miso.v"
`include "clk_div.v"
module  spi_final_O (data_out,spi_mosi_out,spi_miso_in,read_req,m_clk,n_reset);



output [119:0] data_out;
output spi_mosi_out;
input m_clk,read_req;
input n_reset;

input spi_miso_in;

wire[119:0] data_out;

 wire [2:0] control ;
wire [7:0] spi_miso_out;

wire [7:0] data_to_mosi;
    wire control_clk_miso,spi_clk,spi_cs;




clk_div A(.spi_clk(spi_clk),.m_clk(m_clk),.spi_cs(spi_cs),.nrst(n_reset)); // spi_cs control spi_clk by spi_clk enable

// input (spi_mosi_out,m_clk,n_reset,spi_cs,data_in,data_av);

//spi_mosi I2(.control_clk(control_clk),.spi_mosi_out(spi_mosi_out),.spi_cs(spi_cs),.spi_clk(spi_clk),.n_reset(n_reset),.spi_mosi_in(spi_mosi_in));

//asy_fifo_input I1(.data_to_mosi(spi_mosi_in), .wdata(data_in),.clk(m_clk),.rst(n_reset),.data_av(data_av),.control_clk(control_clk));



//output


spi_miso O2(.control_clk_miso(control_clk_miso),.spi_mosi_out(spi_mosi_out),.spi_miso_out(spi_miso_out),.spi_cs(spi_cs),.spi_clk(spi_clk),.spi_miso_in(spi_miso_in),.n_reset(n_reset));

asy_fifo_output O1(.data_out(data_out),.spi_cs(spi_cs) ,.wdata(spi_miso_out),.clk(m_clk),.control_clk_miso(control_clk_miso),.rst(n_reset),.read_req(read_req));







endmodule

spi_final/Synthesize/FINAL_O/final_test_O.v
`timescale 1 ns / 1 ps
module final_test_O;


reg m_clk;
reg n_reset;
reg  spi_miso_in;
wire[119:0] data_out;
wire spi_mosi_out;
reg read_req;

event end_first_pass;
     spi_final_O T(data_out,spi_mosi_out,spi_miso_in,read_req,m_clk,n_reset);

always #50 m_clk = ~m_clk;

	// Setting the initial input values
	initial
	begin
	m_clk=0;
       
n_reset=0;

read_req<=0; 
   
	

	end
	
	/*initial 
	begin
      $dumpfile("final_O_waveform_result.vcd");
     $dumpvars(0,final_test_O);
      end */   
initial begin
		$shm_open("final_O.shm");
		$shm_probe("AS"); // AS = all signals
	end
	initial begin
		$display ("time spi_miso_in, n_reset,m_clk,read_req,data_out");
		$monitor ("at time %0d spi_mosi_out=%b spi_miso_in =%b n_reset = %b  m_clk = %b  read_req =%b data_out=%b", $time, spi_mosi_out,spi_miso_in,n_reset,m_clk, read_req,data_out);
	end





initial
begin

begin
 #2500
n_reset=1;


spi_miso_in =1'b1;
#2000 spi_miso_in =1'b0;
#2000 spi_miso_in =1'b0;
#2000 spi_miso_in =1'b0;
#2000 spi_miso_in =1'b0;
#2000 spi_miso_in =1'b0;
#2000 spi_miso_in =1'b0;
#2000 spi_miso_in =1'b0;


#2000

 spi_miso_in =1'b0;
#2000 spi_miso_in =1'b1;
#2000 spi_miso_in =1'b0;
#2000 spi_miso_in =1'b0;
#2000 spi_miso_in =1'b0;
#2000 spi_miso_in =1'b0;
#2000 spi_miso_in =1'b0;
#2000 spi_miso_in =1'b0;

#2000




 spi_miso_in =1'b1;
#2000 spi_miso_in =1'b1;
#2000 spi_miso_in =1'b0;
#2000 spi_miso_in =1'b0;
#2000 spi_miso_in =1'b0;
#2000 spi_miso_in =1'b0;
#2000 spi_miso_in =1'b0;
#2000 spi_miso_in =1'b1;

#2000




 spi_miso_in =1'b0;
#2000 spi_miso_in =1'b0;
#2000 spi_miso_in =1'b1;
#2000 spi_miso_in =1'b0;
#2000 spi_miso_in =1'b0;
#2000 spi_miso_in =1'b0;
#2000 spi_miso_in =1'b0;
#2000 spi_miso_in =1'b1;

#2000




 spi_miso_in =1'b1;
#2000 spi_miso_in =1'b0;
#2000 spi_miso_in =1'b1;
#2000 spi_miso_in =1'b0;
#2000 spi_miso_in =1'b0;
#2000 spi_miso_in =1'b0;
#2000 spi_miso_in =1'b0;
#2000 spi_miso_in =1'b1;

#2000




 spi_miso_in =1'b1;
#2000 spi_miso_in =1'b1;
#2000 spi_miso_in =1'b1;
#2000 spi_miso_in =1'b0;
#2000 spi_miso_in =1'b0;
#2000 spi_miso_in =1'b0;
#2000 spi_miso_in =1'b0;
#2000 spi_miso_in =1'b1;

#2000




 spi_miso_in =1'b0;
#2000 spi_miso_in =1'b0;
#2000 spi_miso_in =1'b0;
#2000 spi_miso_in =1'b1;
#2000 spi_miso_in =1'b0;
#2000 spi_miso_in =1'b0;
#2000 spi_miso_in =1'b0;
#2000 spi_miso_in =1'b1;

#2000




 spi_miso_in =1'b1;
#2000 spi_miso_in =1'b0;
#2000 spi_miso_in =1'b0;
#2000 spi_miso_in =1'b1;
#2000 spi_miso_in =1'b0;
#2000 spi_miso_in =1'b0;
#2000 spi_miso_in =1'b0;
#2000 spi_miso_in =1'b1;

#2000




 spi_miso_in =1'b0;
#2000 spi_miso_in =1'b1;
#2000 spi_miso_in =1'b0;
#2000 spi_miso_in =1'b1;
#2000 spi_miso_in =1'b0;
#2000 spi_miso_in =1'b0;
#2000 spi_miso_in =1'b0;
#2000 spi_miso_in =1'b1;

#2000




 spi_miso_in =1'b1;
#2000 spi_miso_in =1'b1;
#2000 spi_miso_in =1'b0;
#2000 spi_miso_in =1'b1;
#2000 spi_miso_in =1'b0;
#2000 spi_miso_in =1'b0;
#2000 spi_miso_in =1'b0;
#2000 spi_miso_in =1'b1;

#2000




 spi_miso_in =1'b0;
#2000 spi_miso_in =1'b0;
#2000 spi_miso_in =1'b1;
#2000 spi_miso_in =1'b1;
#2000 spi_miso_in =1'b0;
#2000 spi_miso_in =1'b0;
#2000 spi_miso_in =1'b0;
#2000 spi_miso_in =1'b1;

#2000




 spi_miso_in =1'b1;
#2000 spi_miso_in =1'b0;
#2000 spi_miso_in =1'b1;
#2000 spi_miso_in =1'b1;
#2000 spi_miso_in =1'b0;
#2000 spi_miso_in =1'b0;
#2000 spi_miso_in =1'b0;
#2000 spi_miso_in =1'b1;

#2000




 spi_miso_in =1'b0;
#2000 spi_miso_in =1'b1;
#2000 spi_miso_in =1'b1;
#2000 spi_miso_in =1'b1;
#2000 spi_miso_in =1'b0;
#2000 spi_miso_in =1'b0;
#2000 spi_miso_in =1'b0;
#2000 spi_miso_in =1'b1;

#2000




 spi_miso_in =1'b1;
#2000 spi_miso_in =1'b1;
#2000 spi_miso_in =1'b1;
#2000 spi_miso_in =1'b1;
#2000 spi_miso_in =1'b0;
#2000 spi_miso_in =1'b0;
#2000 spi_miso_in =1'b0;
#2000 spi_miso_in =1'b1;

#2000




 spi_miso_in =1'b0;
#2000 spi_miso_in =1'b0;
#2000 spi_miso_in =1'b0;
#2000 spi_miso_in =1'b0;
#2000 spi_miso_in =1'b1;
#2000 spi_miso_in =1'b0;
#2000 spi_miso_in =1'b0;
#2000 spi_miso_in =1'b1;

#2000




 spi_miso_in =1'b1;
#2000 spi_miso_in =1'b0;
#2000 spi_miso_in =1'b0;
#2000 spi_miso_in =1'b0;
#2000 spi_miso_in =1'b1;
#2000 spi_miso_in =1'b0;
#2000 spi_miso_in =1'b0;
#2000 spi_miso_in =1'b1;

#2000




 spi_miso_in =1'b1;
#2000 spi_miso_in =1'b1;
#2000 spi_miso_in =1'b0;
#2000 spi_miso_in =1'b0;
#2000 spi_miso_in =1'b0;
#2000 spi_miso_in =1'b0;
#2000 spi_miso_in =1'b0;
#2000 spi_miso_in =1'b1;

#2000




 spi_miso_in =1'b1;
#2000 spi_miso_in =1'b1;
#2000 spi_miso_in =1'b0;
#2000 spi_miso_in =1'b0;
#2000 spi_miso_in =1'b0;
#2000 spi_miso_in =1'b0;
#2000 spi_miso_in =1'b0;
#2000 spi_miso_in =1'b1;

#2000




 spi_miso_in =1'b1;
#2000 spi_miso_in =1'b1;
#2000 spi_miso_in =1'b0;
#2000 spi_miso_in =1'b0;
#2000 spi_miso_in =1'b0;
#2000 spi_miso_in =1'b0;
#2000 spi_miso_in =1'b0;
#2000 spi_miso_in =1'b1;

#2000




 spi_miso_in =1'b1;
#2000 spi_miso_in =1'b1;
#2000 spi_miso_in =1'b0;
#2000 spi_miso_in =1'b0;
#2000 spi_miso_in =1'b0;
#2000 spi_miso_in =1'b0;
#2000 spi_miso_in =1'b0;
#2000 spi_miso_in =1'b1;
#2000



 spi_miso_in =1'b1;
#2000 spi_miso_in =1'b0;
#2000 spi_miso_in =1'b0;
#2000 spi_miso_in =1'b1;
#2000 spi_miso_in =1'b0;
#2000 spi_miso_in =1'b0;
#2000 spi_miso_in =1'b0;
#2000 spi_miso_in =1'b1;

#2000




 spi_miso_in =1'b0;
#2000 spi_miso_in =1'b1;
#2000 spi_miso_in =1'b0;
#2000 spi_miso_in =1'b1;
#2000 spi_miso_in =1'b0;
#2000 spi_miso_in =1'b0;
#2000 spi_miso_in =1'b0;
#2000 spi_miso_in =1'b1;

#2000




 spi_miso_in =1'b1;
#2000 spi_miso_in =1'b1;
#2000 spi_miso_in =1'b0;
#2000 spi_miso_in =1'b1;
#2000 spi_miso_in =1'b0;
#2000 spi_miso_in =1'b0;
#2000 spi_miso_in =1'b0;
#2000 spi_miso_in =1'b1;

#2000




 spi_miso_in =1'b0;
#2000 spi_miso_in =1'b0;
#2000 spi_miso_in =1'b1;
#2000 spi_miso_in =1'b1;
#2000 spi_miso_in =1'b0;
#2000 spi_miso_in =1'b0;
#2000 spi_miso_in =1'b0;
#2000 spi_miso_in =1'b1;

#2000




 spi_miso_in =1'b1;
#2000 spi_miso_in =1'b0;
#2000 spi_miso_in =1'b1;
#2000 spi_miso_in =1'b1;
#2000 spi_miso_in =1'b0;
#2000 spi_miso_in =1'b0;
#2000 spi_miso_in =1'b0;
#2000 spi_miso_in =1'b1;

#2000




 spi_miso_in =1'b0;
#2000 spi_miso_in =1'b1;
#2000 spi_miso_in =1'b1;
#2000 spi_miso_in =1'b1;
#2000 spi_miso_in =1'b0;
#2000 spi_miso_in =1'b0;
#2000 spi_miso_in =1'b0;
#2000 spi_miso_in =1'b1;

#2000




 spi_miso_in =1'b1;
#2000 spi_miso_in =1'b1;
#2000 spi_miso_in =1'b1;
#2000 spi_miso_in =1'b1;
#2000 spi_miso_in =1'b0;
#2000 spi_miso_in =1'b0;
#2000 spi_miso_in =1'b0;
#2000 spi_miso_in =1'b1;

#2000




 spi_miso_in =1'b0;
#2000 spi_miso_in =1'b0;
#2000 spi_miso_in =1'b0;
#2000 spi_miso_in =1'b0;
#2000 spi_miso_in =1'b1;
#2000 spi_miso_in =1'b0;
#2000 spi_miso_in =1'b0;
#2000 spi_miso_in =1'b1;

#2000




 spi_miso_in =1'b1;
#2000 spi_miso_in =1'b0;
#2000 spi_miso_in =1'b0;
#2000 spi_miso_in =1'b0;
#2000 spi_miso_in =1'b1;
#2000 spi_miso_in =1'b0;
#2000 spi_miso_in =1'b0;
#2000 spi_miso_in =1'b1;

#2000




 spi_miso_in =1'b1;
#2000 spi_miso_in =1'b1;
#2000 spi_miso_in =1'b0;
#2000 spi_miso_in =1'b0;
#2000 spi_miso_in =1'b0;
#2000 spi_miso_in =1'b0;
#2000 spi_miso_in =1'b0;
#2000 spi_miso_in =1'b1;

#2000




 spi_miso_in =1'b1;
#2000 spi_miso_in =1'b1;
#2000 spi_miso_in =1'b0;
#2000 spi_miso_in =1'b0;
#2000 spi_miso_in =1'b0;
#2000 spi_miso_in =1'b0;
#2000 spi_miso_in =1'b0;
#2000 spi_miso_in =1'b1;

#2000




 spi_miso_in =1'b1;
#2000 spi_miso_in =1'b1;
#2000 spi_miso_in =1'b0;
#2000 spi_miso_in =1'b0;
#2000 spi_miso_in =1'b0;
#2000 spi_miso_in =1'b0;
#2000 spi_miso_in =1'b0;
#2000 spi_miso_in =1'b1;

#2000




 spi_miso_in =1'b1;
#2000 spi_miso_in =1'b1;
#2000 spi_miso_in =1'b0;
#2000 spi_miso_in =1'b0;
#2000 spi_miso_in =1'b0;
#2000 spi_miso_in =1'b0;
#2000 spi_miso_in =1'b0;
#2000 spi_miso_in =1'b1;


read_req=0;
#400
read_req=~read_req;
#50
read_req=~read_req;

#10000
read_req=~read_req;
#50
read_req=~read_req;
#6000
read_req=~read_req;
#50
read_req=~read_req;
#10000
read_req=~read_req;
#50
read_req=~read_req;
#20000
read_req=~read_req;
#50
read_req=~read_req;


#100000 ->end_first_pass;
   end
   $finish;
end
endmodule

spi_final/Synthesize/FINAL_O/final_O_waveform_result.vcd
$date
    Jul 18, 2016  15:00:01
$end
$version
    Tool:	VERILOG-XL	08.20.001-d
$end
$timescale
     1ps
$end

$scope module final_test_O $end
$var reg       1 !    m_clk  $end
$var reg       1 "    n_reset  $end
$var reg       1 #    spi_miso_in  $end
$var wire     120 $    data_out [119:0] $end
$var wire      1 %    spi_mosi_out  $end
$var reg       1 &    read_req  $end
$var event     1 '    end_first_pass  $end

$scope module T $end
$var wire      1 %    spi_mosi_out  $end
$var wire      1 (    m_clk  $end
$var wire      1 )    read_req  $end
$var wire      1 *    n_reset  $end
$var wire      1 +    spi_miso_in  $end
$var wire     120 $    data_out [119:0] $end
$var wire      3 ,    control [2:0] $end
$var wire      8 -    spi_miso_out [7:0] $end
$var wire      8 .    data_to_mosi [7:0] $end
$var wire      1 /    control_clk_miso  $end
$var wire      1 0    spi_clk  $end
$var wire      1 1    spi_cs  $end

$scope module A $end
$var wire      1 *    nrst  $end
$var wire      1 1    spi_cs  $end
$var wire      1 (    m_clk  $end
$var reg       1 2    spi_clk  $end
$var reg       4 3    counter [0:3] $end
$upscope $end


$scope module O2 $end
$var parameter 32 4    DSIZE  $end
$var wire      1 1    spi_cs  $end
$var wire      1 0    spi_clk  $end
$var wire      1 *    n_reset  $end
$var wire      1 +    spi_miso_in  $end
$var reg       1 5    control_clk_miso  $end
$var reg       8 6    spi_miso_out [7:0] $end
$var reg       1 7    spi_mosi_out  $end
$var reg       8 8    data [7:0] $end
$var reg       8 9    final_data [7:0] $end
$var reg       8 :    add_byte [7:0] $end
$var reg       3 ;    point [2:0] $end
$var reg       3 <    point_add [2:0] $end
$var reg       3 =    control [2:0] $end
$upscope $end


$scope module O1 $end
$var parameter 32 >    MEMDEPTH  $end
$var parameter 32 ?    DSIZE  $end
$var parameter 32 @    ASIZE  $end
$var wire      1 /    control_clk_miso  $end
$var wire      8 -    wdata [7:0] $end
$var wire      1 (    clk  $end
$var wire      1 )    read_req  $end
$var wire      1 *    rst  $end
$var reg       4 A    w_pointer [3:0] $end
$var reg       4 B    r_pointer [3:0] $end
$var reg       8 C    rdata [7:0] $end
$var reg       1 D    winc  $end
$var reg       1 E    rinc  $end
$var reg       1 F    spi_cs  $end
$var reg       1 G    w_full  $end
$var reg       1 H    r_empty  $end
$var reg       1 I    read_en  $end
$var reg      120 J    data_out [119:0] $end
$upscope $end

$upscope $end

$upscope $end

$enddefinitions $end
$dumpvars
0!
0"
x#
b000000000000000000000000000000000000000000000000000000000000000000000000000000000000000000000000000000000000000000000000 $
x%
0&
x'
0(
0)
0*
x+
bzzz ,
b00000000 -
bzzzzzzzz .
0/
00
01
02
b0000 3
b00000000000000000000000000001000 4
05
b00000000 6
x7
b00000000 8
b00000000 9
b11100101 :
b000 ;
b000 <
b010 =
b00000000000000000000000000011110 >
b00000000000000000000000000001000 ?
b00000000000000000000000000000100 @
b0000 A
b0000 B
b00000000 C
0D
0E
0F
0G
0H
0I
b000000000000000000000000000000000000000000000000000000000000000000000000000000000000000000000000000000000000000000000000 J
$end
#50000
1!
1(
#100000
0!
0(
#150000
1!
1(
#200000
0!
0(
#250000
1!
1(
#300000
0!
0(
#350000
1!
1(
#400000
0!
0(
#450000
1!
1(
#500000
0!
0(
#550000
1!
1(
#600000
0!
0(
#650000
1!
1(
#700000
0!
0(
#750000
1!
1(
#800000
0!
0(
#850000
1!
1(
#900000
0!
0(
#950000
1!
1(
#1000000
0!
0(
#1050000
1!
1(
#1100000
0!
0(
#1150000
1!
1(
#1200000
0!
0(
#1250000
1!
1(
#1300000
0!
0(
#1350000
1!
1(
#1400000
0!
0(
#1450000
1!
1(
#1500000
0!
0(
#1550000
1!
1(
#1600000
0!
0(
#1650000
1!
1(
#1700000
0!
0(
#1750000
1!
1(
#1800000
0!
0(
#1850000
1!
1(
#1900000
0!
0(
#1950000
1!
1(
#2000000
0!
0(
#2050000
1!
1(
#2100000
0!
0(
#2150000
1!
1(
#2200000
0!
0(
#2250000
1!
1(
#2300000
0!
0(
#2350000
1!
1(
#2400000
0!
0(
#2450000
1!
1(
#2500000
1"
1#
0!
1*
1+
0(
#2550000
1!
1(
b0001 3
1D
#2600000
0!
0(
#2650000
1!
1(
b0010 3
#2700000
0!
0(
#2750000
1!
1(
b0011 3
#2800000
0!
0(
#2850000
1!
1(
b0100 3
#2900000
0!
0(
#2950000
1!
1(
b0101 3
#3000000
0!
0(
#3050000
1!
1(
b0110 3
#3100000
0!
0(
#3150000
1!
1(
b0111 3
#3200000
0!
0(
#3250000
1!
1(
b1000 3
#3300000
0!
0(
#3350000
1!
1(
b1001 3
#3400000
0!
0(
#3450000
1!
1(
12
b0000 3
10
b011 =
17
b001 <
1%
#3500000
0!
0(
#3550000
1!
1(
b0001 3
#3600000
0!
0(
#3650000
1!
1(
b0010 3
#3700000
0!
0(
#3750000
1!
1(
b0011 3
#3800000
0!
0(
#3850000
1!
1(
b0100 3
#3900000
0!
0(
#3950000
1!
1(
b0101 3
#4000000
0!
0(
#4050000
1!
1(
b0110 3
#4100000
0!
0(
#4150000
1!
1(
b0111 3
#4200000
0!
0(
#4250000
1!
1(
b1000 3
#4300000
0!
0(
#4350000
1!
1(
b1001 3
#4400000
0!
0(
#4450000
1!
1(
02
b0000 3
00
#4500000
0#
0!
0+
0(
#4550000
1!
1(
b0001 3
#4600000
0!
0(
#4650000
1!
1(
b0010 3
#4700000
0!
0(
#4750000
1!
1(
b0011 3
#4800000
0!
0(
#4850000
1!
1(
b0100 3
#4900000
0!
0(
#4950000
1!
1(
b0101 3
#5000000
0!
0(
#5050000
1!
1(
b0110 3
#5100000
0!
0(
#5150000
1!
1(
b0111 3
#5200000
0!
0(
#5250000
1!
1(
b1000 3
#5300000
0!
0(
#5350000
1!
1(
b1001 3
#5400000
0!
0(
#5450000
1!
1(
12
b0000 3
10
b100 =
07
b010 <
0%
#5500000
0!
0(
#5550000
1!
1(
b0001 3
#5600000
0!
0(
#5650000
1!
1(
b0010 3
#5700000
0!
0(
#5750000
1!
1(
b0011 3
#5800000
0!
0(
#5850000
1!
1(
b0100 3
#5900000
0!
0(
#5950000
1!
1(
b0101 3
#6000000
0!
0(
#6050000
1!
1(
b0110 3
#6100000
0!
0(
#6150000
1!
1(
b0111 3
#6200000
0!
0(
#6250000
1!
1(
b1000 3
#6300000
0!
0(
#6350000
1!
1(
b1001 3
#6400000
0!
0(
#6450000
1!
1(
02
b0000 3
00
#6500000
0!
0(
#6550000
1!
1(
b0001 3
#6600000
0!
0(
#6650000
1!
1(
b0010 3
#6700000
0!
0(
#6750000
1!
1(
b0011 3
#6800000
0!
0(
#6850000
1!
1(
b0100 3
#6900000
0!
0(
#6950000
1!
1(
b0101 3
#7000000
0!
0(
#7050000
1!
1(
b0110 3
#7100000
0!
0(
#7150000
1!
1(
b0111 3
#7200000
0!
0(
#7250000
1!
1(
b1000 3
#7300000
0!
0(
#7350000
1!
1(
b1001 3
#7400000
0!
0(
#7450000
1!
1(
12
b0000 3
10
b101 =
17
b011 <
1%
#7500000
0!
0(
#7550000
1!
1(
b0001 3
#7600000
0!
0(
#7650000
1!
1(
b0010 3
#7700000
0!
0(
#7750000
1!
1(
b0011 3
#7800000
0!
0(
#7850000
1!
1(
b0100 3
#7900000
0!
0(
#7950000
1!
1(
b0101 3
#8000000
0!
0(
#8050000
1!
1(
b0110 3
#8100000
0!
0(
#8150000
1!
1(
b0111 3
#8200000
0!
0(
#8250000
1!
1(
b1000 3
#8300000
0!
0(
#8350000
1!
1(
b1001 3
#8400000
0!
0(
#8450000
1!
1(
02
b0000 3
00
#8500000
0!
0(
#8550000
1!
1(
b0001 3
#8600000
0!
0(
#8650000
1!
1(
b0010 3
#8700000
0!
0(
#8750000
1!
1(
b0011 3
#8800000
0!
0(
#8850000
1!
1(
b0100 3
#8900000
0!
0(
#8950000
1!
1(
b0101 3
#9000000
0!
0(
#9050000
1!
1(
b0110 3
#9100000
0!
0(
#9150000
1!
1(
b0111 3
#9200000
0!
0(
#9250000
1!
1(
b1000 3
#9300000
0!
0(
#9350000
1!
1(
b1001 3
#9400000
0!
0(
#9450000
1!
1(
12
b0000 3
10
b110 =
07
b100 <
0%
#9500000
0!
0(
#9550000
1!
1(
b0001 3
#9600000
0!
0(
#9650000
1!
1(
b0010 3
#9700000
0!
0(
#9750000
1!
1(
b0011 3
#9800000
0!
0(
#9850000
1!
1(
b0100 3
#9900000
0!
0(
#9950000
1!
1(
b0101 3
#10000000
0!
0(
#10050000
1!
1(
b0110 3
#10100000
0!
0(
#10150000
1!
1(
b0111 3
#10200000
0!
0(
#10250000
1!
1(
b1000 3
#10300000
0!
0(
#10350000
1!
1(
b1001 3
#10400000
0!
0(
#10450000
1!
1(
02
b0000 3
00
#10500000
0!
0(
#10550000
1!
1(
b0001 3
#10600000
0!
0(
#10650000
1!
1(
b0010 3
#10700000
0!
0(
#10750000
1!
1(
b0011 3
#10800000
0!
0(
#10850000
1!
1(
b0100 3
#10900000
0!
0(
#10950000
1!
1(
b0101 3
#11000000
0!
0(
#11050000
1!
1(
b0110 3
#11100000
0!
0(
#11150000
1!
1(
b0111 3
#11200000
0!
0(
#11250000
1!
1(
b1000 3
#11300000
0!
0(
#11350000
1!
1(
b1001 3
#11400000
0!
0(
#11450000
1!
1(
12
b0000 3
10
b111 =
b101 <
#11500000
0!
0(
#11550000
1!
1(
b0001 3
#11600000
0!
0(
#11650000
1!
1(
b0010 3
#11700000
0!
0(
#11750000
1!
1(
b0011 3
#11800000
0!
0(
#11850000
1!
1(
b0100 3
#11900000
0!
0(
#11950000
1!
1(
b0101 3
#12000000
0!
0(
#12050000
1!
1(
b0110 3
#12100000
0!
0(
#12150000
1!
1(
b0111 3
#12200000
0!
0(
#12250000
1!
1(
b1000 3
#12300000
0!
0(
#12350000
1!
1(
b1001 3
#12400000
0!
0(
#12450000
1!
1(
02
b0000 3
00
#12500000
0!
0(
#12550000
1!
1(
b0001 3
#12600000
0!
0(
#12650000
1!
1(
b0010 3
#12700000
0!
0(
#12750000
1!
1(
b0011 3
#12800000
0!
0(
#12850000
1!
1(
b0100 3
#12900000
0!
0(
#12950000
1!
1(
b0101 3
#13000000
0!
0(
#13050000
1!
1(
b0110 3
#13100000
0!
0(
#13150000
1!
1(
b0111 3
#13200000
0!
0(
#13250000
1!
1(
b1000 3
#13300000
0!
0(
#13350000
1!
1(
b1001 3
#13400000
0!
0(
